Workbook

Sheet Resumen
A1: PROYECCIÓN DE CAJA 2026 – 2034
A2: Unidad: miles de soles (S/000). Ejemplo: 140,028 equivale a S/ 140.028 millones. Todo se recalcula desde Supuestos, Inversiones, Headcount, Deuda y Motor Semanal.
A4: Resultados clave | C4: ='Flujo Anual'!C4 -> 2026 | D4: ='Flujo Anual'!D4 -> 2027 | E4: ='Flujo Anual'!E4 -> 2028 | F4: ='Flujo Anual'!F4 -> 2029 | G4: ='Flujo Anual'!G4 -> 2030 | H4: ='Flujo Anual'!H4 -> 2031 | I4: ='Flujo Anual'!I4 -> 2032 | J4: ='Flujo Anual'!J4 -> 2033 | K4: ='Flujo Anual'!K4 -> 2034 | L4: Total
A5: Ventas del año | C5: ='Flujo Anual'!C7 -> 140027.51 | D5: ='Flujo Anual'!D7 -> 170243.83 | E5: ='Flujo Anual'!E7 -> 199056.11 | F5: ='Flujo Anual'!F7 -> 231900.37 | G5: ='Flujo Anual'!G7 -> 269004.43 | H5: ='Flujo Anual'!H7 -> 310700.11 | I5: ='Flujo Anual'!I7 -> 354198.13 | J5: ='Flujo Anual'!J7 -> 403785.87 | ... L5: ='Flujo Anual'!L7 -> 2539232.3
A6: Total ingresos operativos | C6: ='Flujo Anual'!C13 -> 135832.09 | D6: ='Flujo Anual'!D13 -> 167690.27 | E6: ='Flujo Anual'!E13 -> 196375.92 | F6: ='Flujo Anual'!F13 -> 229024.28 | G6: ='Flujo Anual'!G13 -> 265954.05 | H6: ='Flujo Anual'!H13 -> 307507.3 | I6: ='Flujo Anual'!I13 -> 350980.96 | J6: ='Flujo Anual'!J13 -> 400522.08 | ... L6: ='Flujo Anual'!L13 -> 2510942.4
A7: Total egresos operativos | C7: ='Flujo Anual'!C23 -> 142200.85 | D7: ='Flujo Anual'!D23 -> 170708.59 | E7: ='Flujo Anual'!E23 -> 197120.67 | F7: ='Flujo Anual'!F23 -> 226509.95 | G7: ='Flujo Anual'!G23 -> 259338.44 | H7: ='Flujo Anual'!H23 -> 295434.53 | I7: ='Flujo Anual'!I23 -> 333273.36 | J7: ='Flujo Anual'!J23 -> 376121.75 | ... L7: ='Flujo Anual'!L23 -> 2425882
A8: Flujo operativo | C8: ='Flujo Anual'!C25 -> -6368.762 | D8: ='Flujo Anual'!D25 -> -3018.3271 | E8: ='Flujo Anual'!E25 -> -744.74482 | F8: ='Flujo Anual'!F25 -> 2514.3326 | G8: ='Flujo Anual'!G25 -> 6615.6132 | H8: ='Flujo Anual'!H25 -> 12072.769 | I8: ='Flujo Anual'!I25 -> 17707.596 | J8: ='Flujo Anual'!J25 -> 24400.327 | ... L8: ='Flujo Anual'!L25 -> 85060.389
A9: Inversiones | C9: ='Flujo Anual'!C29 -> 2070 | D9: ='Flujo Anual'!D29 -> 1440 | E9: ='Flujo Anual'!E29 -> 570 | F9: ='Flujo Anual'!F29 -> 0 | G9: ='Flujo Anual'!G29 -> 200 | H9: ='Flujo Anual'!H29 -> 1050 | I9: ='Flujo Anual'!I29 -> 0 | J9: ='Flujo Anual'!J29 -> 0 | ... L9: ='Flujo Anual'!L29 -> 5330
A10: Servicio de deuda | C10: ='Flujo Anual'!C40 -> 2854.3688 | D10: ='Flujo Anual'!D40 -> 4702.9933 | E10: ='Flujo Anual'!E40 -> 5088.0194 | F10: ='Flujo Anual'!F40 -> 4923.3061 | G10: ='Flujo Anual'!G40 -> 2017.5632 | H10: ='Flujo Anual'!H40 -> 2463.825 | I10: ='Flujo Anual'!I40 -> 2747.2531 | J10: ='Flujo Anual'!J40 -> 2991.1252 | ... L10: ='Flujo Anual'!L40 -> 30756.229
A11: Desembolso de préstamos y leasing | C11: ='Flujo Anual'!C32 -> 2070 | D11: ='Flujo Anual'!D32 -> 1440 | E11: ='Flujo Anual'!E32 -> 570 | F11: ='Flujo Anual'!F32 -> 0 | G11: ='Flujo Anual'!G32 -> 200 | H11: ='Flujo Anual'!H32 -> 1050 | I11: ='Flujo Anual'!I32 -> 0 | J11: ='Flujo Anual'!J32 -> 0 | ... L11: ='Flujo Anual'!L32 -> 5330
A12: Flujo neto del año | C12: ='Flujo Anual'!C43 -> -9223.1308 | D12: ='Flujo Anual'!D43 -> -7721.3205 | E12: ='Flujo Anual'!E43 -> -5832.7642 | F12: ='Flujo Anual'!F43 -> -2408.9736 | G12: ='Flujo Anual'!G43 -> 4598.05 | H12: ='Flujo Anual'!H43 -> 9608.9438 | I12: ='Flujo Anual'!I43 -> 14960.343 | J12: ='Flujo Anual'!J43 -> 21409.202 | ... L12: ='Flujo Anual'!L43 -> 54304.159
A13: Caja final | C13: ='Flujo Anual'!C47 -> -9223.1308 | D13: ='Flujo Anual'!D47 -> -16944.451 | E13: ='Flujo Anual'!E47 -> -22777.215 | F13: ='Flujo Anual'!F47 -> -25186.189 | G13: ='Flujo Anual'!G47 -> -20588.139 | H13: ='Flujo Anual'!H47 -> -10979.195 | I13: ='Flujo Anual'!I47 -> 3981.1473 | J13: ='Flujo Anual'!J47 -> 25390.349 | ... L13: ='Flujo Anual'!L47 -> 54304.159
A14: Caja mínima de un mes del año | C14: ='Flujo Anual'!C48 -> -9275.4056 | D14: ='Flujo Anual'!D48 -> -18263.212 | E14: ='Flujo Anual'!E48 -> -25394.365 | F14: ='Flujo Anual'!F48 -> -30035.422 | G14: ='Flujo Anual'!G48 -> -29115.047 | H14: ='Flujo Anual'!H48 -> -22988.756 | I14: ='Flujo Anual'!I48 -> -11360.064 | J14: ='Flujo Anual'!J48 -> 2748.4621 | ... L14: ='Flujo Anual'!L48 -> -30035.422
A33: CÓMO ESTÁ ORDENADO EL ARCHIVO
A34: Resumen | B34: Esta hoja: resultados clave, guía y puntos a revisar.
A35: Flujo Anual | B35: El flujo de caja 2026-2034, un año por columna (suma del mensual).
A36: Flujo Mensual | B36: Mismo flujo mes a mes (108 meses). Aquí ves cuándo la caja se aprieta.
A37: Supuestos | B37: TODOS los datos de entrada: ventas, compras, gastos, financiamientos, movimientos manuales.
A38: Inversiones | B38: Inversiones y alquileres nuevos por año (en S/).
A39: Headcount | B39: Personal por año; define cuánto crece la planilla.
A40: Deuda Mensual | B40: Deuda mes a mes: cuotas de bancos + tabla de amortización de cada nuevo préstamo/leasing.
A41: Deuda Bancos | B41: Cronograma de cuotas que te entregó el banco (solo datos).
A42: Motor Semanal | B42: Cálculo semanal de ventas → cobranza. No se edita salvo las ventas semanales de 2026.
A43: Arch_… | B43: Hojas antiguas que ya no alimentan el flujo (se dejan por si las necesitas).
A45: COLORES
A46: Azul | B46: dato que tú ingresas
A47: Negro | B47: fórmula de la misma hoja
A48: Verde | B48: viene de otra hoja
A49: Fondo amarillo | B49: supuesto clave: revísalo primero
A51: PUNTOS A REVISAR (supuestos míos o vacíos de tu archivo original)
A52: 1. Unidad: tomé "miles de S/" porque la deuda y las inversiones están en soles. Si tu flujo está en miles de US$, avísame.
A53: 2. Otros gastos administrativos y comerciales 2027-2034 = % de ventas de tu cuadro (Supuestos fila 56). Con Supuestos!B22 = 0 quedan en cero.
A54: 3. La tabla de deuda empieza en oct-2026: el pago de cuotas ene-sep 2026 no está en el flujo (solo los 3 pagos CP manuales).
A55: 4. El motor semanal usa siempre la mezcla contado/crédito 2026 (66%/34%) aunque Supuestos tiene una mezcla distinta por año. Afecta solo el calendario de cobro.
A56: 5. No están modelados: IGV de ventas, renta 1.5%, rebates e intereses de préstamos CP. Protestos e incobrables sí siguen tu cuadro de %.
A57: 6. Caja inicial ene-2026 = 0 (como tu flujo original). Cámbiala en Supuestos!B24.
A58: 7. Financiamiento: camiones = leasing, mejoras/racks/mobiliario = mediano plazo; los montos salen de Inversiones. El desembolso entra en el mes de la 1ª cuota (Supuestos!I35:I40).
A59: 8. Inversiones se pagan en un solo mes por año (Supuestos fila 20); alquileres nuevos se reparten en 12 meses.
A60: 9. Compras nov y dic-2034 usan ventas 2035 estimadas con +14% (Supuestos!B21), porque tu modelo termina en 2034.
A61: 10. Inversiones: "Alquiler Máquinas Lima" 2028-29 = 4,500 sin ×12 como las otras sedes; confirma si es mensual.
A62: 11. Fórmulas simples: sumas de rangos, multiplicaciones y referencias directas. La columna B del Flujo Mensual dice de dónde viene cada línea.
... A67: GLOSARIO (también verás estos textos al pasar el mouse por las celdas con triángulo rojo)
A68: TEA | B68: Tasa Efectiva Anual: lo que cuesta un préstamo en 12 meses, contando intereses sobre intereses. Es la tasa que te dice el banco.
A69: TEM | B69: Tasa Efectiva Mensual: la TEA llevada a un mes, (1+TEA)^(30/360)−1. Es el % que se cobra cada mes sobre la deuda pendiente.
A70: MP (mediano plazo) | B70: Préstamo bancario a varios años. Aquí financia mejoras de almacén, racks y mobiliario.
A71: Leasing | B71: Arrendamiento financiero: el banco compra el activo (los camiones) y tú lo pagas en cuotas; el activo queda para la empresa.
A72: Cuota | B72: Pago fijo mensual de un préstamo. Incluye una parte de capital y una parte de intereses.
A73: Capital | B73: La parte de la cuota que reduce lo que debes (el dinero prestado).
A74: Intereses | B74: El costo del dinero: la parte de la cuota que se paga al banco por prestarte.
A75: Saldo | B75: Lo que todavía debes. Sube con el desembolso y baja con el capital que pagas.
A76: Desembolso | B76: Momento en que el banco deposita el dinero del préstamo en tu caja.
A77: Letras / descuento de letras | B77: Letra = factura de venta a crédito con fecha de pago. Descontarla = cederla al banco para recibir el dinero antes, a cambio de un interés.
A78: Cobranza libre / cartera | B78: Letras o facturas a crédito que cobras tú directamente al cliente, sin pasar por el banco.
A79: Incobrables | B79: Ventas a crédito que nunca se logran cobrar. Se restan de la cobranza.
... A87: Inversión (capex) | B87: Compra de activos que duran años: mejoras, racks, mobiliario y camiones.

Sheet Flujo Anual
A1: FLUJO DE CAJA ANUAL 2026 – 2034
A2: Unidad: miles de soles (S/000). Ejemplo: 140,028 equivale a S/ 140.028 millones. Egresos en positivo (se restan); cada año suma 12 meses de Flujo Mensual.
A4: Año | C4: =Supuestos!B1 -> 2026 | D4: =Supuestos!C1 -> 2027 | E4: =Supuestos!D1 -> 2028 | F4: =Supuestos!E1 -> 2029 | G4: =Supuestos!F1 -> 2030 | H4: =Supuestos!G1 -> 2031 | I4: =Supuestos!H1 -> 2032 | J4: =Supuestos!I1 -> 2033 | K4: =Supuestos!J1 -> 2034 | L4: Total
A6: 1. INGRESOS OPERATIVOS
A7: Ventas del año (referencia, no es caja) | C7: =SUM('Flujo Mensual'!C10:N10) -> 140027.51 | D7: =SUM('Flujo Mensual'!O10:Z10) -> 170243.83 | E7: =SUM('Flujo Mensual'!AA10:AL10) -> 199056.11 | F7: =SUM('Flujo Mensual'!AM10:AX10) -> 231900.37 | G7: =SUM('Flujo Mensual'!AY10:BJ10) -> 269004.43 | H7: =SUM('Flujo Mensual'!BK10:BV10) -> 310700.11 | I7: =SUM('Flujo Mensual'!BW10:CH10) -> 354198.13 | J7: =SUM('Flujo Mensual'!CI10:CT10) -> 403785.87 | K7: =SUM('Flujo Mensual'!CU10:DF10) -> 460315.89 | L7: =SUM(C7:K7) -> 2539232.3
A8: Crecimiento de ventas | D8: =D7/C7-1 -> 0.21578844 | E8: =E7/D7-1 -> 0.16924125 | F8: =F7/E7-1 -> 0.165 | G8: =G7/F7-1 -> 0.16 | H8: =H7/G7-1 -> 0.155 | I8: =I7/H7-1 -> 0.14 | J8: =J7/I7-1 -> 0.14 | K8: =K7/J7-1 -> 0.14
A9: Cobro de ventas al contado | C9: =SUM('Flujo Mensual'!C11:N11) -> 87876.291 | D9: =SUM('Flujo Mensual'!O11:Z11) -> 112233.23 | E9: =SUM('Flujo Mensual'!AA11:AL11) -> 131324.36 | F9: =SUM('Flujo Mensual'!AM11:AX11) -> 152994.42 | G9: =SUM('Flujo Mensual'!AY11:BJ11) -> 177475.35 | H9: =SUM('Flujo Mensual'!BK11:BV11) -> 204986.14 | I9: =SUM('Flujo Mensual'!BW11:CH11) -> 233691.54 | J9: =SUM('Flujo Mensual'!CI11:CT11) -> 266408.36 | K9: =SUM('Flujo Mensual'!CU11:DF11) -> 303705.53 | L9: =SUM(C9:K9) -> 1670695.2
A10: Cobro por descuento de letras | C10: =SUM('Flujo Mensual'!C12:N12) -> 23670.8 | D10: =SUM('Flujo Mensual'!O12:Z12) -> 26616.342 | E10: =SUM('Flujo Mensual'!AA12:AL12) -> 31090.767 | F10: =SUM('Flujo Mensual'!AM12:AX12) -> 36221.967 | G10: =SUM('Flujo Mensual'!AY12:BJ12) -> 42018.914 | H10: =SUM('Flujo Mensual'!BK12:BV12) -> 48533.513 | I10: =SUM('Flujo Mensual'!BW12:CH12) -> 55334.01 | J10: =SUM('Flujo Mensual'!CI12:CT12) -> 63080.771 | K10: =SUM('Flujo Mensual'!CU12:DF12) -> 71912.079 | L10: =SUM(C10:K10) -> 398479.16
A11: Cobranza libre / cartera | C11: =SUM('Flujo Mensual'!C13:N13) -> 26105.359 | D11: =SUM('Flujo Mensual'!O13:Z13) -> 30883.62 | E11: =SUM('Flujo Mensual'!AA13:AL13) -> 36150.418 | F11: =SUM('Flujo Mensual'!AM13:AX13) -> 42126.893 | G11: =SUM('Flujo Mensual'!AY13:BJ13) -> 48880.832 | H11: =SUM('Flujo Mensual'!BK13:BV13) -> 56473.248 | I11: =SUM('Flujo Mensual'!BW13:CH13) -> 64434.79 | J11: =SUM('Flujo Mensual'!CI13:CT13) -> 73455.66 | K11: =SUM('Flujo Mensual'!CU13:DF13) -> 83739.452 | L11: =SUM(C11:K11) -> 462250.27
A12: (−) Incobrables | C12: =SUM('Flujo Mensual'!C14:N14) -> -1820.3577 | D12: =SUM('Flujo Mensual'!O14:Z14) -> -2042.926 | E12: =SUM('Flujo Mensual'!AA14:AL14) -> -2189.6172 | F12: =SUM('Flujo Mensual'!AM14:AX14) -> -2319.0037 | G12: =SUM('Flujo Mensual'!AY14:BJ14) -> -2421.0399 | H12: =SUM('Flujo Mensual'!BK14:BV14) -> -2485.6009 | I12: =SUM('Flujo Mensual'!BW14:CH14) -> -2479.3869 | J12: =SUM('Flujo Mensual'!CI14:CT14) -> -2422.7152 | K12: =SUM('Flujo Mensual'!CU14:DF14) -> -2301.5795 | L12: =SUM(C12:K12) -> -20482.227
A13: TOTAL INGRESOS OPERATIVOS | C13: =SUM('Flujo Mensual'!C15:N15) -> 135832.09 | D13: =SUM('Flujo Mensual'!O15:Z15) -> 167690.27 | E13: =SUM('Flujo Mensual'!AA15:AL15) -> 196375.92 | F13: =SUM('Flujo Mensual'!AM15:AX15) -> 229024.28 | G13: =SUM('Flujo Mensual'!AY15:BJ15) -> 265954.05 | H13: =SUM('Flujo Mensual'!BK15:BV15) -> 307507.3 | I13: =SUM('Flujo Mensual'!BW15:CH15) -> 350980.96 | J13: =SUM('Flujo Mensual'!CI15:CT15) -> 400522.08 | K13: =SUM('Flujo Mensual'!CU15:DF15) -> 457055.48 | L13: =SUM(C13:K13) -> 2510942.4
A15: 2. EGRESOS OPERATIVOS
A16: Compras de mercadería | C16: =SUM('Flujo Mensual'!C18:N18) -> 124789.37 | D16: =SUM('Flujo Mensual'!O18:Z18) -> 150392.29 | E16: =SUM('Flujo Mensual'!AA18:AL18) -> 174155.78 | F16: =SUM('Flujo Mensual'!AM18:AX18) -> 200815.17 | G16: =SUM('Flujo Mensual'!AY18:BJ18) -> 230668.73 | H16: =SUM('Flujo Mensual'!BK18:BV18) -> 264023.06 | I16: =SUM('Flujo Mensual'!BW18:CH18) -> 298975.42 | J16: =SUM('Flujo Mensual'!CI18:CT18) -> 338539.93 | K16: =SUM('Flujo Mensual'!CU18:DF18) -> 383800.08 | L16: =SUM(C16:K16) -> 2166159.8
A17: Planilla administrativa | C17: =SUM('Flujo Mensual'!C19:N19) -> 2008.7878 | D17: =SUM('Flujo Mensual'!O19:Z19) -> 2371.6035 | E17: =SUM('Flujo Mensual'!AA19:AL19) -> 2574.8838 | F17: =SUM('Flujo Mensual'!AM19:AX19) -> 2642.6439 | G17: =SUM('Flujo Mensual'!AY19:BJ19) -> 2845.9242 | H17: =SUM('Flujo Mensual'!BK19:BV19) -> 2913.6843 | I17: =SUM('Flujo Mensual'!BW19:CH19) -> 3184.7247 | J17: =SUM('Flujo Mensual'!CI19:CT19) -> 3388.005 | K17: =SUM('Flujo Mensual'!CU19:DF19) -> 3523.5252 | L17: =SUM(C17:K17) -> 25453.782
A18: Otros gastos administrativos | C18: =SUM('Flujo Mensual'!C20:N20) -> 2979.6605 | D18: =SUM('Flujo Mensual'!O20:Z20) -> 3404.8766 | E18: =SUM('Flujo Mensual'!AA20:AL20) -> 3583.01 | F18: =SUM('Flujo Mensual'!AM20:AX20) -> 4174.2066 | G18: =SUM('Flujo Mensual'!AY20:BJ20) -> 4842.0797 | H18: =SUM('Flujo Mensual'!BK20:BV20) -> 5592.6021 | I18: =SUM('Flujo Mensual'!BW20:CH20) -> 6021.3682 | J18: =SUM('Flujo Mensual'!CI20:CT20) -> 6864.3598 | K18: =SUM('Flujo Mensual'!CU20:DF20) -> 7825.3701 | L18: =SUM(C18:K18) -> 45287.534
A19: Planilla comercial | C19: =SUM('Flujo Mensual'!C21:N21) -> 5264.2599 | D19: =SUM('Flujo Mensual'!O21:Z21) -> 6089.8718 | E19: =SUM('Flujo Mensual'!AA21:AL21) -> 6983.7979 | F19: =SUM('Flujo Mensual'!AM21:AX21) -> 7710.1129 | G19: =SUM('Flujo Mensual'!AY21:BJ21) -> 8324.6871 | H19: =SUM('Flujo Mensual'!BK21:BV21) -> 8939.2613 | I19: =SUM('Flujo Mensual'!BW21:CH21) -> 9609.7059 | J19: =SUM('Flujo Mensual'!CI21:CT21) -> 10168.41 | K19: =SUM('Flujo Mensual'!CU21:DF21) -> 11006.465 | L19: =SUM(C19:K19) -> 74096.572
A20: Otros gastos comerciales | C20: =SUM('Flujo Mensual'!C22:N22) -> 6598.6694 | D20: =SUM('Flujo Mensual'!O22:Z22) -> 7660.9724 | E20: =SUM('Flujo Mensual'!AA22:AL22) -> 8758.4689 | F20: =SUM('Flujo Mensual'!AM22:AX22) -> 9971.7159 | G20: =SUM('Flujo Mensual'!AY22:BJ22) -> 11029.182 | H20: =SUM('Flujo Mensual'!BK22:BV22) -> 12117.304 | I20: =SUM('Flujo Mensual'!BW22:CH22) -> 13459.529 | J20: =SUM('Flujo Mensual'!CI22:CT22) -> 14940.077 | K20: =SUM('Flujo Mensual'!CU22:DF22) -> 16571.372 | L20: =SUM(C20:K20) -> 101107.29
A21: Protestos | C21: =SUM('Flujo Mensual'!C23:N23) -> 560.11005 | D21: =SUM('Flujo Mensual'!O23:Z23) -> 680.97533 | E21: =SUM('Flujo Mensual'!AA23:AL23) -> 796.22444 | F21: =SUM('Flujo Mensual'!AM23:AX23) -> 927.60148 | G21: =SUM('Flujo Mensual'!AY23:BJ23) -> 1076.0177 | H21: =SUM('Flujo Mensual'!BK23:BV23) -> 1242.8005 | I21: =SUM('Flujo Mensual'!BW23:CH23) -> 1416.7925 | J21: =SUM('Flujo Mensual'!CI23:CT23) -> 1615.1435 | K21: =SUM('Flujo Mensual'!CU23:DF23) -> 1841.2636 | L21: =SUM(C21:K21) -> 10156.929
A22: Alquileres nuevas sedes y máquinas | C22: =SUM('Flujo Mensual'!C24:N24) -> 0 | D22: =SUM('Flujo Mensual'!O24:Z24) -> 108 | E22: =SUM('Flujo Mensual'!AA24:AL24) -> 268.5 | F22: =SUM('Flujo Mensual'!AM24:AX24) -> 268.5 | G22: =SUM('Flujo Mensual'!AY24:BJ24) -> 551.82 | H22: =SUM('Flujo Mensual'!BK24:BV24) -> 605.82 | I22: =SUM('Flujo Mensual'!BW24:CH24) -> 605.82 | J22: =SUM('Flujo Mensual'!CI24:CT24) -> 605.82 | K22: =SUM('Flujo Mensual'!CU24:DF24) -> 605.82 | L22: =SUM(C22:K22) -> 3620.1
A23: TOTAL EGRESOS OPERATIVOS | C23: =SUM('Flujo Mensual'!C25:N25) -> 142200.85 | D23: =SUM('Flujo Mensual'!O25:Z25) -> 170708.59 | E23: =SUM('Flujo Mensual'!AA25:AL25) -> 197120.67 | F23: =SUM('Flujo Mensual'!AM25:AX25) -> 226509.95 | G23: =SUM('Flujo Mensual'!AY25:BJ25) -> 259338.44 | H23: =SUM('Flujo Mensual'!BK25:BV25) -> 295434.53 | I23: =SUM('Flujo Mensual'!BW25:CH25) -> 333273.36 | J23: =SUM('Flujo Mensual'!CI25:CT25) -> 376121.75 | K23: =SUM('Flujo Mensual'!CU25:DF25) -> 425173.9 | L23: =SUM(C23:K23) -> 2425882
A25: 3. FLUJO OPERATIVO (1 − 2) | C25: =SUM('Flujo Mensual'!C27:N27) -> -6368.762 | D25: =SUM('Flujo Mensual'!O27:Z27) -> -3018.3271 | E25: =SUM('Flujo Mensual'!AA27:AL27) -> -744.74482 | F25: =SUM('Flujo Mensual'!AM27:AX27) -> 2514.3326 | G25: =SUM('Flujo Mensual'!AY27:BJ27) -> 6615.6132 | H25: =SUM('Flujo Mensual'!BK27:BV27) -> 12072.769 | I25: =SUM('Flujo Mensual'!BW27:CH27) -> 17707.596 | J25: =SUM('Flujo Mensual'!CI27:CT27) -> 24400.327 | K25: =SUM('Flujo Mensual'!CU27:DF27) -> 31881.585 | L25: =SUM(C25:K25) -> 85060.389
A26: % sobre ingresos | C26: =IF(C13=0,0,C25/C13) -> -0.04688702 | D26: =IF(D13=0,0,D25/D13) -> -0.017999417 | E26: =IF(E13=0,0,E25/E13) -> -0.0037924446 | F26: =IF(F13=0,0,F25/F13) -> 0.010978454 | G26: =IF(G13=0,0,G25/G13) -> 0.024875023 | H26: =IF(H13=0,0,H25/H13) -> 0.039260105 | I26: =IF(I13=0,0,I25/I13) -> 0.050451728 | J26: =IF(J13=0,0,J25/J13) -> 0.060921304 | ... L26: =IF(L13=0,0,L25/L13) -> 0.033875882
A28: 4. INVERSIONES
A29: Inversión en activos | C29: =SUM('Flujo Mensual'!C31:N31) -> 2070 | D29: =SUM('Flujo Mensual'!O31:Z31) -> 1440 | E29: =SUM('Flujo Mensual'!AA31:AL31) -> 570 | F29: =SUM('Flujo Mensual'!AM31:AX31) -> 0 | G29: =SUM('Flujo Mensual'!AY31:BJ31) -> 200 | H29: =SUM('Flujo Mensual'!BK31:BV31) -> 1050 | I29: =SUM('Flujo Mensual'!BW31:CH31) -> 0 | J29: =SUM('Flujo Mensual'!CI31:CT31) -> 0 | K29: =SUM('Flujo Mensual'!CU31:DF31) -> 0 | L29: =SUM(C29:K29) -> 5330
A31: 5. FINANCIAMIENTO
A32: (+) Desembolso de préstamos y leasing | C32: =SUM('Flujo Mensual'!C34:N34) -> 2070 | D32: =SUM('Flujo Mensual'!O34:Z34) -> 1440 | E32: =SUM('Flujo Mensual'!AA34:AL34) -> 570 | F32: =SUM('Flujo Mensual'!AM34:AX34) -> 0 | G32: =SUM('Flujo Mensual'!AY34:BJ34) -> 200 | H32: =SUM('Flujo Mensual'!BK34:BV34) -> 1050 | I32: =SUM('Flujo Mensual'!BW34:CH34) -> 0 | J32: =SUM('Flujo Mensual'!CI34:CT34) -> 0 | K32: =SUM('Flujo Mensual'!CU34:DF34) -> 0 | L32: =SUM(C32:K32) -> 5330
A33: (−) Principal mediano plazo | C33: =SUM('Flujo Mensual'!C35:N35) -> 475.45054 | D33: =SUM('Flujo Mensual'!O35:Z35) -> 2563.3155 | E33: =SUM('Flujo Mensual'!AA35:AL35) -> 2962.7569 | F33: =SUM('Flujo Mensual'!AM35:AX35) -> 2967.5417 | G33: =SUM('Flujo Mensual'!AY35:BJ35) -> 265.20047 | H33: =SUM('Flujo Mensual'!BK35:BV35) -> 66.565056 | I33: =SUM('Flujo Mensual'!BW35:CH35) -> 71.22461 | J33: =SUM('Flujo Mensual'!CI35:CT35) -> 0 | K33: =SUM('Flujo Mensual'!CU35:DF35) -> 0 | L33: =SUM(C33:K33) -> 9372.0547
A34: (−) Principal leasing | C34: =SUM('Flujo Mensual'!C36:N36) -> 66.548402 | D34: =SUM('Flujo Mensual'!O36:Z36) -> 387.27179 | E34: =SUM('Flujo Mensual'!AA36:AL36) -> 404.00917 | F34: =SUM('Flujo Mensual'!AM36:AX36) -> 313.35128 | G34: =SUM('Flujo Mensual'!AY36:BJ36) -> 0 | H34: =SUM('Flujo Mensual'!BK36:BV36) -> 326.60425 | I34: =SUM('Flujo Mensual'!BW36:CH36) -> 349.46655 | J34: =SUM('Flujo Mensual'!CI36:CT36) -> 373.9292 | K34: =SUM('Flujo Mensual'!CU36:DF36) -> 0 | L34: =SUM(C34:K34) -> 2221.1806
A35: (−) Intereses mediano plazo | C35: =SUM('Flujo Mensual'!C37:N37) -> 146.41171 | D35: =SUM('Flujo Mensual'!O37:Z37) -> 581.57036 | E35: =SUM('Flujo Mensual'!AA37:AL37) -> 392.65653 | F35: =SUM('Flujo Mensual'!AM37:AX37) -> 138.72505 | G35: =SUM('Flujo Mensual'!AY37:BJ37) -> 19.196368 | H35: =SUM('Flujo Mensual'!BK37:BV37) -> 7.3042527 | I35: =SUM('Flujo Mensual'!BW37:CH37) -> 2.6446988 | J35: =SUM('Flujo Mensual'!CI37:CT37) -> 0 | K35: =SUM('Flujo Mensual'!CU37:DF37) -> 0 | L35: =SUM(C35:K35) -> 1288.509
A36: (−) Intereses leasing | C36: =SUM('Flujo Mensual'!C38:N38) -> 13.753993 | D36: =SUM('Flujo Mensual'!O38:Z38) -> 63.209087 | E36: =SUM('Flujo Mensual'!AA38:AL38) -> 36.027265 | F36: =SUM('Flujo Mensual'!AM38:AX38) -> 9.8269438 | G36: =SUM('Flujo Mensual'!AY38:BJ38) -> 0 | H36: =SUM('Flujo Mensual'!BK38:BV38) -> 61.209624 | I36: =SUM('Flujo Mensual'!BW38:CH38) -> 38.347327 | J36: =SUM('Flujo Mensual'!CI38:CT38) -> 13.884669 | K36: =SUM('Flujo Mensual'!CU38:DF38) -> 0 | L36: =SUM(C36:K36) -> 236.25891
A37: (−) IGV y otros cargos de cuotas | C37: =SUM('Flujo Mensual'!C39:N39) -> 2.82003 | D37: =SUM('Flujo Mensual'!O39:Z39) -> 11.28012 | E37: =SUM('Flujo Mensual'!AA39:AL39) -> 9.40011 | F37: =SUM('Flujo Mensual'!AM39:AX39) -> 0 | G37: =SUM('Flujo Mensual'!AY39:BJ39) -> 0 | H37: =SUM('Flujo Mensual'!BK39:BV39) -> 0 | I37: =SUM('Flujo Mensual'!BW39:CH39) -> 0 | J37: =SUM('Flujo Mensual'!CI39:CT39) -> 0 | K37: =SUM('Flujo Mensual'!CU39:DF39) -> 0 | L37: =SUM(C37:K37) -> 23.50026
A38: (−) Gasto financiero por descuento de letras | C38: =SUM('Flujo Mensual'!C40:N40) -> 949.38412 | D38: =SUM('Flujo Mensual'!O40:Z40) -> 1096.3465 | E38: =SUM('Flujo Mensual'!AA40:AL40) -> 1283.1694 | F38: =SUM('Flujo Mensual'!AM40:AX40) -> 1493.8612 | G38: =SUM('Flujo Mensual'!AY40:BJ40) -> 1733.1663 | H38: =SUM('Flujo Mensual'!BK40:BV40) -> 2002.1418 | I38: =SUM('Flujo Mensual'!BW40:CH40) -> 2285.5699 | J38: =SUM('Flujo Mensual'!CI40:CT40) -> 2603.3114 | K38: =SUM('Flujo Mensual'!CU40:DF40) -> 2967.7749 | L38: =SUM(C38:K38) -> 16414.726
A39: (−) Pagos préstamos CP y otros manuales | C39: =SUM('Flujo Mensual'!C41:N41) -> 1200 | D39: =SUM('Flujo Mensual'!O41:Z41) -> 0 | E39: =SUM('Flujo Mensual'!AA41:AL41) -> 0 | F39: =SUM('Flujo Mensual'!AM41:AX41) -> 0 | G39: =SUM('Flujo Mensual'!AY41:BJ41) -> 0 | H39: =SUM('Flujo Mensual'!BK41:BV41) -> 0 | I39: =SUM('Flujo Mensual'!BW41:CH41) -> 0 | J39: =SUM('Flujo Mensual'!CI41:CT41) -> 0 | K39: =SUM('Flujo Mensual'!CU41:DF41) -> 0 | L39: =SUM(C39:K39) -> 1200
A40: SERVICIO DE DEUDA | C40: =SUM('Flujo Mensual'!C42:N42) -> 2854.3688 | D40: =SUM('Flujo Mensual'!O42:Z42) -> 4702.9933 | E40: =SUM('Flujo Mensual'!AA42:AL42) -> 5088.0194 | F40: =SUM('Flujo Mensual'!AM42:AX42) -> 4923.3061 | G40: =SUM('Flujo Mensual'!AY42:BJ42) -> 2017.5632 | H40: =SUM('Flujo Mensual'!BK42:BV42) -> 2463.825 | I40: =SUM('Flujo Mensual'!BW42:CH42) -> 2747.2531 | J40: =SUM('Flujo Mensual'!CI42:CT42) -> 2991.1252 | K40: =SUM('Flujo Mensual'!CU42:DF42) -> 2967.7749 | L40: =SUM(C40:K40) -> 30756.229
A41: FINANCIAMIENTO NETO (desembolsos − servicio) | C41: =SUM('Flujo Mensual'!C43:N43) -> -784.3688 | D41: =SUM('Flujo Mensual'!O43:Z43) -> -3262.9933 | E41: =SUM('Flujo Mensual'!AA43:AL43) -> -4518.0194 | F41: =SUM('Flujo Mensual'!AM43:AX43) -> -4923.3061 | G41: =SUM('Flujo Mensual'!AY43:BJ43) -> -1817.5632 | H41: =SUM('Flujo Mensual'!BK43:BV43) -> -1413.825 | I41: =SUM('Flujo Mensual'!BW43:CH43) -> -2747.2531 | J41: =SUM('Flujo Mensual'!CI43:CT43) -> -2991.1252 | K41: =SUM('Flujo Mensual'!CU43:DF43) -> -2967.7749 | L41: =SUM(C41:K41) -> -25426.229
A43: 6. FLUJO NETO DEL AÑO (3 − 4 + 5) | C43: =SUM('Flujo Mensual'!C45:N45) -> -9223.1308 | D43: =SUM('Flujo Mensual'!O45:Z45) -> -7721.3205 | E43: =SUM('Flujo Mensual'!AA45:AL45) -> -5832.7642 | F43: =SUM('Flujo Mensual'!AM45:AX45) -> -2408.9736 | G43: =SUM('Flujo Mensual'!AY45:BJ45) -> 4598.05 | H43: =SUM('Flujo Mensual'!BK45:BV45) -> 9608.9438 | I43: =SUM('Flujo Mensual'!BW45:CH45) -> 14960.343 | J43: =SUM('Flujo Mensual'!CI45:CT45) -> 21409.202 | K43: =SUM('Flujo Mensual'!CU45:DF45) -> 28913.81 | L43: =SUM(C43:K43) -> 54304.159
A45: 7. CAJA
A46: Caja inicial | C46: ='Flujo Mensual'!C48 -> 0 | D46: ='Flujo Mensual'!O48 -> -9223.1308 | E46: ='Flujo Mensual'!AA48 -> -16944.451 | F46: ='Flujo Mensual'!AM48 -> -22777.215 | G46: ='Flujo Mensual'!AY48 -> -25186.189 | H46: ='Flujo Mensual'!BK48 -> -20588.139 | I46: ='Flujo Mensual'!BW48 -> -10979.195 | J46: ='Flujo Mensual'!CI48 -> 3981.1473 | K46: ='Flujo Mensual'!CU48 -> 25390.349 | L46: =C46 -> 0
A47: CAJA FINAL | C47: ='Flujo Mensual'!N49 -> -9223.1308 | D47: ='Flujo Mensual'!Z49 -> -16944.451 | E47: ='Flujo Mensual'!AL49 -> -22777.215 | F47: ='Flujo Mensual'!AX49 -> -25186.189 | G47: ='Flujo Mensual'!BJ49 -> -20588.139 | H47: ='Flujo Mensual'!BV49 -> -10979.195 | I47: ='Flujo Mensual'!CH49 -> 3981.1473 | J47: ='Flujo Mensual'!CT49 -> 25390.349 | K47: ='Flujo Mensual'!DF49 -> 54304.159 | L47: =K47 -> 54304.159
A48: Caja mínima de un mes dentro del año | C48: =MIN('Flujo Mensual'!C49:N49) -> -9275.4056 | D48: =MIN('Flujo Mensual'!O49:Z49) -> -18263.212 | E48: =MIN('Flujo Mensual'!AA49:AL49) -> -25394.365 | F48: =MIN('Flujo Mensual'!AM49:AX49) -> -30035.422 | G48: =MIN('Flujo Mensual'!AY49:BJ49) -> -29115.047 | H48: =MIN('Flujo Mensual'!BK49:BV49) -> -22988.756 | I48: =MIN('Flujo Mensual'!BW49:CH49) -> -11360.064 | J48: =MIN('Flujo Mensual'!CI49:CT49) -> 2748.4621 | K48: =MIN('Flujo Mensual'!CU49:DF49) -> 24783.991 | L48: =MIN(C48:K48) -> -30035.422
A50: COBERTURAS
A51: Flujo operativo / Servicio de deuda | C51: =IF(C40=0,0,C25/C40) -> -2.2312331 | D51: =IF(D40=0,0,D25/D40) -> -0.64178852 | E51: =IF(E40=0,0,E25/E40) -> -0.14637224 | F51: =IF(F40=0,0,F25/F40) -> 0.51070003 | G51: =IF(G40=0,0,G25/G40) -> 3.2790117 | H51: =IF(H40=0,0,H25/H40) -> 4.9000107 | I51: =IF(I40=0,0,I25/I40) -> 6.4455639 | J51: =IF(J40=0,0,J25/J40) -> 8.1575746 | ... L51: =IF(L40=0,0,L25/L40) -> 2.7656313
A52: Caja final / Servicio de deuda | C52: =IF(C40=0,0,C47/C40) -> -3.2312331 | D52: =IF(D40=0,0,D47/D40) -> -3.6029078 | E52: =IF(E40=0,0,E47/E40) -> -4.4766369 | F52: =IF(F40=0,0,F47/F40) -> -5.1157065 | G52: =IF(G40=0,0,G47/G40) -> -10.204458 | H52: =IF(H40=0,0,H47/H40) -> -4.4561587 | I52: =IF(I40=0,0,I47/I40) -> 1.4491374 | J52: =IF(J40=0,0,J47/J40) -> 8.4885611 | K52: =IF(K40=0,0,K47/K40) -> 18.297937
A54: VERIFICACIONES (deben dar 0)
A55: Caja final = caja inicial + flujo neto | C55: =ROUND(C47-(C46+C43),4) -> 0 | D55: =ROUND(D47-(D46+D43),4) -> 0 | E55: =ROUND(E47-(E46+E43),4) -> 0 | F55: =ROUND(F47-(F46+F43),4) -> 0 | G55: =ROUND(G47-(G46+G43),4) -> 0 | H55: =ROUND(H47-(H46+H43),4) -> 0 | I55: =ROUND(I47-(I46+I43),4) -> 0 | J55: =ROUND(J47-(J46+J43),4) -> 0 | K55: =ROUND(K47-(K46+K43),4) -> 0
A56: Ingreso efectivo vs motor semanal | C56: =ROUND(C13-SUM('Motor Semanal'!B17:BH17),4) -> 0 | D56: =ROUND(D13-SUM('Motor Semanal'!BI17:DO17),4) -> 0 | E56: =ROUND(E13-SUM('Motor Semanal'!DP17:FW17),4) -> 0 | F56: =ROUND(F13-SUM('Motor Semanal'!FX17:ID17),4) -> 0 | G56: =ROUND(G13-SUM('Motor Semanal'!IE17:KK17),4) -> 0 | H56: =ROUND(H13-SUM('Motor Semanal'!KL17:MR17),4) -> 0 | I56: =ROUND(I13-SUM('Motor Semanal'!MS17:OZ17),4) -> 0 | J56: =ROUND(J13-SUM('Motor Semanal'!PA17:RG17),4) -> 0 | K56: =ROUND(K13-SUM('Motor Semanal'!RH17:TN17),4) -> 0

Sheet Flujo Mensual
A1: FLUJO DE CAJA MENSUAL 2026 – 2034
A2: Unidad: miles de soles (S/000). Ejemplo: 11,669 equivale a S/ 11.669 millones. Egresos en positivo (se restan); los cambios se realizan en las hojas de datos.
DG3: Ext. 2035 (solo para compras nov-dic 2034)
A4: Mes | B4: De dónde viene | C4: =DATE(Supuestos!$B$1,1,1) -> 46023 | D4: =EDATE(C4,1) -> 46054 | E4: =EDATE(D4,1) -> 46082 | F4: =EDATE(E4,1) -> 46113 | G4: =EDATE(F4,1) -> 46143 | H4: =EDATE(G4,1) -> 46174 | I4: =EDATE(H4,1) -> 46204 | J4: =EDATE(I4,1) -> 46235 | K4: =EDATE(J4,1) -> 46266 | ... DH4: =EDATE(DG4,1) -> 49341
A5: Año | C5: =YEAR(C4) -> 2026 | D5: =YEAR(D4) -> 2026 | E5: =YEAR(E4) -> 2026 | F5: =YEAR(F4) -> 2026 | G5: =YEAR(G4) -> 2026 | H5: =YEAR(H4) -> 2026 | I5: =YEAR(I4) -> 2026 | J5: =YEAR(J4) -> 2026 | ... DH5: =YEAR(DH4) -> 2035
A6: N° mes | C6: =MONTH(C4) -> 1 | D6: =MONTH(D4) -> 2 | E6: =MONTH(E4) -> 3 | F6: =MONTH(F4) -> 4 | G6: =MONTH(G4) -> 5 | H6: =MONTH(H4) -> 6 | I6: =MONTH(I4) -> 7 | J6: =MONTH(J4) -> 8 | ... DH6: =MONTH(DH4) -> 2
A7: Días del mes | C7: =DAY(EOMONTH(C4,0)) -> 31 | D7: =DAY(EOMONTH(D4,0)) -> 28 | E7: =DAY(EOMONTH(E4,0)) -> 31 | F7: =DAY(EOMONTH(F4,0)) -> 30 | G7: =DAY(EOMONTH(G4,0)) -> 31 | H7: =DAY(EOMONTH(H4,0)) -> 30 | I7: =DAY(EOMONTH(I4,0)) -> 31 | J7: =DAY(EOMONTH(J4,0)) -> 31 | ... DH7: =DAY(EOMONTH(DH4,0)) -> 28
A9: 1. INGRESOS OPERATIVOS
A10: Ventas del mes (referencia, no es caja) | B10: Motor Semanal fila 9 | C10: =SUM('Motor Semanal'!B9:F9) -> 12462.316 | D10: =SUM('Motor Semanal'!G9:J9) -> 10499.207 | E10: =SUM('Motor Semanal'!K9:O9) -> 11314.833 | F10: =SUM('Motor Semanal'!P9:T9) -> 10945.825 | G10: =SUM('Motor Semanal'!U9:Y9) -> 12393.374 | H10: =SUM('Motor Semanal'!Z9:AD9) -> 9631.5746 | I10: =SUM('Motor Semanal'!AE9:AI9) -> 12526.86 | J10: =SUM('Motor Semanal'!AJ9:AN9) -> 13904.901 | K10: =SUM('Motor Semanal'!AO9:AS9) -> 13278.453 | L10: =SUM('Motor Semanal'!AT9:AX9) -> 13619.536 | M10: =SUM('Motor Semanal'!AY9:BC9) -> 12809.204 | N10: =SUM('Motor Semanal'!BD9:BH9) -> 6641.4291 | O10: =SUM('Motor Semanal'!BI9:BM9) -> 15141.714 | P10: =SUM('Motor Semanal'!BN9:BQ9) -> 12756.537 | Q10: =SUM('Motor Semanal'!BR9:BV9) -> 13747.522 | R10: =SUM('Motor Semanal'!BW9:CA9) -> 13299.178 | S10: =SUM('Motor Semanal'!CB9:CF9) -> 15057.95 | T10: =SUM('Motor Semanal'!CG9:CK9) -> 11702.363 | U10: =SUM('Motor Semanal'!CL9:CP9) -> 15330.538 | V10: =SUM('Motor Semanal'!CQ9:CU9) -> 16894.455 | W10: =SUM('Motor Semanal'!CV9:CZ9) -> 16133.321 | X10: =SUM('Motor Semanal'!DA9:DE9) -> 16547.737 | Y10: =SUM('Motor Semanal'!DF9:DJ9) -> 15563.183 | Z10: =SUM('Motor Semanal'!DK9:DO9) -> 8069.3363 | AA10: =SUM('Motor Semanal'!DP9:DT9) -> 17715.805 | AB10: =SUM('Motor Semanal'!DU9:DY9) -> 14925.148 | AC10: =SUM('Motor Semanal'!DZ9:ED9) -> 16084.6 | AD10: =SUM('Motor Semanal'!EE9:EI9) -> 15560.038 | AE10: =SUM('Motor Semanal'!EJ9:EN9) -> 17617.801 | AF10: =SUM('Motor Semanal'!EO9:ES9) -> 13691.765 | AG10: =SUM('Motor Semanal'!ET9:EX9) -> 17807.557 | AH10: =SUM('Motor Semanal'!EY9:FC9) -> 19766.512 | AI10: =SUM('Motor Semanal'!FD9:FH9) -> 18875.985 | AJ10: =SUM('Motor Semanal'!FI9:FM9) -> 19360.852 | AK10: =SUM('Motor Semanal'!FN9:FR9) -> 18208.924 | AL10: =SUM('Motor Semanal'!FS9:FW9) -> 9441.1235 | AM10: =SUM('Motor Semanal'!FX9:GB9) -> 20638.913 | AN10: =SUM('Motor Semanal'!GC9:GF9) -> 17387.797 | AO10: =SUM('Motor Semanal'!GG9:GK9) -> 18738.559 | AP10: =SUM('Motor Semanal'!GL9:GP9) -> 18127.444 | AQ10: =SUM('Motor Semanal'!GQ9:GU9) -> 20524.738 | AR10: =SUM('Motor Semanal'!GV9:GZ9) -> 15950.906 | AS10: =SUM('Motor Semanal'!HA9:HE9) -> 20745.804 | AT10: =SUM('Motor Semanal'!HF9:HJ9) -> 23027.986 | AU10: =SUM('Motor Semanal'!HK9:HO9) -> 21990.523 | AV10: =SUM('Motor Semanal'!HP9:HT9) -> 22555.392 | AW10: =SUM('Motor Semanal'!HU9:HY9) -> 21213.396 | AX10: =SUM('Motor Semanal'!HZ9:ID9) -> 10998.909 | AY10: =SUM('Motor Semanal'!IE9:II9) -> 23941.139 | AZ10: =SUM('Motor Semanal'!IJ9:IM9) -> 20169.845 | BA10: =SUM('Motor Semanal'!IN9:IR9) -> 21736.729 | BB10: =SUM('Motor Semanal'!IS9:IW9) -> 21027.835 | BC10: =SUM('Motor Semanal'!IX9:JB9) -> 23808.696 | BD10: =SUM('Motor Semanal'!JC9:JG9) -> 18503.051 | BE10: =SUM('Motor Semanal'!JH9:JL9) -> 24065.133 | BF10: =SUM('Motor Semanal'!JM9:JQ9) -> 26712.464 | BG10: =SUM('Motor Semanal'!JR9:JV9) -> 25509.007 | BH10: =SUM('Motor Semanal'!JW9:KA9) -> 26164.255 | BI10: =SUM('Motor Semanal'!KB9:KF9) -> 24607.54 | BJ10: =SUM('Motor Semanal'!KG9:KK9) -> 12758.734 | BK10: =SUM('Motor Semanal'!KL9:KP9) -> 27652.016 | BL10: =SUM('Motor Semanal'!KQ9:KT9) -> 23296.171 | BM10: =SUM('Motor Semanal'!KU9:KY9) -> 25105.922 | BN10: =SUM('Motor Semanal'!KZ9:LD9) -> 24287.149 | BO10: =SUM('Motor Semanal'!LE9:LI9) -> 27499.044 | BP10: =SUM('Motor Semanal'!LJ9:LN9) -> 21371.024 | BQ10: =SUM('Motor Semanal'!LO9:LS9) -> 27795.229 | BR10: =SUM('Motor Semanal'!LT9:LX9) -> 30852.896 | BS10: =SUM('Motor Semanal'!LY9:MC9) -> 29462.903 | BT10: =SUM('Motor Semanal'!MD9:MH9) -> 30219.715 | BU10: =SUM('Motor Semanal'!MI9:MM9) -> 28421.708 | BV10: =SUM('Motor Semanal'!MN9:MR9) -> 14736.338 | BW10: =SUM('Motor Semanal'!MS9:MW9) -> 31523.298 | BX10: =SUM('Motor Semanal'!MX9:NB9) -> 26557.634 | BY10: =SUM('Motor Semanal'!NC9:NG9) -> 28620.751 | BZ10: =SUM('Motor Semanal'!NH9:NL9) -> 27687.35 | CA10: =SUM('Motor Semanal'!NM9:NQ9) -> 31348.91 | CB10: =SUM('Motor Semanal'!NR9:NV9) -> 24362.967 | CC10: =SUM('Motor Semanal'!NW9:OA9) -> 31686.561 | CD10: =SUM('Motor Semanal'!OB9:OF9) -> 35172.301 | CE10: =SUM('Motor Semanal'!OG9:OK9) -> 33587.709 | CF10: =SUM('Motor Semanal'!OL9:OP9) -> 34450.475 | CG10: =SUM('Motor Semanal'!OQ9:OU9) -> 32400.748 | CH10: =SUM('Motor Semanal'!OV9:OZ9) -> 16799.425 | CI10: =SUM('Motor Semanal'!PA9:PE9) -> 35936.56 | CJ10: =SUM('Motor Semanal'!PF9:PI9) -> 30275.703 | CK10: =SUM('Motor Semanal'!PJ9:PN9) -> 32627.656 | CL10: =SUM('Motor Semanal'!PO9:PS9) -> 31563.579 | CM10: =SUM('Motor Semanal'!PT9:PX9) -> 35737.758 | CN10: =SUM('Motor Semanal'!PY9:QC9) -> 27773.783 | CO10: =SUM('Motor Semanal'!QD9:QH9) -> 36122.679 | CP10: =SUM('Motor Semanal'!QI9:QM9) -> 40096.424 | CQ10: =SUM('Motor Semanal'!QN9:QR9) -> 38289.988 | CR10: =SUM('Motor Semanal'!QS9:QW9) -> 39273.541 | CS10: =SUM('Motor Semanal'!QX9:RB9) -> 36936.852 | CT10: =SUM('Motor Semanal'!RC9:RG9) -> 19151.345 | CU10: =SUM('Motor Semanal'!RH9:RL9) -> 40967.679 | CV10: =SUM('Motor Semanal'!RM9:RP9) -> 34514.302 | CW10: =SUM('Motor Semanal'!RQ9:RU9) -> 37195.528 | CX10: =SUM('Motor Semanal'!RV9:RZ9) -> 35982.481 | CY10: =SUM('Motor Semanal'!SA9:SE9) -> 40741.044 | CZ10: =SUM('Motor Semanal'!SF9:SJ9) -> 31662.112 | DA10: =SUM('Motor Semanal'!SK9:SO9) -> 41179.854 | DB10: =SUM('Motor Semanal'!SP9:ST9) -> 45709.923 | DC10: =SUM('Motor Semanal'!SU9:SY9) -> 43650.587 | DD10: =SUM('Motor Semanal'!SZ9:TD9) -> 44771.837 | DE10: =SUM('Motor Semanal'!TE9:TI9) -> 42108.012 | DF10: =SUM('Motor Semanal'!TJ9:TN9) -> 21832.533 | DG10: =CU10*(1+Supuestos!$B$21) -> 46703.154 | DH10: =CV10*(1+Supuestos!$B$21) -> 39346.304
A11: Cobro de ventas al contado | B11: Motor Semanal fila 11 | C11: =SUM('Motor Semanal'!B11:F11) -> 7688.3132 | D11: =SUM('Motor Semanal'!G11:J11) -> 5675.1535 | E11: =SUM('Motor Semanal'!K11:O11) -> 7124.4154 | F11: =SUM('Motor Semanal'!P11:T11) -> 6782.2126 | G11: =SUM('Motor Semanal'!U11:Y11) -> 7152.0433 | H11: =SUM('Motor Semanal'!Z11:AD11) -> 5920.7573 | I11: =SUM('Motor Semanal'!AE11:AI11) -> 6807.6876 | J11: =SUM('Motor Semanal'!AJ11:AN11) -> 10057.844 | K11: =SUM('Motor Semanal'!AO11:AS11) -> 8539.6445 | L11: =SUM('Motor Semanal'!AT11:AX11) -> 9022.8435 | M11: =SUM('Motor Semanal'!AY11:BC11) -> 8485.1913 | N11: =SUM('Motor Semanal'!BD11:BH11) -> 4620.1851 | O11: =SUM('Motor Semanal'!BI11:BM11) -> 9667.1212 | P11: =SUM('Motor Semanal'!BN11:BQ11) -> 7833.6257 | Q11: =SUM('Motor Semanal'!BR11:BV11) -> 9712.5895 | R11: =SUM('Motor Semanal'!BW11:CA11) -> 8794.6736 | S11: =SUM('Motor Semanal'!CB11:CF11) -> 9870.71 | T11: =SUM('Motor Semanal'!CG11:CK11) -> 7852.4139 | U11: =SUM('Motor Semanal'!CL11:CP11) -> 9910.2067 | V11: =SUM('Motor Semanal'!CQ11:CU11) -> 11086.046 | W11: =SUM('Motor Semanal'!CV11:CZ11) -> 10677.219 | X11: =SUM('Motor Semanal'!DA11:DE11) -> 10905.593 | Y11: =SUM('Motor Semanal'!DF11:DJ11) -> 10309.507 | Z11: =SUM('Motor Semanal'!DK11:DO11) -> 5613.5249 | AA11: =SUM('Motor Semanal'!DP11:DT11) -> 11322.008 | AB11: =SUM('Motor Semanal'!DU11:DY11) -> 9957.7585 | AC11: =SUM('Motor Semanal'!DZ11:ED11) -> 10571.313 | AD11: =SUM('Motor Semanal'!EE11:EI11) -> 10289.768 | AE11: =SUM('Motor Semanal'!EJ11:EN11) -> 11548.731 | AF11: =SUM('Motor Semanal'!EO11:ES11) -> 9187.3242 | AG11: =SUM('Motor Semanal'!ET11:EX11) -> 11594.942 | AH11: =SUM('Motor Semanal'!EY11:FC11) -> 12970.674 | AI11: =SUM('Motor Semanal'!FD11:FH11) -> 12492.347 | AJ11: =SUM('Motor Semanal'!FI11:FM11) -> 12759.543 | AK11: =SUM('Motor Semanal'!FN11:FR11) -> 12062.124 | AL11: =SUM('Motor Semanal'!FS11:FW11) -> 6567.8241 | AM11: =SUM('Motor Semanal'!FX11:GB11) -> 13191.689 | AN11: =SUM('Motor Semanal'!GC11:GF11) -> 10677.624 | AO11: =SUM('Motor Semanal'!GG11:GK11) -> 13238.745 | AP11: =SUM('Motor Semanal'!GL11:GP11) -> 11987.58 | AQ11: =SUM('Motor Semanal'!GQ11:GU11) -> 13454.271 | AR11: =SUM('Motor Semanal'!GV11:GZ11) -> 10703.233 | AS11: =SUM('Motor Semanal'!HA11:HE11) -> 13508.107 | AT11: =SUM('Motor Semanal'!HF11:HJ11) -> 15110.835 | AU11: =SUM('Motor Semanal'!HK11:HO11) -> 14553.584 | AV11: =SUM('Motor Semanal'!HP11:HT11) -> 14864.868 | AW11: =SUM('Motor Semanal'!HU11:HY11) -> 14052.374 | AX11: =SUM('Motor Semanal'!HZ11:ID11) -> 7651.5151 | AY11: =SUM('Motor Semanal'!IE11:II11) -> 15304.172 | AZ11: =SUM('Motor Semanal'!IJ11:IM11) -> 12386.043 | BA11: =SUM('Motor Semanal'!IN11:IR11) -> 15356.944 | BB11: =SUM('Motor Semanal'!IS11:IW11) -> 13905.593 | BC11: =SUM('Motor Semanal'!IX11:JB11) -> 15606.955 | BD11: =SUM('Motor Semanal'!JC11:JG11) -> 12415.75 | BE11: =SUM('Motor Semanal'!JH11:JL11) -> 15669.404 | BF11: =SUM('Motor Semanal'!JM11:JQ11) -> 17528.569 | BG11: =SUM('Motor Semanal'!JR11:JV11) -> 16882.157 | BH11: =SUM('Motor Semanal'!JW11:KA11) -> 17243.247 | BI11: =SUM('Motor Semanal'!KB11:KF11) -> 16300.754 | BJ11: =SUM('Motor Semanal'!KG11:KK11) -> 8875.7575 | BK11: =SUM('Motor Semanal'!KL11:KP11) -> 17678.43 | BL11: =SUM('Motor Semanal'!KQ11:KT11) -> 14305.88 | BM11: =SUM('Motor Semanal'!KU11:KY11) -> 17737.271 | BN11: =SUM('Motor Semanal'!KZ11:LD11) -> 16060.959 | BO11: =SUM('Motor Semanal'!LE11:LI11) -> 18026.033 | BP11: =SUM('Motor Semanal'!LJ11:LN11) -> 14340.191 | BQ11: =SUM('Motor Semanal'!LO11:LS11) -> 18098.162 | BR11: =SUM('Motor Semanal'!LT11:LX11) -> 20245.497 | BS11: =SUM('Motor Semanal'!LY11:MC11) -> 19498.891 | BT11: =SUM('Motor Semanal'!MD11:MH11) -> 19915.95 | BU11: =SUM('Motor Semanal'!MI11:MM11) -> 18827.371 | BV11: =SUM('Motor Semanal'!MN11:MR11) -> 10251.5 | BW11: =SUM('Motor Semanal'!MS11:MW11) -> 20160.759 | BX11: =SUM('Motor Semanal'!MX11:NB11) -> 17718.72 | BY11: =SUM('Motor Semanal'!NC11:NG11) -> 18810.472 | BZ11: =SUM('Motor Semanal'!NH11:NL11) -> 18309.494 | CA11: =SUM('Motor Semanal'!NM11:NQ11) -> 20549.677 | CB11: =SUM('Motor Semanal'!NR11:NV11) -> 16347.818 | CC11: =SUM('Motor Semanal'!NW11:OA11) -> 20631.905 | CD11: =SUM('Motor Semanal'!OB11:OF11) -> 23079.867 | CE11: =SUM('Motor Semanal'!OG11:OK11) -> 22228.736 | CF11: =SUM('Motor Semanal'!OL11:OP11) -> 22704.183 | CG11: =SUM('Motor Semanal'!OQ11:OU11) -> 21463.203 | CH11: =SUM('Motor Semanal'!OV11:OZ11) -> 11686.71 | CI11: =SUM('Motor Semanal'!PA11:PE11) -> 22983.266 | CJ11: =SUM('Motor Semanal'!PF11:PI11) -> 18591.922 | CK11: =SUM('Motor Semanal'!PJ11:PN11) -> 23051.357 | CL11: =SUM('Motor Semanal'!PO11:PS11) -> 20872.823 | CM11: =SUM('Motor Semanal'!PT11:PX11) -> 23426.632 | CN11: =SUM('Motor Semanal'!PY11:QC11) -> 18636.513 | CO11: =SUM('Motor Semanal'!QD11:QH11) -> 23520.371 | CP11: =SUM('Motor Semanal'!QI11:QM11) -> 26311.048 | CQ11: =SUM('Motor Semanal'!QN11:QR11) -> 25340.759 | CR11: =SUM('Motor Semanal'!QS11:QW11) -> 25882.769 | CS11: =SUM('Motor Semanal'!QX11:RB11) -> 24468.051 | CT11: =SUM('Motor Semanal'!RC11:RG11) -> 13322.849 | CU11: =SUM('Motor Semanal'!RH11:RL11) -> 26200.923 | CV11: =SUM('Motor Semanal'!RM11:RP11) -> 21194.791 | CW11: =SUM('Motor Semanal'!RQ11:RU11) -> 26278.547 | CX11: =SUM('Motor Semanal'!RV11:RZ11) -> 23795.018 | CY11: =SUM('Motor Semanal'!SA11:SE11) -> 26706.361 | CZ11: =SUM('Motor Semanal'!SF11:SJ11) -> 21245.624 | DA11: =SUM('Motor Semanal'!SK11:SO11) -> 26813.223 | DB11: =SUM('Motor Semanal'!SP11:ST11) -> 29994.595 | DC11: =SUM('Motor Semanal'!SU11:SY11) -> 28888.466 | DD11: =SUM('Motor Semanal'!SZ11:TD11) -> 29506.357 | DE11: =SUM('Motor Semanal'!TE11:TI11) -> 27893.578 | DF11: =SUM('Motor Semanal'!TJ11:TN11) -> 15188.048
A12: Cobro por descuento de letras | B12: Motor Semanal fila 13 | C12: =SUM('Motor Semanal'!B13:F13) -> 1568.047 | D12: =SUM('Motor Semanal'!G13:J13) -> 1460.4981 | E12: =SUM('Motor Semanal'!K13:O13) -> 2685.4251 | F12: =SUM('Motor Semanal'!P13:T13) -> 1803.1158 | G12: =SUM('Motor Semanal'!U13:Y13) -> 2486.2205 | H12: =SUM('Motor Semanal'!Z13:AD13) -> 1743.6983 | I12: =SUM('Motor Semanal'!AE13:AI13) -> 2482.6376 | J12: =SUM('Motor Semanal'!AJ13:AN13) -> 2223.8702 | K12: =SUM('Motor Semanal'!AO13:AS13) -> 1806.6361 | L12: =SUM('Motor Semanal'!AT13:AX13) -> 2156.9122 | M12: =SUM('Motor Semanal'!AY13:BC13) -> 2027.9385 | N12: =SUM('Motor Semanal'!BD13:BH13) -> 1225.8007 | O12: =SUM('Motor Semanal'!BI13:BM13) -> 2110.3331 | P12: =SUM('Motor Semanal'!BN13:BQ13) -> 1532.4876 | Q12: =SUM('Motor Semanal'!BR13:BV13) -> 2655.0358 | R12: =SUM('Motor Semanal'!BW13:CA13) -> 2093.5906 | S12: =SUM('Motor Semanal'!CB13:CF13) -> 2301.7162 | T12: =SUM('Motor Semanal'!CG13:CK13) -> 1932.0314 | U12: =SUM('Motor Semanal'!CL13:CP13) -> 2273.7279 | V12: =SUM('Motor Semanal'!CQ13:CU13) -> 2642.2927 | W12: =SUM('Motor Semanal'!CV13:CZ13) -> 2546.3381 | X12: =SUM('Motor Semanal'!DA13:DE13) -> 2575.4959 | Y12: =SUM('Motor Semanal'!DF13:DJ13) -> 2463.9453 | Z12: =SUM('Motor Semanal'!DK13:DO13) -> 1489.3478 | AA12: =SUM('Motor Semanal'!DP13:DT13) -> 2478.1549 | AB12: =SUM('Motor Semanal'!DU13:DY13) -> 2418.9394 | AC12: =SUM('Motor Semanal'!DZ13:ED13) -> 2480.4629 | AD12: =SUM('Motor Semanal'!EE13:EI13) -> 2449.501 | AE12: =SUM('Motor Semanal'!EJ13:EN13) -> 2693.0079 | AF12: =SUM('Motor Semanal'!EO13:ES13) -> 2260.4767 | AG12: =SUM('Motor Semanal'!ET13:EX13) -> 2660.2616 | AH12: =SUM('Motor Semanal'!EY13:FC13) -> 3032.0634 | AI12: =SUM('Motor Semanal'!FD13:FH13) -> 2979.2156 | AJ12: =SUM('Motor Semanal'!FI13:FM13) -> 3013.3302 | AK12: =SUM('Motor Semanal'!FN13:FR13) -> 2882.816 | AL12: =SUM('Motor Semanal'!FS13:FW13) -> 1742.537 | AM12: =SUM('Motor Semanal'!FX13:GB13) -> 2888.2743 | AN12: =SUM('Motor Semanal'!GC13:GF13) -> 2088.8573 | AO12: =SUM('Motor Semanal'!GG13:GK13) -> 3618.9465 | AP12: =SUM('Motor Semanal'!GL13:GP13) -> 2853.6686 | AQ12: =SUM('Motor Semanal'!GQ13:GU13) -> 3137.3542 | AR12: =SUM('Motor Semanal'!GV13:GZ13) -> 2633.4554 | AS12: =SUM('Motor Semanal'!HA13:HE13) -> 3099.2048 | AT12: =SUM('Motor Semanal'!HF13:HJ13) -> 3532.3538 | AU12: =SUM('Motor Semanal'!HK13:HO13) -> 3470.7862 | AV12: =SUM('Motor Semanal'!HP13:HT13) -> 3510.5297 | AW12: =SUM('Motor Semanal'!HU13:HY13) -> 3358.4807 | AX12: =SUM('Motor Semanal'!HZ13:ID13) -> 2030.0556 | AY12: =SUM('Motor Semanal'!IE13:II13) -> 3351.83 | AZ12: =SUM('Motor Semanal'!IJ13:IM13) -> 2423.0744 | BA12: =SUM('Motor Semanal'!IN13:IR13) -> 4197.9779 | BB12: =SUM('Motor Semanal'!IS13:IW13) -> 3310.2556 | BC12: =SUM('Motor Semanal'!IX13:JB13) -> 3639.3309 | BD12: =SUM('Motor Semanal'!JC13:JG13) -> 3054.8082 | BE12: =SUM('Motor Semanal'!JH13:JL13) -> 3595.0775 | BF12: =SUM('Motor Semanal'!JM13:JQ13) -> 4097.5304 | BG12: =SUM('Motor Semanal'!JR13:JV13) -> 4026.112 | BH12: =SUM('Motor Semanal'!JW13:KA13) -> 4072.2145 | BI12: =SUM('Motor Semanal'!KB13:KF13) -> 3895.8376 | BJ12: =SUM('Motor Semanal'!KG13:KK13) -> 2354.8645 | BK12: =SUM('Motor Semanal'!KL13:KP13) -> 3873.0317 | BL12: =SUM('Motor Semanal'!KQ13:KT13) -> 2798.651 | BM12: =SUM('Motor Semanal'!KU13:KY13) -> 4848.6645 | BN12: =SUM('Motor Semanal'!KZ13:LD13) -> 3823.3452 | BO12: =SUM('Motor Semanal'!LE13:LI13) -> 4203.4272 | BP12: =SUM('Motor Semanal'!LJ13:LN13) -> 3528.3035 | BQ12: =SUM('Motor Semanal'!LO13:LS13) -> 4152.3145 | BR12: =SUM('Motor Semanal'!LT13:LX13) -> 4732.6477 | BS12: =SUM('Motor Semanal'!LY13:MC13) -> 4650.1593 | BT12: =SUM('Motor Semanal'!MD13:MH13) -> 4703.4077 | BU12: =SUM('Motor Semanal'!MI13:MM13) -> 4499.6924 | BV12: =SUM('Motor Semanal'!MN13:MR13) -> 2719.8685 | BW12: =SUM('Motor Semanal'!MS13:MW13) -> 4421.0611 | BX12: =SUM('Motor Semanal'!MX13:NB13) -> 4304.2327 | BY12: =SUM('Motor Semanal'!NC13:NG13) -> 4413.7069 | BZ12: =SUM('Motor Semanal'!NH13:NL13) -> 4358.6135 | CA12: =SUM('Motor Semanal'!NM13:NQ13) -> 4791.907 | CB12: =SUM('Motor Semanal'!NR13:NV13) -> 4022.266 | CC12: =SUM('Motor Semanal'!NW13:OA13) -> 4733.6386 | CD12: =SUM('Motor Semanal'!OB13:OF13) -> 5395.2183 | CE12: =SUM('Motor Semanal'!OG13:OK13) -> 5301.1816 | CF12: =SUM('Motor Semanal'!OL13:OP13) -> 5361.8848 | CG12: =SUM('Motor Semanal'!OQ13:OU13) -> 5129.6493 | CH12: =SUM('Motor Semanal'!OV13:OZ13) -> 3100.65 | CI12: =SUM('Motor Semanal'!PA13:PE13) -> 5040.0097 | CJ12: =SUM('Motor Semanal'!PF13:PI13) -> 3637.1268 | CK12: =SUM('Motor Semanal'!PJ13:PN13) -> 6301.3244 | CL12: =SUM('Motor Semanal'!PO13:PS13) -> 4968.8194 | CM12: =SUM('Motor Semanal'!PT13:PX13) -> 5462.774 | CN12: =SUM('Motor Semanal'!PY13:QC13) -> 4585.3832 | CO12: =SUM('Motor Semanal'!QD13:QH13) -> 5396.348 | CP12: =SUM('Motor Semanal'!QI13:QM13) -> 6150.5489 | CQ12: =SUM('Motor Semanal'!QN13:QR13) -> 6043.3471 | CR12: =SUM('Motor Semanal'!QS13:QW13) -> 6112.5487 | CS12: =SUM('Motor Semanal'!QX13:RB13) -> 5847.8002 | CT12: =SUM('Motor Semanal'!RC13:RG13) -> 3534.741 | CU12: =SUM('Motor Semanal'!RH13:RL13) -> 5745.6111 | CV12: =SUM('Motor Semanal'!RM13:RP13) -> 4146.3245 | CW12: =SUM('Motor Semanal'!RQ13:RU13) -> 7183.5098 | CX12: =SUM('Motor Semanal'!RV13:RZ13) -> 5664.4541 | CY12: =SUM('Motor Semanal'!SA13:SE13) -> 6227.5623 | CZ12: =SUM('Motor Semanal'!SF13:SJ13) -> 5227.3369 | DA12: =SUM('Motor Semanal'!SK13:SO13) -> 6151.8367 | DB12: =SUM('Motor Semanal'!SP13:ST13) -> 7011.6257 | DC12: =SUM('Motor Semanal'!SU13:SY13) -> 6889.4156 | DD12: =SUM('Motor Semanal'!SZ13:TD13) -> 6968.3055 | DE12: =SUM('Motor Semanal'!TE13:TI13) -> 6666.4923 | DF12: =SUM('Motor Semanal'!TJ13:TN13) -> 4029.6048
A13: Cobranza libre / cartera | B13: Motor Semanal fila 14 | C13: =SUM('Motor Semanal'!B14:F14) -> 29.442892 | D13: =SUM('Motor Semanal'!G14:J14) -> 1064.6493 | E13: =SUM('Motor Semanal'!K14:O14) -> 2473.9772 | F13: =SUM('Motor Semanal'!P14:T14) -> 2865.4535 | G13: =SUM('Motor Semanal'!U14:Y14) -> 2238.0926 | H13: =SUM('Motor Semanal'!Z14:AD14) -> 2740.2836 | I13: =SUM('Motor Semanal'!AE14:AI14) -> 2244.1559 | J13: =SUM('Motor Semanal'!AJ14:AN14) -> 2704.9998 | K13: =SUM('Motor Semanal'!AO14:AS14) -> 2734.799 | L13: =SUM('Motor Semanal'!AT14:AX14) -> 2089.7689 | M13: =SUM('Motor Semanal'!AY14:BC14) -> 2543.5802 | N13: =SUM('Motor Semanal'!BD14:BH14) -> 2376.1561 | O13: =SUM('Motor Semanal'!BI14:BM14) -> 1596.4435 | P13: =SUM('Motor Semanal'!BN14:BQ14) -> 1717.9558 | Q13: =SUM('Motor Semanal'!BR14:BV14) -> 2614.0617 | R13: =SUM('Motor Semanal'!BW14:CA14) -> 2907.1593 | S13: =SUM('Motor Semanal'!CB14:CF14) -> 2473.0789 | T13: =SUM('Motor Semanal'!CG14:CK14) -> 2653.8968 | U13: =SUM('Motor Semanal'!CL14:CP14) -> 2349.8812 | V13: =SUM('Motor Semanal'!CQ14:CU14) -> 2613.7985 | W13: =SUM('Motor Semanal'!CV14:CZ14) -> 3052.4937 | X13: =SUM('Motor Semanal'!DA14:DE14) -> 3006.4196 | Y13: =SUM('Motor Semanal'!DF14:DJ14) -> 3011.4009 | Z13: =SUM('Motor Semanal'!DK14:DO14) -> 2887.0297 | AA13: =SUM('Motor Semanal'!DP14:DT14) -> 1937.3259 | AB13: =SUM('Motor Semanal'!DU14:DY14) -> 2699.1406 | AC13: =SUM('Motor Semanal'!DZ14:ED14) -> 2901.5914 | AD13: =SUM('Motor Semanal'!EE14:EI14) -> 2885.9541 | AE13: =SUM('Motor Semanal'!EJ14:EN14) -> 2893.5023 | AF13: =SUM('Motor Semanal'!EO14:ES14) -> 3105.0593 | AG13: =SUM('Motor Semanal'!ET14:EX14) -> 2749.361 | AH13: =SUM('Motor Semanal'!EY14:FC14) -> 3044.1937 | AI13: =SUM('Motor Semanal'!FD14:FH14) -> 3515.6153 | AJ13: =SUM('Motor Semanal'!FI14:FM14) -> 3517.511 | AK13: =SUM('Motor Semanal'!FN14:FR14) -> 3523.339 | AL13: =SUM('Motor Semanal'!FS14:FW14) -> 3377.8248 | AM13: =SUM('Motor Semanal'!FX14:GB14) -> 2266.3654 | AN13: =SUM('Motor Semanal'!GC14:GF14) -> 2363.5637 | AO13: =SUM('Motor Semanal'!GG14:GK14) -> 3563.0968 | AP13: =SUM('Motor Semanal'!GL14:GP14) -> 3962.6035 | AQ13: =SUM('Motor Semanal'!GQ14:GU14) -> 3370.9302 | AR13: =SUM('Motor Semanal'!GV14:GZ14) -> 3617.3941 | AS13: =SUM('Motor Semanal'!HA14:HE14) -> 3203.0055 | AT13: =SUM('Motor Semanal'!HF14:HJ14) -> 3546.4856 | AU13: =SUM('Motor Semanal'!HK14:HO14) -> 4095.6918 | AV13: =SUM('Motor Semanal'!HP14:HT14) -> 4097.9003 | AW13: =SUM('Motor Semanal'!HU14:HY14) -> 4104.6899 | AX13: =SUM('Motor Semanal'!HZ14:ID14) -> 3935.1658 | AY13: =SUM('Motor Semanal'!IE14:II14) -> 2639.9594 | AZ13: =SUM('Motor Semanal'!IJ14:IM14) -> 2744.3952 | BA13: =SUM('Motor Semanal'!IN14:IR14) -> 4133.1923 | BB13: =SUM('Motor Semanal'!IS14:IW14) -> 4596.62 | BC13: =SUM('Motor Semanal'!IX14:JB14) -> 3910.279 | BD13: =SUM('Motor Semanal'!JC14:JG14) -> 4196.1772 | BE13: =SUM('Motor Semanal'!JH14:JL14) -> 3715.4864 | BF13: =SUM('Motor Semanal'!JM14:JQ14) -> 4113.9233 | BG13: =SUM('Motor Semanal'!JR14:JV14) -> 4751.0025 | BH13: =SUM('Motor Semanal'!JW14:KA14) -> 4753.5643 | BI13: =SUM('Motor Semanal'!KB14:KF14) -> 4761.4403 | BJ13: =SUM('Motor Semanal'!KG14:KK14) -> 4564.7924 | BK13: =SUM('Motor Semanal'!KL14:KP14) -> 3061.9395 | BL13: =SUM('Motor Semanal'!KQ14:KT14) -> 3172.877 | BM13: =SUM('Motor Semanal'!KU14:KY14) -> 4773.8371 | BN13: =SUM('Motor Semanal'!KZ14:LD14) -> 5309.0961 | BO13: =SUM('Motor Semanal'!LE14:LI14) -> 4516.3722 | BP13: =SUM('Motor Semanal'!LJ14:LN14) -> 4846.5846 | BQ13: =SUM('Motor Semanal'!LO14:LS14) -> 4291.3868 | BR13: =SUM('Motor Semanal'!LT14:LX14) -> 4751.5814 | BS13: =SUM('Motor Semanal'!LY14:MC14) -> 5487.4079 | BT13: =SUM('Motor Semanal'!MD14:MH14) -> 5490.3668 | BU13: =SUM('Motor Semanal'!MI14:MM14) -> 5499.4636 | BV13: =SUM('Motor Semanal'!MN14:MR14) -> 5272.3352 | BW13: =SUM('Motor Semanal'!MS14:MW14) -> 3535.1079 | BX13: =SUM('Motor Semanal'!MX14:NB14) -> 4824.122 | BY13: =SUM('Motor Semanal'!NC14:NG14) -> 5163.0581 | BZ13: =SUM('Motor Semanal'!NH14:NL14) -> 5135.2331 | CA13: =SUM('Motor Semanal'!NM14:NQ14) -> 5148.6643 | CB13: =SUM('Motor Semanal'!NR14:NV14) -> 5525.1065 | CC13: =SUM('Motor Semanal'!NW14:OA14) -> 4892.181 | CD13: =SUM('Motor Semanal'!OB14:OF14) -> 5416.8028 | CE13: =SUM('Motor Semanal'!OG14:OK14) -> 6255.645 | CF13: =SUM('Motor Semanal'!OL14:OP14) -> 6259.0182 | CG13: =SUM('Motor Semanal'!OQ14:OU14) -> 6269.3885 | CH13: =SUM('Motor Semanal'!OV14:OZ14) -> 6010.4621 | CI13: =SUM('Motor Semanal'!PA14:PE14) -> 4030.023 | CJ13: =SUM('Motor Semanal'!PF14:PI14) -> 4135.771 | CK13: =SUM('Motor Semanal'!PJ14:PN14) -> 6204.0788 | CL13: =SUM('Motor Semanal'!PO14:PS14) -> 6899.7013 | CM13: =SUM('Motor Semanal'!PT14:PX14) -> 5869.4773 | CN13: =SUM('Motor Semanal'!PY14:QC14) -> 6298.6214 | CO13: =SUM('Motor Semanal'!QD14:QH14) -> 5577.0863 | CP13: =SUM('Motor Semanal'!QI14:QM14) -> 6175.1552 | CQ13: =SUM('Motor Semanal'!QN14:QR14) -> 7131.4353 | CR13: =SUM('Motor Semanal'!QS14:QW14) -> 7135.2807 | CS13: =SUM('Motor Semanal'!QX14:RB14) -> 7147.1029 | CT13: =SUM('Motor Semanal'!RC14:RG14) -> 6851.9268 | CU13: =SUM('Motor Semanal'!RH14:RL14) -> 4594.2262 | CV13: =SUM('Motor Semanal'!RM14:RP14) -> 4714.779 | CW13: =SUM('Motor Semanal'!RQ14:RU14) -> 7072.6498 | CX13: =SUM('Motor Semanal'!RV14:RZ14) -> 7865.6595 | CY13: =SUM('Motor Semanal'!SA14:SE14) -> 6691.2042 | CZ13: =SUM('Motor Semanal'!SF14:SJ14) -> 7180.4284 | DA13: =SUM('Motor Semanal'!SK14:SO14) -> 6357.8784 | DB13: =SUM('Motor Semanal'!SP14:ST14) -> 7039.6769 | DC13: =SUM('Motor Semanal'!SU14:SY14) -> 8129.8363 | DD13: =SUM('Motor Semanal'!SZ14:TD14) -> 8134.22 | DE13: =SUM('Motor Semanal'!TE14:TI14) -> 8147.6973 | DF13: =SUM('Motor Semanal'!TJ14:TN14) -> 7811.1966
A14: (−) Incobrables | B14: Motor Semanal fila 16 (% fila 59) | C14: =-SUM('Motor Semanal'!B16:F16) -> -162.01011 | D14: =-SUM('Motor Semanal'!G16:J16) -> -136.48969 | E14: =-SUM('Motor Semanal'!K16:O16) -> -147.09282 | F14: =-SUM('Motor Semanal'!P16:T16) -> -142.29573 | G14: =-SUM('Motor Semanal'!U16:Y16) -> -161.11386 | H14: =-SUM('Motor Semanal'!Z16:AD16) -> -125.21047 | I14: =-SUM('Motor Semanal'!AE16:AI16) -> -162.84918 | J14: =-SUM('Motor Semanal'!AJ16:AN16) -> -180.76371 | K14: =-SUM('Motor Semanal'!AO16:AS16) -> -172.61989 | L14: =-SUM('Motor Semanal'!AT16:AX16) -> -177.05397 | M14: =-SUM('Motor Semanal'!AY16:BC16) -> -166.51965 | N14: =-SUM('Motor Semanal'!BD16:BH16) -> -86.338578 | O14: =-SUM('Motor Semanal'!BI16:BM16) -> -181.70057 | P14: =-SUM('Motor Semanal'!BN16:BQ16) -> -153.07844 | Q14: =-SUM('Motor Semanal'!BR16:BV16) -> -164.97026 | R14: =-SUM('Motor Semanal'!BW16:CA16) -> -159.59013 | S14: =-SUM('Motor Semanal'!CB16:CF16) -> -180.69539 | T14: =-SUM('Motor Semanal'!CG16:CK16) -> -140.42836 | U14: =-SUM('Motor Semanal'!CL16:CP16) -> -183.96645 | V14: =-SUM('Motor Semanal'!CQ16:CU16) -> -202.73345 | W14: =-SUM('Motor Semanal'!CV16:CZ16) -> -193.59985 | X14: =-SUM('Motor Semanal'!DA16:DE16) -> -198.57284 | Y14: =-SUM('Motor Semanal'!DF16:DJ16) -> -186.75819 | Z14: =-SUM('Motor Semanal'!DK16:DO16) -> -96.832036 | AA14: =-SUM('Motor Semanal'!DP16:DT16) -> -194.87386 | AB14: =-SUM('Motor Semanal'!DU16:DY16) -> -164.17663 | AC14: =-SUM('Motor Semanal'!DZ16:ED16) -> -176.9306 | AD14: =-SUM('Motor Semanal'!EE16:EI16) -> -171.16042 | AE14: =-SUM('Motor Semanal'!EJ16:EN16) -> -193.79581 | AF14: =-SUM('Motor Semanal'!EO16:ES16) -> -150.60941 | AG14: =-SUM('Motor Semanal'!ET16:EX16) -> -195.88313 | AH14: =-SUM('Motor Semanal'!EY16:FC16) -> -217.43163 | AI14: =-SUM('Motor Semanal'!FD16:FH16) -> -207.63584 | AJ14: =-SUM('Motor Semanal'!FI16:FM16) -> -212.96937 | AK14: =-SUM('Motor Semanal'!FN16:FR16) -> -200.29816 | AL14: =-SUM('Motor Semanal'!FS16:FW16) -> -103.85236 | AM14: =-SUM('Motor Semanal'!FX16:GB16) -> -206.38913 | AN14: =-SUM('Motor Semanal'!GC16:GF16) -> -173.87797 | AO14: =-SUM('Motor Semanal'!GG16:GK16) -> -187.38559 | AP14: =-SUM('Motor Semanal'!GL16:GP16) -> -181.27444 | AQ14: =-SUM('Motor Semanal'!GQ16:GU16) -> -205.24738 | AR14: =-SUM('Motor Semanal'!GV16:GZ16) -> -159.50906 | AS14: =-SUM('Motor Semanal'!HA16:HE16) -> -207.45804 | AT14: =-SUM('Motor Semanal'!HF16:HJ16) -> -230.27986 | AU14: =-SUM('Motor Semanal'!HK16:HO16) -> -219.90523 | AV14: =-SUM('Motor Semanal'!HP16:HT16) -> -225.55392 | AW14: =-SUM('Motor Semanal'!HU16:HY16) -> -212.13396 | AX14: =-SUM('Motor Semanal'!HZ16:ID16) -> -109.98909 | AY14: =-SUM('Motor Semanal'!IE16:II16) -> -215.47026 | AZ14: =-SUM('Motor Semanal'!IJ16:IM16) -> -181.5286 | BA14: =-SUM('Motor Semanal'!IN16:IR16) -> -195.63056 | BB14: =-SUM('Motor Semanal'!IS16:IW16) -> -189.25052 | BC14: =-SUM('Motor Semanal'!IX16:JB16) -> -214.27827 | BD14: =-SUM('Motor Semanal'!JC16:JG16) -> -166.52746 | BE14: =-SUM('Motor Semanal'!JH16:JL16) -> -216.5862 | BF14: =-SUM('Motor Semanal'!JM16:JQ16) -> -240.41218 | BG14: =-SUM('Motor Semanal'!JR16:JV16) -> -229.58106 | BH14: =-SUM('Motor Semanal'!JW16:KA16) -> -235.4783 | BI14: =-SUM('Motor Semanal'!KB16:KF16) -> -221.46786 | BJ14: =-SUM('Motor Semanal'!KG16:KK16) -> -114.82861 | BK14: =-SUM('Motor Semanal'!KL16:KP16) -> -221.21613 | BL14: =-SUM('Motor Semanal'!KQ16:KT16) -> -186.36936 | BM14: =-SUM('Motor Semanal'!KU16:KY16) -> -200.84737 | BN14: =-SUM('Motor Semanal'!KZ16:LD16) -> -194.2972 | BO14: =-SUM('Motor Semanal'!LE16:LI16) -> -219.99235 | BP14: =-SUM('Motor Semanal'!LJ16:LN16) -> -170.96819 | BQ14: =-SUM('Motor Semanal'!LO16:LS16) -> -222.36183 | BR14: =-SUM('Motor Semanal'!LT16:LX16) -> -246.82317 | BS14: =-SUM('Motor Semanal'!LY16:MC16) -> -235.70322 | BT14: =-SUM('Motor Semanal'!MD16:MH16) -> -241.75772 | BU14: =-SUM('Motor Semanal'!MI16:MM16) -> -227.37367 | BV14: =-SUM('Motor Semanal'!MN16:MR16) -> -117.89071 | BW14: =-SUM('Motor Semanal'!MS16:MW16) -> -220.66309 | BX14: =-SUM('Motor Semanal'!MX16:NB16) -> -185.90344 | BY14: =-SUM('Motor Semanal'!NC16:NG16) -> -200.34526 | BZ14: =-SUM('Motor Semanal'!NH16:NL16) -> -193.81145 | CA14: =-SUM('Motor Semanal'!NM16:NQ16) -> -219.44237 | CB14: =-SUM('Motor Semanal'!NR16:NV16) -> -170.54077 | CC14: =-SUM('Motor Semanal'!NW16:OA16) -> -221.80592 | CD14: =-SUM('Motor Semanal'!OB16:OF16) -> -246.20611 | CE14: =-SUM('Motor Semanal'!OG16:OK16) -> -235.11396 | CF14: =-SUM('Motor Semanal'!OL16:OP16) -> -241.15332 | CG14: =-SUM('Motor Semanal'!OQ16:OU16) -> -226.80523 | CH14: =-SUM('Motor Semanal'!OV16:OZ16) -> -117.59598 | CI14: =-SUM('Motor Semanal'!PA16:PE16) -> -215.61936 | CJ14: =-SUM('Motor Semanal'!PF16:PI16) -> -181.65422 | CK14: =-SUM('Motor Semanal'!PJ16:PN16) -> -195.76594 | CL14: =-SUM('Motor Semanal'!PO16:PS16) -> -189.38148 | CM14: =-SUM('Motor Semanal'!PT16:PX16) -> -214.42655 | CN14: =-SUM('Motor Semanal'!PY16:QC16) -> -166.6427 | CO14: =-SUM('Motor Semanal'!QD16:QH16) -> -216.73607 | CP14: =-SUM('Motor Semanal'!QI16:QM16) -> -240.57854 | CQ14: =-SUM('Motor Semanal'!QN16:QR16) -> -229.73993 | CR14: =-SUM('Motor Semanal'!QS16:QW16) -> -235.64125 | CS14: =-SUM('Motor Semanal'!QX16:RB16) -> -221.62111 | CT14: =-SUM('Motor Semanal'!RC16:RG16) -> -114.90807 | CU14: =-SUM('Motor Semanal'!RH16:RL16) -> -204.83839 | CV14: =-SUM('Motor Semanal'!RM16:RP16) -> -172.57151 | CW14: =-SUM('Motor Semanal'!RQ16:RU16) -> -185.97764 | CX14: =-SUM('Motor Semanal'!RV16:RZ16) -> -179.9124 | CY14: =-SUM('Motor Semanal'!SA16:SE16) -> -203.70522 | CZ14: =-SUM('Motor Semanal'!SF16:SJ16) -> -158.31056 | DA14: =-SUM('Motor Semanal'!SK16:SO16) -> -205.89927 | DB14: =-SUM('Motor Semanal'!SP16:ST16) -> -228.54961 | DC14: =-SUM('Motor Semanal'!SU16:SY16) -> -218.25293 | DD14: =-SUM('Motor Semanal'!SZ16:TD16) -> -223.85919 | DE14: =-SUM('Motor Semanal'!TE16:TI16) -> -210.54006 | DF14: =-SUM('Motor Semanal'!TJ16:TN16) -> -109.16267
A15: TOTAL INGRESOS OPERATIVOS | B15: Suma de las 4 líneas | C15: =SUM(C11:C14) -> 9123.7929 | D15: =SUM(D11:D14) -> 8063.8112 | E15: =SUM(E11:E14) -> 12136.725 | F15: =SUM(F11:F14) -> 11308.486 | G15: =SUM(G11:G14) -> 11715.243 | H15: =SUM(H11:H14) -> 10279.529 | I15: =SUM(I11:I14) -> 11371.632 | J15: =SUM(J11:J14) -> 14805.95 | ... DF15: =SUM(DF11:DF14) -> 26919.687
A17: 2. EGRESOS OPERATIVOS
A18: Compras de mercadería | B18: Ventas de 2 meses después × fila 60 | C18: =E10*C60 -> 9740.0794 | D18: =F10*D60 -> 9422.429 | E18: =G10*E60 -> 10668.514 | F18: =H10*F60 -> 8291.0906 | G18: =I10*G60 -> 10783.421 | H18: =J10*H60 -> 11969.672 | I18: =K10*I60 -> 11430.411 | J18: =L10*J60 -> 11724.024 | ... DF18: =DH10*DF60 -> 32069.756
A19: Planilla administrativa | B19: 2026: Supuestos fila 60 | C19: =Supuestos!B28 -> 190.6829 | D19: =Supuestos!C28 -> 162.33706 | E19: =Supuestos!D28 -> 161.86676 | F19: =Supuestos!E28 -> 130.37507 | G19: =Supuestos!F28 -> 147.09969 | H19: =Supuestos!G28 -> 162.25642 | I19: =Supuestos!H28 -> 150.70194 | J19: =Supuestos!I28 -> 180.6936 | ... N19: =Supuestos!M28 -> 180.6936 | O19: =IF(Supuestos!$B$25=1,N19*(1+Supuestos!$C$18),Supuestos!$C$60*O10) -> 197.63362 | P19: =IF(Supuestos!$B$25=1,O19,Supuestos!$C$60*P10) -> 197.63362 | Q19: =IF(Supuestos!$B$25=1,P19,Supuestos!$C$60*Q10) -> 197.63362 | R19: =IF(Supuestos!$B$25=1,Q19,Supuestos!$C$60*R10) -> 197.63362 | S19: =IF(Supuestos!$B$25=1,R19,Supuestos!$C$60*S10) -> 197.63362 | T19: =IF(Supuestos!$B$25=1,S19,Supuestos!$C$60*T10) -> 197.63362 | U19: =IF(Supuestos!$B$25=1,T19,Supuestos!$C$60*U10) -> 197.63362 | V19: =IF(Supuestos!$B$25=1,U19,Supuestos!$C$60*V10) -> 197.63362 | W19: =IF(Supuestos!$B$25=1,V19,Supuestos!$C$60*W10) -> 197.63362 | ... Z19: =IF(Supuestos!$B$25=1,Y19,Supuestos!$C$60*Z10) -> 197.63362 | AA19: =IF(Supuestos!$B$25=1,Z19*(1+Supuestos!$D$18),Supuestos!$D$60*AA10) -> 214.57365 | AB19: =IF(Supuestos!$B$25=1,AA19,Supuestos!$D$60*AB10) -> 214.57365 | AC19: =IF(Supuestos!$B$25=1,AB19,Supuestos!$D$60*AC10) -> 214.57365 | AD19: =IF(Supuestos!$B$25=1,AC19,Supuestos!$D$60*AD10) -> 214.57365 | AE19: =IF(Supuestos!$B$25=1,AD19,Supuestos!$D$60*AE10) -> 214.57365 | AF19: =IF(Supuestos!$B$25=1,AE19,Supuestos!$D$60*AF10) -> 214.57365 | AG19: =IF(Supuestos!$B$25=1,AF19,Supuestos!$D$60*AG10) -> 214.57365 | AH19: =IF(Supuestos!$B$25=1,AG19,Supuestos!$D$60*AH10) -> 214.57365 | AI19: =IF(Supuestos!$B$25=1,AH19,Supuestos!$D$60*AI10) -> 214.57365 | ... AL19: =IF(Supuestos!$B$25=1,AK19,Supuestos!$D$60*AL10) -> 214.57365 | AM19: =IF(Supuestos!$B$25=1,AL19*(1+Supuestos!$E$18),Supuestos!$E$60*AM10) -> 220.22033 | AN19: =IF(Supuestos!$B$25=1,AM19,Supuestos!$E$60*AN10) -> 220.22033 | AO19: =IF(Supuestos!$B$25=1,AN19,Supuestos!$E$60*AO10) -> 220.22033 | AP19: =IF(Supuestos!$B$25=1,AO19,Supuestos!$E$60*AP10) -> 220.22033 | AQ19: =IF(Supuestos!$B$25=1,AP19,Supuestos!$E$60*AQ10) -> 220.22033 | AR19: =IF(Supuestos!$B$25=1,AQ19,Supuestos!$E$60*AR10) -> 220.22033 | AS19: =IF(Supuestos!$B$25=1,AR19,Supuestos!$E$60*AS10) -> 220.22033 | AT19: =IF(Supuestos!$B$25=1,AS19,Supuestos!$E$60*AT10) -> 220.22033 | AU19: =IF(Supuestos!$B$25=1,AT19,Supuestos!$E$60*AU10) -> 220.22033 | ... AX19: =IF(Supuestos!$B$25=1,AW19,Supuestos!$E$60*AX10) -> 220.22033 | AY19: =IF(Supuestos!$B$25=1,AX19*(1+Supuestos!$F$18),Supuestos!$F$60*AY10) -> 237.16035 | AZ19: =IF(Supuestos!$B$25=1,AY19,Supuestos!$F$60*AZ10) -> 237.16035 | BA19: =IF(Supuestos!$B$25=1,AZ19,Supuestos!$F$60*BA10) -> 237.16035 | BB19: =IF(Supuestos!$B$25=1,BA19,Supuestos!$F$60*BB10) -> 237.16035 | BC19: =IF(Supuestos!$B$25=1,BB19,Supuestos!$F$60*BC10) -> 237.16035 | BD19: =IF(Supuestos!$B$25=1,BC19,Supuestos!$F$60*BD10) -> 237.16035 | BE19: =IF(Supuestos!$B$25=1,BD19,Supuestos!$F$60*BE10) -> 237.16035 | BF19: =IF(Supuestos!$B$25=1,BE19,Supuestos!$F$60*BF10) -> 237.16035 | BG19: =IF(Supuestos!$B$25=1,BF19,Supuestos!$F$60*BG10) -> 237.16035 | ... BJ19: =IF(Supuestos!$B$25=1,BI19,Supuestos!$F$60*BJ10) -> 237.16035 | BK19: =IF(Supuestos!$B$25=1,BJ19*(1+Supuestos!$G$18),Supuestos!$G$60*BK10) -> 242.80702 | BL19: =IF(Supuestos!$B$25=1,BK19,Supuestos!$G$60*BL10) -> 242.80702 | BM19: =IF(Supuestos!$B$25=1,BL19,Supuestos!$G$60*BM10) -> 242.80702 | BN19: =IF(Supuestos!$B$25=1,BM19,Supuestos!$G$60*BN10) -> 242.80702 | BO19: =IF(Supuestos!$B$25=1,BN19,Supuestos!$G$60*BO10) -> 242.80702 | BP19: =IF(Supuestos!$B$25=1,BO19,Supuestos!$G$60*BP10) -> 242.80702 | BQ19: =IF(Supuestos!$B$25=1,BP19,Supuestos!$G$60*BQ10) -> 242.80702 | BR19: =IF(Supuestos!$B$25=1,BQ19,Supuestos!$G$60*BR10) -> 242.80702 | BS19: =IF(Supuestos!$B$25=1,BR19,Supuestos!$G$60*BS10) -> 242.80702 | ... BV19: =IF(Supuestos!$B$25=1,BU19,Supuestos!$G$60*BV10) -> 242.80702 | BW19: =IF(Supuestos!$B$25=1,BV19*(1+Supuestos!$H$18),Supuestos!$H$60*BW10) -> 265.39372 | BX19: =IF(Supuestos!$B$25=1,BW19,Supuestos!$H$60*BX10) -> 265.39372 | BY19: =IF(Supuestos!$B$25=1,BX19,Supuestos!$H$60*BY10) -> 265.39372 | BZ19: =IF(Supuestos!$B$25=1,BY19,Supuestos!$H$60*BZ10) -> 265.39372 | CA19: =IF(Supuestos!$B$25=1,BZ19,Supuestos!$H$60*CA10) -> 265.39372 | CB19: =IF(Supuestos!$B$25=1,CA19,Supuestos!$H$60*CB10) -> 265.39372 | CC19: =IF(Supuestos!$B$25=1,CB19,Supuestos!$H$60*CC10) -> 265.39372 | CD19: =IF(Supuestos!$B$25=1,CC19,Supuestos!$H$60*CD10) -> 265.39372 | CE19: =IF(Supuestos!$B$25=1,CD19,Supuestos!$H$60*CE10) -> 265.39372 | ... CH19: =IF(Supuestos!$B$25=1,CG19,Supuestos!$H$60*CH10) -> 265.39372 | CI19: =IF(Supuestos!$B$25=1,CH19*(1+Supuestos!$I$18),Supuestos!$I$60*CI10) -> 282.33375 | CJ19: =IF(Supuestos!$B$25=1,CI19,Supuestos!$I$60*CJ10) -> 282.33375 | CK19: =IF(Supuestos!$B$25=1,CJ19,Supuestos!$I$60*CK10) -> 282.33375 | CL19: =IF(Supuestos!$B$25=1,CK19,Supuestos!$I$60*CL10) -> 282.33375 | CM19: =IF(Supuestos!$B$25=1,CL19,Supuestos!$I$60*CM10) -> 282.33375 | CN19: =IF(Supuestos!$B$25=1,CM19,Supuestos!$I$60*CN10) -> 282.33375 | CO19: =IF(Supuestos!$B$25=1,CN19,Supuestos!$I$60*CO10) -> 282.33375 | CP19: =IF(Supuestos!$B$25=1,CO19,Supuestos!$I$60*CP10) -> 282.33375 | CQ19: =IF(Supuestos!$B$25=1,CP19,Supuestos!$I$60*CQ10) -> 282.33375 | ... CT19: =IF(Supuestos!$B$25=1,CS19,Supuestos!$I$60*CT10) -> 282.33375 | CU19: =IF(Supuestos!$B$25=1,CT19*(1+Supuestos!$J$18),Supuestos!$J$60*CU10) -> 293.6271 | CV19: =IF(Supuestos!$B$25=1,CU19,Supuestos!$J$60*CV10) -> 293.6271 | CW19: =IF(Supuestos!$B$25=1,CV19,Supuestos!$J$60*CW10) -> 293.6271 | CX19: =IF(Supuestos!$B$25=1,CW19,Supuestos!$J$60*CX10) -> 293.6271 | CY19: =IF(Supuestos!$B$25=1,CX19,Supuestos!$J$60*CY10) -> 293.6271 | CZ19: =IF(Supuestos!$B$25=1,CY19,Supuestos!$J$60*CZ10) -> 293.6271 | DA19: =IF(Supuestos!$B$25=1,CZ19,Supuestos!$J$60*DA10) -> 293.6271 | DB19: =IF(Supuestos!$B$25=1,DA19,Supuestos!$J$60*DB10) -> 293.6271 | DC19: =IF(Supuestos!$B$25=1,DB19,Supuestos!$J$60*DC10) -> 293.6271 | ... DF19: =IF(Supuestos!$B$25=1,DE19,Supuestos!$J$60*DF10) -> 293.6271
A20: Otros gastos administrativos | B20: 2026: Supuestos fila 61 | C20: =Supuestos!B29 -> 188.76043 | D20: =Supuestos!C29 -> 178.79869 | E20: =Supuestos!D29 -> 169.81775 | F20: =Supuestos!E29 -> 194.14934 | G20: =Supuestos!F29 -> 103.13808 | H20: =Supuestos!G29 -> 205.85347 | I20: =Supuestos!H29 -> 224.18031 | J20: =Supuestos!I29 -> 342.99249 | ... N20: =Supuestos!M29 -> 342.99249 | O20: =Supuestos!$B$22*O10*Supuestos!$C$61 -> 302.83428 | P20: =Supuestos!$B$22*P10*Supuestos!$C$61 -> 255.13073 | Q20: =Supuestos!$B$22*Q10*Supuestos!$C$61 -> 274.95043 | R20: =Supuestos!$B$22*R10*Supuestos!$C$61 -> 265.98355 | S20: =Supuestos!$B$22*S10*Supuestos!$C$61 -> 301.15899 | T20: =Supuestos!$B$22*T10*Supuestos!$C$61 -> 234.04726 | U20: =Supuestos!$B$22*U10*Supuestos!$C$61 -> 306.61076 | V20: =Supuestos!$B$22*V10*Supuestos!$C$61 -> 337.88909 | ... Z20: =Supuestos!$B$22*Z10*Supuestos!$C$61 -> 161.38673 | AA20: =Supuestos!$B$22*AA10*Supuestos!$D$61 -> 318.8845 | AB20: =Supuestos!$B$22*AB10*Supuestos!$D$61 -> 268.65266 | AC20: =Supuestos!$B$22*AC10*Supuestos!$D$61 -> 289.5228 | AD20: =Supuestos!$B$22*AD10*Supuestos!$D$61 -> 280.08068 | AE20: =Supuestos!$B$22*AE10*Supuestos!$D$61 -> 317.12042 | AF20: =Supuestos!$B$22*AF10*Supuestos!$D$61 -> 246.45177 | AG20: =Supuestos!$B$22*AG10*Supuestos!$D$61 -> 320.53603 | AH20: =Supuestos!$B$22*AH10*Supuestos!$D$61 -> 355.79721 | ... AL20: =Supuestos!$B$22*AL10*Supuestos!$D$61 -> 169.94022 | AM20: =Supuestos!$B$22*AM10*Supuestos!$E$61 -> 371.50044 | AN20: =Supuestos!$B$22*AN10*Supuestos!$E$61 -> 312.98035 | AO20: =Supuestos!$B$22*AO10*Supuestos!$E$61 -> 337.29407 | AP20: =Supuestos!$B$22*AP10*Supuestos!$E$61 -> 326.29399 | AQ20: =Supuestos!$B$22*AQ10*Supuestos!$E$61 -> 369.44529 | AR20: =Supuestos!$B$22*AR10*Supuestos!$E$61 -> 287.11631 | AS20: =Supuestos!$B$22*AS10*Supuestos!$E$61 -> 373.42448 | AT20: =Supuestos!$B$22*AT10*Supuestos!$E$61 -> 414.50375 | ... AX20: =Supuestos!$B$22*AX10*Supuestos!$E$61 -> 197.98036 | AY20: =Supuestos!$B$22*AY10*Supuestos!$F$61 -> 430.94051 | AZ20: =Supuestos!$B$22*AZ10*Supuestos!$F$61 -> 363.0572 | BA20: =Supuestos!$B$22*BA10*Supuestos!$F$61 -> 391.26112 | BB20: =Supuestos!$B$22*BB10*Supuestos!$F$61 -> 378.50103 | BC20: =Supuestos!$B$22*BC10*Supuestos!$F$61 -> 428.55653 | BD20: =Supuestos!$B$22*BD10*Supuestos!$F$61 -> 333.05492 | BE20: =Supuestos!$B$22*BE10*Supuestos!$F$61 -> 433.17239 | BF20: =Supuestos!$B$22*BF10*Supuestos!$F$61 -> 480.82435 | ... BJ20: =Supuestos!$B$22*BJ10*Supuestos!$F$61 -> 229.65722 | BK20: =Supuestos!$B$22*BK10*Supuestos!$G$61 -> 497.73629 | BL20: =Supuestos!$B$22*BL10*Supuestos!$G$61 -> 419.33107 | BM20: =Supuestos!$B$22*BM10*Supuestos!$G$61 -> 451.90659 | BN20: =Supuestos!$B$22*BN10*Supuestos!$G$61 -> 437.16869 | BO20: =Supuestos!$B$22*BO10*Supuestos!$G$61 -> 494.9828 | BP20: =Supuestos!$B$22*BP10*Supuestos!$G$61 -> 384.67843 | BQ20: =Supuestos!$B$22*BQ10*Supuestos!$G$61 -> 500.31412 | BR20: =Supuestos!$B$22*BR10*Supuestos!$G$61 -> 555.35213 | ... BV20: =Supuestos!$B$22*BV10*Supuestos!$G$61 -> 265.25409 | BW20: =Supuestos!$B$22*BW10*Supuestos!$H$61 -> 535.89607 | BX20: =Supuestos!$B$22*BX10*Supuestos!$H$61 -> 451.47979 | BY20: =Supuestos!$B$22*BY10*Supuestos!$H$61 -> 486.55276 | BZ20: =Supuestos!$B$22*BZ10*Supuestos!$H$61 -> 470.68496 | CA20: =Supuestos!$B$22*CA10*Supuestos!$H$61 -> 532.93148 | CB20: =Supuestos!$B$22*CB10*Supuestos!$H$61 -> 414.17045 | CC20: =Supuestos!$B$22*CC10*Supuestos!$H$61 -> 538.67153 | CD20: =Supuestos!$B$22*CD10*Supuestos!$H$61 -> 597.92912 | ... CH20: =Supuestos!$B$22*CH10*Supuestos!$H$61 -> 285.59023 | CI20: =Supuestos!$B$22*CI10*Supuestos!$I$61 -> 610.92152 | CJ20: =Supuestos!$B$22*CJ10*Supuestos!$I$61 -> 514.68696 | CK20: =Supuestos!$B$22*CK10*Supuestos!$I$61 -> 554.67015 | CL20: =Supuestos!$B$22*CL10*Supuestos!$I$61 -> 536.58085 | CM20: =Supuestos!$B$22*CM10*Supuestos!$I$61 -> 607.54188 | CN20: =Supuestos!$B$22*CN10*Supuestos!$I$61 -> 472.15431 | CO20: =Supuestos!$B$22*CO10*Supuestos!$I$61 -> 614.08555 | CP20: =Supuestos!$B$22*CP10*Supuestos!$I$61 -> 681.6392 | ... CT20: =Supuestos!$B$22*CT10*Supuestos!$I$61 -> 325.57287 | CU20: =Supuestos!$B$22*CU10*Supuestos!$J$61 -> 696.45053 | CV20: =Supuestos!$B$22*CV10*Supuestos!$J$61 -> 586.74313 | CW20: =Supuestos!$B$22*CW10*Supuestos!$J$61 -> 632.32397 | CX20: =Supuestos!$B$22*CX10*Supuestos!$J$61 -> 611.70217 | CY20: =Supuestos!$B$22*CY10*Supuestos!$J$61 -> 692.59775 | CZ20: =Supuestos!$B$22*CZ10*Supuestos!$J$61 -> 538.25591 | DA20: =Supuestos!$B$22*DA10*Supuestos!$J$61 -> 700.05752 | DB20: =Supuestos!$B$22*DB10*Supuestos!$J$61 -> 777.06869 | ... DF20: =Supuestos!$B$22*DF10*Supuestos!$J$61 -> 371.15307
A21: Planilla comercial | B21: 2026: Supuestos fila 62 | C21: =Supuestos!B30 -> 430.5652 | D21: =Supuestos!C30 -> 434.00676 | E21: =Supuestos!D30 -> 435.05003 | F21: =Supuestos!E30 -> 394.4065 | G21: =Supuestos!F30 -> 408.76331 | H21: =Supuestos!G30 -> 434.1769 | I21: =Supuestos!H30 -> 469.19653 | J21: =Supuestos!I30 -> 451.61893 | ... N21: =Supuestos!M30 -> 451.61893 | O21: =IF(Supuestos!$B$25=1,N21*(1+Supuestos!$C$19),Supuestos!$C$62*O10) -> 507.48931 | P21: =IF(Supuestos!$B$25=1,O21,Supuestos!$C$62*P10) -> 507.48931 | Q21: =IF(Supuestos!$B$25=1,P21,Supuestos!$C$62*Q10) -> 507.48931 | R21: =IF(Supuestos!$B$25=1,Q21,Supuestos!$C$62*R10) -> 507.48931 | S21: =IF(Supuestos!$B$25=1,R21,Supuestos!$C$62*S10) -> 507.48931 | T21: =IF(Supuestos!$B$25=1,S21,Supuestos!$C$62*T10) -> 507.48931 | U21: =IF(Supuestos!$B$25=1,T21,Supuestos!$C$62*U10) -> 507.48931 | V21: =IF(Supuestos!$B$25=1,U21,Supuestos!$C$62*V10) -> 507.48931 | W21: =IF(Supuestos!$B$25=1,V21,Supuestos!$C$62*W10) -> 507.48931 | ... Z21: =IF(Supuestos!$B$25=1,Y21,Supuestos!$C$62*Z10) -> 507.48931 | AA21: =IF(Supuestos!$B$25=1,Z21*(1+Supuestos!$D$19),Supuestos!$D$62*AA10) -> 581.98316 | AB21: =IF(Supuestos!$B$25=1,AA21,Supuestos!$D$62*AB10) -> 581.98316 | AC21: =IF(Supuestos!$B$25=1,AB21,Supuestos!$D$62*AC10) -> 581.98316 | AD21: =IF(Supuestos!$B$25=1,AC21,Supuestos!$D$62*AD10) -> 581.98316 | AE21: =IF(Supuestos!$B$25=1,AD21,Supuestos!$D$62*AE10) -> 581.98316 | AF21: =IF(Supuestos!$B$25=1,AE21,Supuestos!$D$62*AF10) -> 581.98316 | AG21: =IF(Supuestos!$B$25=1,AF21,Supuestos!$D$62*AG10) -> 581.98316 | AH21: =IF(Supuestos!$B$25=1,AG21,Supuestos!$D$62*AH10) -> 581.98316 | AI21: =IF(Supuestos!$B$25=1,AH21,Supuestos!$D$62*AI10) -> 581.98316 | ... AL21: =IF(Supuestos!$B$25=1,AK21,Supuestos!$D$62*AL10) -> 581.98316 | AM21: =IF(Supuestos!$B$25=1,AL21*(1+Supuestos!$E$19),Supuestos!$E$62*AM10) -> 642.50941 | AN21: =IF(Supuestos!$B$25=1,AM21,Supuestos!$E$62*AN10) -> 642.50941 | AO21: =IF(Supuestos!$B$25=1,AN21,Supuestos!$E$62*AO10) -> 642.50941 | AP21: =IF(Supuestos!$B$25=1,AO21,Supuestos!$E$62*AP10) -> 642.50941 | AQ21: =IF(Supuestos!$B$25=1,AP21,Supuestos!$E$62*AQ10) -> 642.50941 | AR21: =IF(Supuestos!$B$25=1,AQ21,Supuestos!$E$62*AR10) -> 642.50941 | AS21: =IF(Supuestos!$B$25=1,AR21,Supuestos!$E$62*AS10) -> 642.50941 | AT21: =IF(Supuestos!$B$25=1,AS21,Supuestos!$E$62*AT10) -> 642.50941 | AU21: =IF(Supuestos!$B$25=1,AT21,Supuestos!$E$62*AU10) -> 642.50941 | ... AX21: =IF(Supuestos!$B$25=1,AW21,Supuestos!$E$62*AX10) -> 642.50941 | AY21: =IF(Supuestos!$B$25=1,AX21*(1+Supuestos!$F$19),Supuestos!$F$62*AY10) -> 693.72392 | AZ21: =IF(Supuestos!$B$25=1,AY21,Supuestos!$F$62*AZ10) -> 693.72392 | BA21: =IF(Supuestos!$B$25=1,AZ21,Supuestos!$F$62*BA10) -> 693.72392 | BB21: =IF(Supuestos!$B$25=1,BA21,Supuestos!$F$62*BB10) -> 693.72392 | BC21: =IF(Supuestos!$B$25=1,BB21,Supuestos!$F$62*BC10) -> 693.72392 | BD21: =IF(Supuestos!$B$25=1,BC21,Supuestos!$F$62*BD10) -> 693.72392 | BE21: =IF(Supuestos!$B$25=1,BD21,Supuestos!$F$62*BE10) -> 693.72392 | BF21: =IF(Supuestos!$B$25=1,BE21,Supuestos!$F$62*BF10) -> 693.72392 | BG21: =IF(Supuestos!$B$25=1,BF21,Supuestos!$F$62*BG10) -> 693.72392 | ... BJ21: =IF(Supuestos!$B$25=1,BI21,Supuestos!$F$62*BJ10) -> 693.72392 | BK21: =IF(Supuestos!$B$25=1,BJ21*(1+Supuestos!$G$19),Supuestos!$G$62*BK10) -> 744.93844 | BL21: =IF(Supuestos!$B$25=1,BK21,Supuestos!$G$62*BL10) -> 744.93844 | BM21: =IF(Supuestos!$B$25=1,BL21,Supuestos!$G$62*BM10) -> 744.93844 | BN21: =IF(Supuestos!$B$25=1,BM21,Supuestos!$G$62*BN10) -> 744.93844 | BO21: =IF(Supuestos!$B$25=1,BN21,Supuestos!$G$62*BO10) -> 744.93844 | BP21: =IF(Supuestos!$B$25=1,BO21,Supuestos!$G$62*BP10) -> 744.93844 | BQ21: =IF(Supuestos!$B$25=1,BP21,Supuestos!$G$62*BQ10) -> 744.93844 | BR21: =IF(Supuestos!$B$25=1,BQ21,Supuestos!$G$62*BR10) -> 744.93844 | BS21: =IF(Supuestos!$B$25=1,BR21,Supuestos!$G$62*BS10) -> 744.93844 | ... BV21: =IF(Supuestos!$B$25=1,BU21,Supuestos!$G$62*BV10) -> 744.93844 | BW21: =IF(Supuestos!$B$25=1,BV21*(1+Supuestos!$H$19),Supuestos!$H$62*BW10) -> 800.80882 | BX21: =IF(Supuestos!$B$25=1,BW21,Supuestos!$H$62*BX10) -> 800.80882 | BY21: =IF(Supuestos!$B$25=1,BX21,Supuestos!$H$62*BY10) -> 800.80882 | BZ21: =IF(Supuestos!$B$25=1,BY21,Supuestos!$H$62*BZ10) -> 800.80882 | CA21: =IF(Supuestos!$B$25=1,BZ21,Supuestos!$H$62*CA10) -> 800.80882 | CB21: =IF(Supuestos!$B$25=1,CA21,Supuestos!$H$62*CB10) -> 800.80882 | CC21: =IF(Supuestos!$B$25=1,CB21,Supuestos!$H$62*CC10) -> 800.80882 | CD21: =IF(Supuestos!$B$25=1,CC21,Supuestos!$H$62*CD10) -> 800.80882 | CE21: =IF(Supuestos!$B$25=1,CD21,Supuestos!$H$62*CE10) -> 800.80882 | ... CH21: =IF(Supuestos!$B$25=1,CG21,Supuestos!$H$62*CH10) -> 800.80882 | CI21: =IF(Supuestos!$B$25=1,CH21*(1+Supuestos!$I$19),Supuestos!$I$62*CI10) -> 847.36748 | CJ21: =IF(Supuestos!$B$25=1,CI21,Supuestos!$I$62*CJ10) -> 847.36748 | CK21: =IF(Supuestos!$B$25=1,CJ21,Supuestos!$I$62*CK10) -> 847.36748 | CL21: =IF(Supuestos!$B$25=1,CK21,Supuestos!$I$62*CL10) -> 847.36748 | CM21: =IF(Supuestos!$B$25=1,CL21,Supuestos!$I$62*CM10) -> 847.36748 | CN21: =IF(Supuestos!$B$25=1,CM21,Supuestos!$I$62*CN10) -> 847.36748 | CO21: =IF(Supuestos!$B$25=1,CN21,Supuestos!$I$62*CO10) -> 847.36748 | CP21: =IF(Supuestos!$B$25=1,CO21,Supuestos!$I$62*CP10) -> 847.36748 | CQ21: =IF(Supuestos!$B$25=1,CP21,Supuestos!$I$62*CQ10) -> 847.36748 | ... CT21: =IF(Supuestos!$B$25=1,CS21,Supuestos!$I$62*CT10) -> 847.36748 | CU21: =IF(Supuestos!$B$25=1,CT21*(1+Supuestos!$J$19),Supuestos!$J$62*CU10) -> 917.20546 | CV21: =IF(Supuestos!$B$25=1,CU21,Supuestos!$J$62*CV10) -> 917.20546 | CW21: =IF(Supuestos!$B$25=1,CV21,Supuestos!$J$62*CW10) -> 917.20546 | CX21: =IF(Supuestos!$B$25=1,CW21,Supuestos!$J$62*CX10) -> 917.20546 | CY21: =IF(Supuestos!$B$25=1,CX21,Supuestos!$J$62*CY10) -> 917.20546 | CZ21: =IF(Supuestos!$B$25=1,CY21,Supuestos!$J$62*CZ10) -> 917.20546 | DA21: =IF(Supuestos!$B$25=1,CZ21,Supuestos!$J$62*DA10) -> 917.20546 | DB21: =IF(Supuestos!$B$25=1,DA21,Supuestos!$J$62*DB10) -> 917.20546 | DC21: =IF(Supuestos!$B$25=1,DB21,Supuestos!$J$62*DC10) -> 917.20546 | ... DF21: =IF(Supuestos!$B$25=1,DE21,Supuestos!$J$62*DF10) -> 917.20546
A22: Otros gastos comerciales | B22: 2026: Supuestos fila 63 | C22: =Supuestos!B31 -> 459.12596 | D22: =Supuestos!C31 -> 360.89612 | E22: =Supuestos!D31 -> 334.86291 | F22: =Supuestos!E31 -> 432.30548 | G22: =Supuestos!F31 -> 591.7188 | H22: =Supuestos!G31 -> 847.21691 | I22: =Supuestos!H31 -> 517.1557 | J22: =Supuestos!I31 -> 611.0775 | ... N22: =Supuestos!M31 -> 611.0775 | O22: =Supuestos!$B$22*O10*Supuestos!$C$63 -> 681.37713 | P22: =Supuestos!$B$22*P10*Supuestos!$C$63 -> 574.04414 | Q22: =Supuestos!$B$22*Q10*Supuestos!$C$63 -> 618.63847 | R22: =Supuestos!$B$22*R10*Supuestos!$C$63 -> 598.46299 | S22: =Supuestos!$B$22*S10*Supuestos!$C$63 -> 677.60773 | T22: =Supuestos!$B$22*T10*Supuestos!$C$63 -> 526.60634 | U22: =Supuestos!$B$22*U10*Supuestos!$C$63 -> 689.8742 | V22: =Supuestos!$B$22*V10*Supuestos!$C$63 -> 760.25045 | ... Z22: =Supuestos!$B$22*Z10*Supuestos!$C$63 -> 363.12014 | AA22: =Supuestos!$B$22*AA10*Supuestos!$D$63 -> 779.49544 | AB22: =Supuestos!$B$22*AB10*Supuestos!$D$63 -> 656.7065 | AC22: =Supuestos!$B$22*AC10*Supuestos!$D$63 -> 707.72241 | AD22: =Supuestos!$B$22*AD10*Supuestos!$D$63 -> 684.64166 | AE22: =Supuestos!$B$22*AE10*Supuestos!$D$63 -> 775.18324 | AF22: =Supuestos!$B$22*AF10*Supuestos!$D$63 -> 602.43766 | AG22: =Supuestos!$B$22*AG10*Supuestos!$D$63 -> 783.53252 | AH22: =Supuestos!$B$22*AH10*Supuestos!$D$63 -> 869.72652 | ... AL22: =Supuestos!$B$22*AL10*Supuestos!$D$63 -> 415.40943 | AM22: =Supuestos!$B$22*AM10*Supuestos!$E$63 -> 887.47327 | AN22: =Supuestos!$B$22*AN10*Supuestos!$E$63 -> 747.67528 | AO22: =Supuestos!$B$22*AO10*Supuestos!$E$63 -> 805.75805 | AP22: =Supuestos!$B$22*AP10*Supuestos!$E$63 -> 779.48009 | AQ22: =Supuestos!$B$22*AQ10*Supuestos!$E$63 -> 882.56374 | AR22: =Supuestos!$B$22*AR10*Supuestos!$E$63 -> 685.88896 | AS22: =Supuestos!$B$22*AS10*Supuestos!$E$63 -> 892.06959 | AT22: =Supuestos!$B$22*AT10*Supuestos!$E$63 -> 990.20341 | ... AX22: =Supuestos!$B$22*AX10*Supuestos!$E$63 -> 472.95308 | AY22: =Supuestos!$B$22*AY10*Supuestos!$F$63 -> 981.58672 | AZ22: =Supuestos!$B$22*AZ10*Supuestos!$F$63 -> 826.96363 | BA22: =Supuestos!$B$22*BA10*Supuestos!$F$63 -> 891.20588 | BB22: =Supuestos!$B$22*BB10*Supuestos!$F$63 -> 862.14124 | BC22: =Supuestos!$B$22*BC10*Supuestos!$F$63 -> 976.15655 | BD22: =Supuestos!$B$22*BD10*Supuestos!$F$63 -> 758.6251 | BE22: =Supuestos!$B$22*BE10*Supuestos!$F$63 -> 986.67045 | BF22: =Supuestos!$B$22*BF10*Supuestos!$F$63 -> 1095.211 | ... BJ22: =Supuestos!$B$22*BJ10*Supuestos!$F$63 -> 523.10811 | BK22: =Supuestos!$B$22*BK10*Supuestos!$G$63 -> 1078.4286 | BL22: =Supuestos!$B$22*BL10*Supuestos!$G$63 -> 908.55065 | BM22: =Supuestos!$B$22*BM10*Supuestos!$G$63 -> 979.13095 | BN22: =Supuestos!$B$22*BN10*Supuestos!$G$63 -> 947.19883 | BO22: =Supuestos!$B$22*BO10*Supuestos!$G$63 -> 1072.4627 | BP22: =Supuestos!$B$22*BP10*Supuestos!$G$63 -> 833.46994 | BQ22: =Supuestos!$B$22*BQ10*Supuestos!$G$63 -> 1084.0139 | BR22: =Supuestos!$B$22*BR10*Supuestos!$G$63 -> 1203.2629 | ... BV22: =Supuestos!$B$22*BV10*Supuestos!$G$63 -> 574.71719 | BW22: =Supuestos!$B$22*BW10*Supuestos!$H$63 -> 1197.8853 | BX22: =Supuestos!$B$22*BX10*Supuestos!$H$63 -> 1009.1901 | BY22: =Supuestos!$B$22*BY10*Supuestos!$H$63 -> 1087.5885 | BZ22: =Supuestos!$B$22*BZ10*Supuestos!$H$63 -> 1052.1193 | CA22: =Supuestos!$B$22*CA10*Supuestos!$H$63 -> 1191.2586 | CB22: =Supuestos!$B$22*CB10*Supuestos!$H$63 -> 925.79276 | CC22: =Supuestos!$B$22*CC10*Supuestos!$H$63 -> 1204.0893 | CD22: =Supuestos!$B$22*CD10*Supuestos!$H$63 -> 1336.5475 | ... CH22: =Supuestos!$B$22*CH10*Supuestos!$H$63 -> 638.37817 | CI22: =Supuestos!$B$22*CI10*Supuestos!$I$63 -> 1329.6527 | CJ22: =Supuestos!$B$22*CJ10*Supuestos!$I$63 -> 1120.201 | CK22: =Supuestos!$B$22*CK10*Supuestos!$I$63 -> 1207.2233 | CL22: =Supuestos!$B$22*CL10*Supuestos!$I$63 -> 1167.8524 | CM22: =Supuestos!$B$22*CM10*Supuestos!$I$63 -> 1322.297 | CN22: =Supuestos!$B$22*CN10*Supuestos!$I$63 -> 1027.63 | CO22: =Supuestos!$B$22*CO10*Supuestos!$I$63 -> 1336.5391 | CP22: =Supuestos!$B$22*CP10*Supuestos!$I$63 -> 1483.5677 | ... CT22: =Supuestos!$B$22*CT10*Supuestos!$I$63 -> 708.59977 | CU22: =Supuestos!$B$22*CU10*Supuestos!$J$63 -> 1474.8364 | CV22: =Supuestos!$B$22*CV10*Supuestos!$J$63 -> 1242.5149 | CW22: =Supuestos!$B$22*CW10*Supuestos!$J$63 -> 1339.039 | CX22: =Supuestos!$B$22*CX10*Supuestos!$J$63 -> 1295.3693 | CY22: =Supuestos!$B$22*CY10*Supuestos!$J$63 -> 1466.6776 | CZ22: =Supuestos!$B$22*CZ10*Supuestos!$J$63 -> 1139.836 | DA22: =Supuestos!$B$22*DA10*Supuestos!$J$63 -> 1482.4748 | DB22: =Supuestos!$B$22*DB10*Supuestos!$J$63 -> 1645.5572 | ... DF22: =Supuestos!$B$22*DF10*Supuestos!$J$63 -> 785.9712
A23: Protestos | B23: Ventas × % Supuestos fila 58 | C23: =Supuestos!$B$58*C10 -> 49.849264 | D23: =Supuestos!$B$58*D10 -> 41.996828 | E23: =Supuestos!$B$58*E10 -> 45.25933 | F23: =Supuestos!$B$58*F10 -> 43.783301 | G23: =Supuestos!$B$58*G10 -> 49.573496 | H23: =Supuestos!$B$58*H10 -> 38.526299 | I23: =Supuestos!$B$58*I10 -> 50.107439 | J23: =Supuestos!$B$58*J10 -> 55.619603 | ... N23: =Supuestos!$B$58*N10 -> 26.565716 | O23: =Supuestos!$C$58*O10 -> 60.566856 | P23: =Supuestos!$C$58*P10 -> 51.026146 | Q23: =Supuestos!$C$58*Q10 -> 54.990086 | R23: =Supuestos!$C$58*R10 -> 53.19671 | S23: =Supuestos!$C$58*S10 -> 60.231798 | T23: =Supuestos!$C$58*T10 -> 46.809453 | U23: =Supuestos!$C$58*U10 -> 61.322151 | V23: =Supuestos!$C$58*V10 -> 67.577818 | ... Z23: =Supuestos!$C$58*Z10 -> 32.277345 | AA23: =Supuestos!$D$58*AA10 -> 70.863222 | AB23: =Supuestos!$D$58*AB10 -> 59.700591 | AC23: =Supuestos!$D$58*AC10 -> 64.338401 | AD23: =Supuestos!$D$58*AD10 -> 62.240151 | AE23: =Supuestos!$D$58*AE10 -> 70.471204 | AF23: =Supuestos!$D$58*AF10 -> 54.76706 | AG23: =Supuestos!$D$58*AG10 -> 71.230229 | AH23: =Supuestos!$D$58*AH10 -> 79.066047 | ... AL23: =Supuestos!$D$58*AL10 -> 37.764494 | AM23: =Supuestos!$E$58*AM10 -> 82.555653 | AN23: =Supuestos!$E$58*AN10 -> 69.551188 | AO23: =Supuestos!$E$58*AO10 -> 74.954237 | AP23: =Supuestos!$E$58*AP10 -> 72.509776 | AQ23: =Supuestos!$E$58*AQ10 -> 82.098953 | AR23: =Supuestos!$E$58*AR10 -> 63.803625 | AS23: =Supuestos!$E$58*AS10 -> 82.983217 | AT23: =Supuestos!$E$58*AT10 -> 92.111945 | ... AX23: =Supuestos!$E$58*AX10 -> 43.995636 | AY23: =Supuestos!$F$58*AY10 -> 95.764558 | AZ23: =Supuestos!$F$58*AZ10 -> 80.679379 | BA23: =Supuestos!$F$58*BA10 -> 86.946915 | BB23: =Supuestos!$F$58*BB10 -> 84.11134 | BC23: =Supuestos!$F$58*BC10 -> 95.234785 | BD23: =Supuestos!$F$58*BD10 -> 74.012205 | BE23: =Supuestos!$F$58*BE10 -> 96.260532 | BF23: =Supuestos!$F$58*BF10 -> 106.84986 | ... BJ23: =Supuestos!$F$58*BJ10 -> 51.034937 | BK23: =Supuestos!$G$58*BK10 -> 110.60806 | BL23: =Supuestos!$G$58*BL10 -> 93.184682 | BM23: =Supuestos!$G$58*BM10 -> 100.42369 | BN23: =Supuestos!$G$58*BN10 -> 97.148598 | BO23: =Supuestos!$G$58*BO10 -> 109.99618 | BP23: =Supuestos!$G$58*BP10 -> 85.484096 | BQ23: =Supuestos!$G$58*BQ10 -> 111.18091 | BR23: =Supuestos!$G$58*BR10 -> 123.41158 | ... BV23: =Supuestos!$G$58*BV10 -> 58.945353 | BW23: =Supuestos!$H$58*BW10 -> 126.09319 | BX23: =Supuestos!$H$58*BX10 -> 106.23054 | BY23: =Supuestos!$H$58*BY10 -> 114.483 | BZ23: =Supuestos!$H$58*BZ10 -> 110.7494 | CA23: =Supuestos!$H$58*CA10 -> 125.39564 | CB23: =Supuestos!$H$58*CB10 -> 97.45187 | CC23: =Supuestos!$H$58*CC10 -> 126.74624 | CD23: =Supuestos!$H$58*CD10 -> 140.68921 | ... CH23: =Supuestos!$H$58*CH10 -> 67.197702 | CI23: =Supuestos!$I$58*CI10 -> 143.74624 | CJ23: =Supuestos!$I$58*CJ10 -> 121.10281 | CK23: =Supuestos!$I$58*CK10 -> 130.51062 | CL23: =Supuestos!$I$58*CL10 -> 126.25432 | CM23: =Supuestos!$I$58*CM10 -> 142.95103 | CN23: =Supuestos!$I$58*CN10 -> 111.09513 | CO23: =Supuestos!$I$58*CO10 -> 144.49072 | CP23: =Supuestos!$I$58*CP10 -> 160.38569 | ... CT23: =Supuestos!$I$58*CT10 -> 76.60538 | CU23: =Supuestos!$J$58*CU10 -> 163.87071 | CV23: =Supuestos!$J$58*CV10 -> 138.05721 | CW23: =Supuestos!$J$58*CW10 -> 148.78211 | CX23: =Supuestos!$J$58*CX10 -> 143.92992 | CY23: =Supuestos!$J$58*CY10 -> 162.96418 | CZ23: =Supuestos!$J$58*CZ10 -> 126.64845 | DA23: =Supuestos!$J$58*DA10 -> 164.71942 | DB23: =Supuestos!$J$58*DB10 -> 182.83969 | ... DF23: =Supuestos!$J$58*DF10 -> 87.330133
A24: Alquileres nuevas sedes y máquinas | B24: Inversiones fila 25 ÷ 12 | C24: =Inversiones!$B$25/12/1000 -> 0 | D24: =Inversiones!$B$25/12/1000 -> 0 | E24: =Inversiones!$B$25/12/1000 -> 0 | F24: =Inversiones!$B$25/12/1000 -> 0 | G24: =Inversiones!$B$25/12/1000 -> 0 | H24: =Inversiones!$B$25/12/1000 -> 0 | I24: =Inversiones!$B$25/12/1000 -> 0 | J24: =Inversiones!$B$25/12/1000 -> 0 | ... N24: =Inversiones!$B$25/12/1000 -> 0 | O24: =Inversiones!$C$25/12/1000 -> 9 | P24: =Inversiones!$C$25/12/1000 -> 9 | Q24: =Inversiones!$C$25/12/1000 -> 9 | R24: =Inversiones!$C$25/12/1000 -> 9 | S24: =Inversiones!$C$25/12/1000 -> 9 | T24: =Inversiones!$C$25/12/1000 -> 9 | U24: =Inversiones!$C$25/12/1000 -> 9 | V24: =Inversiones!$C$25/12/1000 -> 9 | ... Z24: =Inversiones!$C$25/12/1000 -> 9 | AA24: =Inversiones!$D$25/12/1000 -> 22.375 | AB24: =Inversiones!$D$25/12/1000 -> 22.375 | AC24: =Inversiones!$D$25/12/1000 -> 22.375 | AD24: =Inversiones!$D$25/12/1000 -> 22.375 | AE24: =Inversiones!$D$25/12/1000 -> 22.375 | AF24: =Inversiones!$D$25/12/1000 -> 22.375 | AG24: =Inversiones!$D$25/12/1000 -> 22.375 | AH24: =Inversiones!$D$25/12/1000 -> 22.375 | ... AL24: =Inversiones!$D$25/12/1000 -> 22.375 | AM24: =Inversiones!$E$25/12/1000 -> 22.375 | AN24: =Inversiones!$E$25/12/1000 -> 22.375 | AO24: =Inversiones!$E$25/12/1000 -> 22.375 | AP24: =Inversiones!$E$25/12/1000 -> 22.375 | AQ24: =Inversiones!$E$25/12/1000 -> 22.375 | AR24: =Inversiones!$E$25/12/1000 -> 22.375 | AS24: =Inversiones!$E$25/12/1000 -> 22.375 | AT24: =Inversiones!$E$25/12/1000 -> 22.375 | ... AX24: =Inversiones!$E$25/12/1000 -> 22.375 | AY24: =Inversiones!$F$25/12/1000 -> 45.985 | AZ24: =Inversiones!$F$25/12/1000 -> 45.985 | BA24: =Inversiones!$F$25/12/1000 -> 45.985 | BB24: =Inversiones!$F$25/12/1000 -> 45.985 | BC24: =Inversiones!$F$25/12/1000 -> 45.985 | BD24: =Inversiones!$F$25/12/1000 -> 45.985 | BE24: =Inversiones!$F$25/12/1000 -> 45.985 | BF24: =Inversiones!$F$25/12/1000 -> 45.985 | ... BJ24: =Inversiones!$F$25/12/1000 -> 45.985 | BK24: =Inversiones!$G$25/12/1000 -> 50.485 | BL24: =Inversiones!$G$25/12/1000 -> 50.485 | BM24: =Inversiones!$G$25/12/1000 -> 50.485 | BN24: =Inversiones!$G$25/12/1000 -> 50.485 | BO24: =Inversiones!$G$25/12/1000 -> 50.485 | BP24: =Inversiones!$G$25/12/1000 -> 50.485 | BQ24: =Inversiones!$G$25/12/1000 -> 50.485 | BR24: =Inversiones!$G$25/12/1000 -> 50.485 | ... BV24: =Inversiones!$G$25/12/1000 -> 50.485 | BW24: =Inversiones!$H$25/12/1000 -> 50.485 | BX24: =Inversiones!$H$25/12/1000 -> 50.485 | BY24: =Inversiones!$H$25/12/1000 -> 50.485 | BZ24: =Inversiones!$H$25/12/1000 -> 50.485 | CA24: =Inversiones!$H$25/12/1000 -> 50.485 | CB24: =Inversiones!$H$25/12/1000 -> 50.485 | CC24: =Inversiones!$H$25/12/1000 -> 50.485 | CD24: =Inversiones!$H$25/12/1000 -> 50.485 | ... CH24: =Inversiones!$H$25/12/1000 -> 50.485 | CI24: =Inversiones!$I$25/12/1000 -> 50.485 | CJ24: =Inversiones!$I$25/12/1000 -> 50.485 | CK24: =Inversiones!$I$25/12/1000 -> 50.485 | CL24: =Inversiones!$I$25/12/1000 -> 50.485 | CM24: =Inversiones!$I$25/12/1000 -> 50.485 | CN24: =Inversiones!$I$25/12/1000 -> 50.485 | CO24: =Inversiones!$I$25/12/1000 -> 50.485 | CP24: =Inversiones!$I$25/12/1000 -> 50.485 | ... CT24: =Inversiones!$I$25/12/1000 -> 50.485 | CU24: =Inversiones!$J$25/12/1000 -> 50.485 | CV24: =Inversiones!$J$25/12/1000 -> 50.485 | CW24: =Inversiones!$J$25/12/1000 -> 50.485 | CX24: =Inversiones!$J$25/12/1000 -> 50.485 | CY24: =Inversiones!$J$25/12/1000 -> 50.485 | CZ24: =Inversiones!$J$25/12/1000 -> 50.485 | DA24: =Inversiones!$J$25/12/1000 -> 50.485 | DB24: =Inversiones!$J$25/12/1000 -> 50.485 | ... DF24: =Inversiones!$J$25/12/1000 -> 50.485
A25: TOTAL EGRESOS OPERATIVOS | B25: Suma de las 7 líneas | C25: =SUM(C18:C24) -> 11059.063 | D25: =SUM(D18:D24) -> 10600.464 | E25: =SUM(E18:E24) -> 11815.371 | F25: =SUM(F18:F24) -> 9486.1103 | G25: =SUM(G18:G24) -> 12083.715 | H25: =SUM(H18:H24) -> 13657.702 | I25: =SUM(I18:I24) -> 12841.753 | J25: =SUM(J18:J24) -> 13366.026 | ... DF25: =SUM(DF18:DF24) -> 34575.528
A27: 3. FLUJO OPERATIVO (1 − 2) | B27: Ingresos − egresos | C27: =C15-C25 -> -1935.2702 | D27: =D15-D25 -> -2536.6533 | E27: =E15-E25 -> 321.35426 | F27: =F15-F25 -> 1822.3759 | G27: =G15-G25 -> -368.47222 | H27: =H15-H25 -> -3378.1736 | I27: =I15-I25 -> -1470.1214 | J27: =J15-J25 -> 1439.924 | ... DF27: =DF15-DF25 -> -7655.8409
A28: % sobre ingresos | C28: =IF(C15=0,0,C27/C15) -> -0.21211247 | D28: =IF(D15=0,0,D27/D15) -> -0.31457251 | E28: =IF(E15=0,0,E27/E15) -> 0.02647784 | F28: =IF(F15=0,0,F27/F15) -> 0.16115118 | G28: =IF(G15=0,0,G27/G15) -> -0.031452376 | H28: =IF(H15=0,0,H27/H15) -> -0.32863117 | I28: =IF(I15=0,0,I27/I15) -> -0.12927972 | J28: =IF(J15=0,0,J27/J15) -> 0.097253067 | ... DF28: =IF(DF15=0,0,DF27/DF15) -> -0.28439561
A30: 4. INVERSIONES
A31: Inversión en activos | B31: Inversiones fila 16 × fila 61 | C31: =C61*Inversiones!$B$16/1000 -> 0 | D31: =D61*Inversiones!$B$16/1000 -> 0 | E31: =E61*Inversiones!$B$16/1000 -> 0 | F31: =F61*Inversiones!$B$16/1000 -> 0 | G31: =G61*Inversiones!$B$16/1000 -> 0 | H31: =H61*Inversiones!$B$16/1000 -> 0 | I31: =I61*Inversiones!$B$16/1000 -> 0 | J31: =J61*Inversiones!$B$16/1000 -> 0 | ... N31: =N61*Inversiones!$B$16/1000 -> 0 | O31: =O61*Inversiones!$C$16/1000 -> 1440 | P31: =P61*Inversiones!$C$16/1000 -> 0 | Q31: =Q61*Inversiones!$C$16/1000 -> 0 | R31: =R61*Inversiones!$C$16/1000 -> 0 | S31: =S61*Inversiones!$C$16/1000 -> 0 | T31: =T61*Inversiones!$C$16/1000 -> 0 | U31: =U61*Inversiones!$C$16/1000 -> 0 | V31: =V61*Inversiones!$C$16/1000 -> 0 | ... Z31: =Z61*Inversiones!$C$16/1000 -> 0 | AA31: =AA61*Inversiones!$D$16/1000 -> 570 | AB31: =AB61*Inversiones!$D$16/1000 -> 0 | AC31: =AC61*Inversiones!$D$16/1000 -> 0 | AD31: =AD61*Inversiones!$D$16/1000 -> 0 | AE31: =AE61*Inversiones!$D$16/1000 -> 0 | AF31: =AF61*Inversiones!$D$16/1000 -> 0 | AG31: =AG61*Inversiones!$D$16/1000 -> 0 | AH31: =AH61*Inversiones!$D$16/1000 -> 0 | ... AL31: =AL61*Inversiones!$D$16/1000 -> 0 | AM31: =AM61*Inversiones!$E$16/1000 -> 0 | AN31: =AN61*Inversiones!$E$16/1000 -> 0 | AO31: =AO61*Inversiones!$E$16/1000 -> 0 | AP31: =AP61*Inversiones!$E$16/1000 -> 0 | AQ31: =AQ61*Inversiones!$E$16/1000 -> 0 | AR31: =AR61*Inversiones!$E$16/1000 -> 0 | AS31: =AS61*Inversiones!$E$16/1000 -> 0 | AT31: =AT61*Inversiones!$E$16/1000 -> 0 | ... AX31: =AX61*Inversiones!$E$16/1000 -> 0 | AY31: =AY61*Inversiones!$F$16/1000 -> 200 | AZ31: =AZ61*Inversiones!$F$16/1000 -> 0 | BA31: =BA61*Inversiones!$F$16/1000 -> 0 | BB31: =BB61*Inversiones!$F$16/1000 -> 0 | BC31: =BC61*Inversiones!$F$16/1000 -> 0 | BD31: =BD61*Inversiones!$F$16/1000 -> 0 | BE31: =BE61*Inversiones!$F$16/1000 -> 0 | BF31: =BF61*Inversiones!$F$16/1000 -> 0 | ... BJ31: =BJ61*Inversiones!$F$16/1000 -> 0 | BK31: =BK61*Inversiones!$G$16/1000 -> 1050 | BL31: =BL61*Inversiones!$G$16/1000 -> 0 | BM31: =BM61*Inversiones!$G$16/1000 -> 0 | BN31: =BN61*Inversiones!$G$16/1000 -> 0 | BO31: =BO61*Inversiones!$G$16/1000 -> 0 | BP31: =BP61*Inversiones!$G$16/1000 -> 0 | BQ31: =BQ61*Inversiones!$G$16/1000 -> 0 | BR31: =BR61*Inversiones!$G$16/1000 -> 0 | ... BV31: =BV61*Inversiones!$G$16/1000 -> 0 | BW31: =BW61*Inversiones!$H$16/1000 -> 0 | BX31: =BX61*Inversiones!$H$16/1000 -> 0 | BY31: =BY61*Inversiones!$H$16/1000 -> 0 | BZ31: =BZ61*Inversiones!$H$16/1000 -> 0 | CA31: =CA61*Inversiones!$H$16/1000 -> 0 | CB31: =CB61*Inversiones!$H$16/1000 -> 0 | CC31: =CC61*Inversiones!$H$16/1000 -> 0 | CD31: =CD61*Inversiones!$H$16/1000 -> 0 | ... CH31: =CH61*Inversiones!$H$16/1000 -> 0 | CI31: =CI61*Inversiones!$I$16/1000 -> 0 | CJ31: =CJ61*Inversiones!$I$16/1000 -> 0 | CK31: =CK61*Inversiones!$I$16/1000 -> 0 | CL31: =CL61*Inversiones!$I$16/1000 -> 0 | CM31: =CM61*Inversiones!$I$16/1000 -> 0 | CN31: =CN61*Inversiones!$I$16/1000 -> 0 | CO31: =CO61*Inversiones!$I$16/1000 -> 0 | CP31: =CP61*Inversiones!$I$16/1000 -> 0 | ... CT31: =CT61*Inversiones!$I$16/1000 -> 0 | CU31: =CU61*Inversiones!$J$16/1000 -> 0 | CV31: =CV61*Inversiones!$J$16/1000 -> 0 | CW31: =CW61*Inversiones!$J$16/1000 -> 0 | CX31: =CX61*Inversiones!$J$16/1000 -> 0 | CY31: =CY61*Inversiones!$J$16/1000 -> 0 | CZ31: =CZ61*Inversiones!$J$16/1000 -> 0 | DA31: =DA61*Inversiones!$J$16/1000 -> 0 | DB31: =DB61*Inversiones!$J$16/1000 -> 0 | ... DF31: =DF61*Inversiones!$J$16/1000 -> 0
A33: 5. FINANCIAMIENTO
A34: (+) Desembolso de préstamos y leasing | B34: Deuda Mensual – Resumen | C34: ='Deuda Mensual'!C71 -> 0 | D34: ='Deuda Mensual'!D71 -> 0 | E34: ='Deuda Mensual'!E71 -> 0 | F34: ='Deuda Mensual'!F71 -> 0 | G34: ='Deuda Mensual'!G71 -> 0 | H34: ='Deuda Mensual'!H71 -> 0 | I34: ='Deuda Mensual'!I71 -> 0 | J34: ='Deuda Mensual'!J71 -> 0 | ... DF34: ='Deuda Mensual'!DF71 -> 0
A35: (−) Principal mediano plazo | B35: Deuda Mensual – Resumen | C35: ='Deuda Mensual'!C72 -> 0 | D35: ='Deuda Mensual'!D72 -> 0 | E35: ='Deuda Mensual'!E72 -> 0 | F35: ='Deuda Mensual'!F72 -> 0 | G35: ='Deuda Mensual'!G72 -> 0 | H35: ='Deuda Mensual'!H72 -> 0 | I35: ='Deuda Mensual'!I72 -> 0 | J35: ='Deuda Mensual'!J72 -> 0 | ... DF35: ='Deuda Mensual'!DF72 -> 0
A36: (−) Principal leasing | B36: Deuda Mensual – Resumen | C36: ='Deuda Mensual'!C73 -> 0 | D36: ='Deuda Mensual'!D73 -> 0 | E36: ='Deuda Mensual'!E73 -> 0 | F36: ='Deuda Mensual'!F73 -> 0 | G36: ='Deuda Mensual'!G73 -> 0 | H36: ='Deuda Mensual'!H73 -> 0 | I36: ='Deuda Mensual'!I73 -> 0 | J36: ='Deuda Mensual'!J73 -> 0 | ... DF36: ='Deuda Mensual'!DF73 -> 0
A37: (−) Intereses mediano plazo | B37: Deuda Mensual – Resumen | C37: ='Deuda Mensual'!C74 -> 0 | D37: ='Deuda Mensual'!D74 -> 0 | E37: ='Deuda Mensual'!E74 -> 0 | F37: ='Deuda Mensual'!F74 -> 0 | G37: ='Deuda Mensual'!G74 -> 0 | H37: ='Deuda Mensual'!H74 -> 0 | I37: ='Deuda Mensual'!I74 -> 0 | J37: ='Deuda Mensual'!J74 -> 0 | ... DF37: ='Deuda Mensual'!DF74 -> 0
A38: (−) Intereses leasing | B38: Deuda Mensual – Resumen | C38: ='Deuda Mensual'!C75 -> 0 | D38: ='Deuda Mensual'!D75 -> 0 | E38: ='Deuda Mensual'!E75 -> 0 | F38: ='Deuda Mensual'!F75 -> 0 | G38: ='Deuda Mensual'!G75 -> 0 | H38: ='Deuda Mensual'!H75 -> 0 | I38: ='Deuda Mensual'!I75 -> 0 | J38: ='Deuda Mensual'!J75 -> 0 | ... DF38: ='Deuda Mensual'!DF75 -> 0
A39: (−) IGV y otros cargos de cuotas | B39: Deuda Mensual – Resumen | C39: ='Deuda Mensual'!C76 -> 0 | D39: ='Deuda Mensual'!D76 -> 0 | E39: ='Deuda Mensual'!E76 -> 0 | F39: ='Deuda Mensual'!F76 -> 0 | G39: ='Deuda Mensual'!G76 -> 0 | H39: ='Deuda Mensual'!H76 -> 0 | I39: ='Deuda Mensual'!I76 -> 0 | J39: ='Deuda Mensual'!J76 -> 0 | ... DF39: ='Deuda Mensual'!DF76 -> 0
A40: (−) Gasto financiero por descuento de letras | B40: Fila 59 × (letras + cobranza libre) | C40: =C59*(C12+C13) -> 30.992802 | D40: =D59*(D12+D13) -> 44.207991 | E40: =E59*(E12+E13) -> 100.09725 | F40: =F59*(F12+F13) -> 87.625615 | G40: =G59*(G12+G13) -> 91.656107 | H40: =H59*(H12+H13) -> 84.161047 | I40: =I59*(I12+I13) -> 91.704228 | J40: =J59*(J12+J13) -> 95.624701 | ... DF40: =DF59*(DF12+DF13) -> 229.72265
A41: (−) Pagos préstamos CP y otros manuales | B41: Supuestos filas 45-54 | C41: =SUMIF(Supuestos!$B$45:$B$54,C$4,Supuestos!$C$45:$C$54) -> 0 | D41: =SUMIF(Supuestos!$B$45:$B$54,D$4,Supuestos!$C$45:$C$54) -> 0 | E41: =SUMIF(Supuestos!$B$45:$B$54,E$4,Supuestos!$C$45:$C$54) -> 500 | F41: =SUMIF(Supuestos!$B$45:$B$54,F$4,Supuestos!$C$45:$C$54) -> 500 | G41: =SUMIF(Supuestos!$B$45:$B$54,G$4,Supuestos!$C$45:$C$54) -> 200 | H41: =SUMIF(Supuestos!$B$45:$B$54,H$4,Supuestos!$C$45:$C$54) -> 0 | I41: =SUMIF(Supuestos!$B$45:$B$54,I$4,Supuestos!$C$45:$C$54) -> 0 | J41: =SUMIF(Supuestos!$B$45:$B$54,J$4,Supuestos!$C$45:$C$54) -> 0 | ... DF41: =SUMIF(Supuestos!$B$45:$B$54,DF$4,Supuestos!$C$45:$C$54) -> 0
A42: SERVICIO DE DEUDA | B42: Suma de principal a manuales | C42: =SUM(C35:C41) -> 30.992802 | D42: =SUM(D35:D41) -> 44.207991 | E42: =SUM(E35:E41) -> 600.09725 | F42: =SUM(F35:F41) -> 587.62562 | G42: =SUM(G35:G41) -> 291.65611 | H42: =SUM(H35:H41) -> 84.161047 | I42: =SUM(I35:I41) -> 91.704228 | J42: =SUM(J35:J41) -> 95.624701 | ... DF42: =SUM(DF35:DF41) -> 229.72265
A43: FINANCIAMIENTO NETO (desembolsos − servicio) | C43: =C34-C42 -> -30.992802 | D43: =D34-D42 -> -44.207991 | E43: =E34-E42 -> -600.09725 | F43: =F34-F42 -> -587.62562 | G43: =G34-G42 -> -291.65611 | H43: =H34-H42 -> -84.161047 | I43: =I34-I42 -> -91.704228 | J43: =J34-J42 -> -95.624701 | ... DF43: =DF34-DF42 -> -229.72265
A45: 6. FLUJO NETO DEL MES (3 − 4 + 5) | C45: =C27-C31+C43 -> -1966.263 | D45: =D27-D31+D43 -> -2580.8613 | E45: =E27-E31+E43 -> -278.74299 | F45: =F27-F31+F43 -> 1234.7503 | G45: =G27-G31+G43 -> -660.12833 | H45: =H27-H31+H43 -> -3462.3346 | I45: =I27-I31+I43 -> -1561.8256 | J45: =J27-J31+J43 -> 1344.2993 | ... DF45: =DF27-DF31+DF43 -> -7885.5636
A47: 7. CAJA
A48: Caja inicial | B48: Caja final del mes anterior | C48: =Supuestos!$B$24 -> 0 | D48: =C49 -> -1966.263 | E48: =D49 -> -4547.1243 | F48: =E49 -> -4825.8673 | G48: =F49 -> -3591.117 | H48: =G49 -> -4251.2454 | I48: =H49 -> -7713.58 | J48: =I49 -> -9275.4056 | K48: =J49 -> -7931.1063 | ... DF48: =DE49 -> 62189.723
A49: CAJA FINAL | B49: Caja inicial + flujo neto | C49: =C48+C45 -> -1966.263 | D49: =D48+D45 -> -4547.1243 | E49: =E48+E45 -> -4825.8673 | F49: =F48+F45 -> -3591.117 | G49: =G48+G45 -> -4251.2454 | H49: =H48+H45 -> -7713.58 | I49: =I48+I45 -> -9275.4056 | J49: =J48+J45 -> -7931.1063 | ... DF49: =DF48+DF45 -> 54304.159
A51: COBERTURAS
A52: Flujo operativo / Servicio de deuda | C52: =IF(C42=0,0,C27/C42) -> -62.44257 | D52: =IF(D42=0,0,D27/D42) -> -57.379973 | E52: =IF(E42=0,0,E27/E42) -> 0.53550364 | F52: =IF(F42=0,0,F27/F42) -> 3.1012533 | G52: =IF(G42=0,0,G27/G42) -> -1.2633791 | H52: =IF(H42=0,0,H27/H42) -> -40.139396 | I52: =IF(I42=0,0,I27/I42) -> -16.031119 | J52: =IF(J42=0,0,J27/J42) -> 15.058076 | ... DF52: =IF(DF42=0,0,DF27/DF42) -> -33.326452
A53: Caja final / Servicio de deuda | C53: =IF(C42=0,0,C49/C42) -> -63.44257 | D53: =IF(D42=0,0,D49/D42) -> -102.85752 | E53: =IF(E42=0,0,E49/E42) -> -8.0418088 | F53: =IF(F42=0,0,F49/F42) -> -6.111233 | G53: =IF(G42=0,0,G49/G42) -> -14.576226 | H53: =IF(H42=0,0,H49/H42) -> -91.652615 | I53: =IF(I42=0,0,I49/I42) -> -101.1448 | J53: =IF(J42=0,0,J49/J42) -> -82.939933 | ... DF53: =IF(DF42=0,0,DF49/DF42) -> 236.39009
A55: VERIFICACIONES (deben dar 0)
A56: Ingresos vs Motor Semanal fila 17 | C56: =ROUND(C15-SUM('Motor Semanal'!B17:F17),4) -> 0 | D56: =ROUND(D15-SUM('Motor Semanal'!G17:J17),4) -> 0 | E56: =ROUND(E15-SUM('Motor Semanal'!K17:O17),4) -> 0 | F56: =ROUND(F15-SUM('Motor Semanal'!P17:T17),4) -> 0 | G56: =ROUND(G15-SUM('Motor Semanal'!U17:Y17),4) -> 0 | H56: =ROUND(H15-SUM('Motor Semanal'!Z17:AD17),4) -> 0 | I56: =ROUND(I15-SUM('Motor Semanal'!AE17:AI17),4) -> 0 | J56: =ROUND(J15-SUM('Motor Semanal'!AJ17:AN17),4) -> 0 | K56: =ROUND(K15-SUM('Motor Semanal'!AO17:AS17),4) -> 0 | L56: =ROUND(L15-SUM('Motor Semanal'!AT17:AX17),4) -> 0 | M56: =ROUND(M15-SUM('Motor Semanal'!AY17:BC17),4) -> 0 | N56: =ROUND(N15-SUM('Motor Semanal'!BD17:BH17),4) -> 0 | O56: =ROUND(O15-SUM('Motor Semanal'!BI17:BM17),4) -> 0 | P56: =ROUND(P15-SUM('Motor Semanal'!BN17:BQ17),4) -> 0 | Q56: =ROUND(Q15-SUM('Motor Semanal'!BR17:BV17),4) -> 0 | R56: =ROUND(R15-SUM('Motor Semanal'!BW17:CA17),4) -> 0 | S56: =ROUND(S15-SUM('Motor Semanal'!CB17:CF17),4) -> 0 | T56: =ROUND(T15-SUM('Motor Semanal'!CG17:CK17),4) -> 0 | U56: =ROUND(U15-SUM('Motor Semanal'!CL17:CP17),4) -> 0 | V56: =ROUND(V15-SUM('Motor Semanal'!CQ17:CU17),4) -> 0 | W56: =ROUND(W15-SUM('Motor Semanal'!CV17:CZ17),4) -> 0 | X56: =ROUND(X15-SUM('Motor Semanal'!DA17:DE17),4) -> 0 | Y56: =ROUND(Y15-SUM('Motor Semanal'!DF17:DJ17),4) -> 0 | Z56: =ROUND(Z15-SUM('Motor Semanal'!DK17:DO17),4) -> 0 | AA56: =ROUND(AA15-SUM('Motor Semanal'!DP17:DT17),4) -> 0 | AB56: =ROUND(AB15-SUM('Motor Semanal'!DU17:DY17),4) -> 0 | AC56: =ROUND(AC15-SUM('Motor Semanal'!DZ17:ED17),4) -> 0 | AD56: =ROUND(AD15-SUM('Motor Semanal'!EE17:EI17),4) -> 0 | AE56: =ROUND(AE15-SUM('Motor Semanal'!EJ17:EN17),4) -> 0 | AF56: =ROUND(AF15-SUM('Motor Semanal'!EO17:ES17),4) -> 0 | AG56: =ROUND(AG15-SUM('Motor Semanal'!ET17:EX17),4) -> 0 | AH56: =ROUND(AH15-SUM('Motor Semanal'!EY17:FC17),4) -> 0 | AI56: =ROUND(AI15-SUM('Motor Semanal'!FD17:FH17),4) -> 0 | AJ56: =ROUND(AJ15-SUM('Motor Semanal'!FI17:FM17),4) -> 0 | AK56: =ROUND(AK15-SUM('Motor Semanal'!FN17:FR17),4) -> 0 | AL56: =ROUND(AL15-SUM('Motor Semanal'!FS17:FW17),4) -> 0 | AM56: =ROUND(AM15-SUM('Motor Semanal'!FX17:GB17),4) -> 0 | AN56: =ROUND(AN15-SUM('Motor Semanal'!GC17:GF17),4) -> 0 | AO56: =ROUND(AO15-SUM('Motor Semanal'!GG17:GK17),4) -> 0 | AP56: =ROUND(AP15-SUM('Motor Semanal'!GL17:GP17),4) -> 0 | AQ56: =ROUND(AQ15-SUM('Motor Semanal'!GQ17:GU17),4) -> 0 | AR56: =ROUND(AR15-SUM('Motor Semanal'!GV17:GZ17),4) -> 0 | AS56: =ROUND(AS15-SUM('Motor Semanal'!HA17:HE17),4) -> 0 | AT56: =ROUND(AT15-SUM('Motor Semanal'!HF17:HJ17),4) -> 0 | AU56: =ROUND(AU15-SUM('Motor Semanal'!HK17:HO17),4) -> 0 | AV56: =ROUND(AV15-SUM('Motor Semanal'!HP17:HT17),4) -> 0 | AW56: =ROUND(AW15-SUM('Motor Semanal'!HU17:HY17),4) -> 0 | AX56: =ROUND(AX15-SUM('Motor Semanal'!HZ17:ID17),4) -> 0 | AY56: =ROUND(AY15-SUM('Motor Semanal'!IE17:II17),4) -> 0 | AZ56: =ROUND(AZ15-SUM('Motor Semanal'!IJ17:IM17),4) -> 0 | BA56: =ROUND(BA15-SUM('Motor Semanal'!IN17:IR17),4) -> 0 | BB56: =ROUND(BB15-SUM('Motor Semanal'!IS17:IW17),4) -> 0 | BC56: =ROUND(BC15-SUM('Motor Semanal'!IX17:JB17),4) -> 0 | BD56: =ROUND(BD15-SUM('Motor Semanal'!JC17:JG17),4) -> 0 | BE56: =ROUND(BE15-SUM('Motor Semanal'!JH17:JL17),4) -> 0 | BF56: =ROUND(BF15-SUM('Motor Semanal'!JM17:JQ17),4) -> 0 | BG56: =ROUND(BG15-SUM('Motor Semanal'!JR17:JV17),4) -> 0 | BH56: =ROUND(BH15-SUM('Motor Semanal'!JW17:KA17),4) -> 0 | BI56: =ROUND(BI15-SUM('Motor Semanal'!KB17:KF17),4) -> 0 | BJ56: =ROUND(BJ15-SUM('Motor Semanal'!KG17:KK17),4) -> 0 | BK56: =ROUND(BK15-SUM('Motor Semanal'!KL17:KP17),4) -> 0 | BL56: =ROUND(BL15-SUM('Motor Semanal'!KQ17:KT17),4) -> 0 | BM56: =ROUND(BM15-SUM('Motor Semanal'!KU17:KY17),4) -> 0 | BN56: =ROUND(BN15-SUM('Motor Semanal'!KZ17:LD17),4) -> 0 | BO56: =ROUND(BO15-SUM('Motor Semanal'!LE17:LI17),4) -> 0 | BP56: =ROUND(BP15-SUM('Motor Semanal'!LJ17:LN17),4) -> 0 | BQ56: =ROUND(BQ15-SUM('Motor Semanal'!LO17:LS17),4) -> 0 | BR56: =ROUND(BR15-SUM('Motor Semanal'!LT17:LX17),4) -> 0 | BS56: =ROUND(BS15-SUM('Motor Semanal'!LY17:MC17),4) -> 0 | BT56: =ROUND(BT15-SUM('Motor Semanal'!MD17:MH17),4) -> 0 | BU56: =ROUND(BU15-SUM('Motor Semanal'!MI17:MM17),4) -> 0 | BV56: =ROUND(BV15-SUM('Motor Semanal'!MN17:MR17),4) -> 0 | BW56: =ROUND(BW15-SUM('Motor Semanal'!MS17:MW17),4) -> 0 | BX56: =ROUND(BX15-SUM('Motor Semanal'!MX17:NB17),4) -> 0 | BY56: =ROUND(BY15-SUM('Motor Semanal'!NC17:NG17),4) -> 0 | BZ56: =ROUND(BZ15-SUM('Motor Semanal'!NH17:NL17),4) -> 0 | CA56: =ROUND(CA15-SUM('Motor Semanal'!NM17:NQ17),4) -> 0 | CB56: =ROUND(CB15-SUM('Motor Semanal'!NR17:NV17),4) -> 0 | CC56: =ROUND(CC15-SUM('Motor Semanal'!NW17:OA17),4) -> 0 | CD56: =ROUND(CD15-SUM('Motor Semanal'!OB17:OF17),4) -> 0 | CE56: =ROUND(CE15-SUM('Motor Semanal'!OG17:OK17),4) -> 0 | CF56: =ROUND(CF15-SUM('Motor Semanal'!OL17:OP17),4) -> 0 | CG56: =ROUND(CG15-SUM('Motor Semanal'!OQ17:OU17),4) -> 0 | CH56: =ROUND(CH15-SUM('Motor Semanal'!OV17:OZ17),4) -> 0 | CI56: =ROUND(CI15-SUM('Motor Semanal'!PA17:PE17),4) -> 0 | CJ56: =ROUND(CJ15-SUM('Motor Semanal'!PF17:PI17),4) -> 0 | CK56: =ROUND(CK15-SUM('Motor Semanal'!PJ17:PN17),4) -> 0 | CL56: =ROUND(CL15-SUM('Motor Semanal'!PO17:PS17),4) -> 0 | CM56: =ROUND(CM15-SUM('Motor Semanal'!PT17:PX17),4) -> 0 | CN56: =ROUND(CN15-SUM('Motor Semanal'!PY17:QC17),4) -> 0 | CO56: =ROUND(CO15-SUM('Motor Semanal'!QD17:QH17),4) -> 0 | CP56: =ROUND(CP15-SUM('Motor Semanal'!QI17:QM17),4) -> 0 | CQ56: =ROUND(CQ15-SUM('Motor Semanal'!QN17:QR17),4) -> 0 | CR56: =ROUND(CR15-SUM('Motor Semanal'!QS17:QW17),4) -> 0 | CS56: =ROUND(CS15-SUM('Motor Semanal'!QX17:RB17),4) -> 0 | CT56: =ROUND(CT15-SUM('Motor Semanal'!RC17:RG17),4) -> 0 | CU56: =ROUND(CU15-SUM('Motor Semanal'!RH17:RL17),4) -> 0 | CV56: =ROUND(CV15-SUM('Motor Semanal'!RM17:RP17),4) -> 0 | CW56: =ROUND(CW15-SUM('Motor Semanal'!RQ17:RU17),4) -> 0 | CX56: =ROUND(CX15-SUM('Motor Semanal'!RV17:RZ17),4) -> 0 | CY56: =ROUND(CY15-SUM('Motor Semanal'!SA17:SE17),4) -> 0 | CZ56: =ROUND(CZ15-SUM('Motor Semanal'!SF17:SJ17),4) -> 0 | DA56: =ROUND(DA15-SUM('Motor Semanal'!SK17:SO17),4) -> 0 | DB56: =ROUND(DB15-SUM('Motor Semanal'!SP17:ST17),4) -> 0 | DC56: =ROUND(DC15-SUM('Motor Semanal'!SU17:SY17),4) -> 0 | DD56: =ROUND(DD15-SUM('Motor Semanal'!SZ17:TD17),4) -> 0 | DE56: =ROUND(DE15-SUM('Motor Semanal'!TE17:TI17),4) -> 0 | DF56: =ROUND(DF15-SUM('Motor Semanal'!TJ17:TN17),4) -> 0
A58: PARÁMETROS POR MES (el supuesto del año que se usa en cada mes)
A59: Tasa del mes por descuento de letras | B59: Supuestos B23 y días del mes | C59: =(1+Supuestos!$B$23)^(C7/360)-1 -> 0.019400938 | D59: =(1+Supuestos!$B$23)^(D7/360)-1 -> 0.017507093 | E59: =(1+Supuestos!$B$23)^(E7/360)-1 -> 0.019400938 | F59: =(1+Supuestos!$B$23)^(F7/360)-1 -> 0.018769265 | G59: =(1+Supuestos!$B$23)^(G7/360)-1 -> 0.019400938 | H59: =(1+Supuestos!$B$23)^(H7/360)-1 -> 0.018769265 | I59: =(1+Supuestos!$B$23)^(I7/360)-1 -> 0.019400938 | J59: =(1+Supuestos!$B$23)^(J7/360)-1 -> 0.019400938 | ... DF59: =(1+Supuestos!$B$23)^(DF7/360)-1 -> 0.019400938
A60: % compras / ventas (se aplica a ventas 2 meses después) | B60: Supuestos fila 17 | C60: =Supuestos!$B$17 -> 0.860824 | D60: =Supuestos!$B$17 -> 0.860824 | E60: =Supuestos!$B$17 -> 0.860824 | F60: =Supuestos!$B$17 -> 0.860824 | G60: =Supuestos!$B$17 -> 0.860824 | H60: =Supuestos!$B$17 -> 0.860824 | I60: =Supuestos!$B$17 -> 0.860824 | J60: =Supuestos!$B$17 -> 0.860824 | ... L60: =Supuestos!$B$17 -> 0.860824 | M60: =Supuestos!$C$17 -> 0.860848 | N60: =Supuestos!$C$17 -> 0.860848 | O60: =Supuestos!$C$17 -> 0.860848 | P60: =Supuestos!$C$17 -> 0.860848 | Q60: =Supuestos!$C$17 -> 0.860848 | R60: =Supuestos!$C$17 -> 0.860848 | S60: =Supuestos!$C$17 -> 0.860848 | T60: =Supuestos!$C$17 -> 0.860848 | ... X60: =Supuestos!$C$17 -> 0.860848 | Y60: =Supuestos!$D$17 -> 0.853357 | Z60: =Supuestos!$D$17 -> 0.853357 | AA60: =Supuestos!$D$17 -> 0.853357 | AB60: =Supuestos!$D$17 -> 0.853357 | AC60: =Supuestos!$D$17 -> 0.853357 | AD60: =Supuestos!$D$17 -> 0.853357 | AE60: =Supuestos!$D$17 -> 0.853357 | AF60: =Supuestos!$D$17 -> 0.853357 | ... AJ60: =Supuestos!$D$17 -> 0.853357 | AK60: =Supuestos!$E$17 -> 0.845307 | AL60: =Supuestos!$E$17 -> 0.845307 | AM60: =Supuestos!$E$17 -> 0.845307 | AN60: =Supuestos!$E$17 -> 0.845307 | AO60: =Supuestos!$E$17 -> 0.845307 | AP60: =Supuestos!$E$17 -> 0.845307 | AQ60: =Supuestos!$E$17 -> 0.845307 | AR60: =Supuestos!$E$17 -> 0.845307 | ... AV60: =Supuestos!$E$17 -> 0.845307 | AW60: =Supuestos!$F$17 -> 0.837261 | AX60: =Supuestos!$F$17 -> 0.837261 | AY60: =Supuestos!$F$17 -> 0.837261 | AZ60: =Supuestos!$F$17 -> 0.837261 | BA60: =Supuestos!$F$17 -> 0.837261 | BB60: =Supuestos!$F$17 -> 0.837261 | BC60: =Supuestos!$F$17 -> 0.837261 | BD60: =Supuestos!$F$17 -> 0.837261 | ... BH60: =Supuestos!$F$17 -> 0.837261 | BI60: =Supuestos!$G$17 -> 0.831712 | BJ60: =Supuestos!$G$17 -> 0.831712 | BK60: =Supuestos!$G$17 -> 0.831712 | BL60: =Supuestos!$G$17 -> 0.831712 | BM60: =Supuestos!$G$17 -> 0.831712 | BN60: =Supuestos!$G$17 -> 0.831712 | BO60: =Supuestos!$G$17 -> 0.831712 | BP60: =Supuestos!$G$17 -> 0.831712 | ... BT60: =Supuestos!$G$17 -> 0.831712 | BU60: =Supuestos!$H$17 -> 0.826162 | BV60: =Supuestos!$H$17 -> 0.826162 | BW60: =Supuestos!$H$17 -> 0.826162 | BX60: =Supuestos!$H$17 -> 0.826162 | BY60: =Supuestos!$H$17 -> 0.826162 | BZ60: =Supuestos!$H$17 -> 0.826162 | CA60: =Supuestos!$H$17 -> 0.826162 | CB60: =Supuestos!$H$17 -> 0.826162 | ... CF60: =Supuestos!$H$17 -> 0.826162 | CG60: =Supuestos!$I$17 -> 0.820613 | CH60: =Supuestos!$I$17 -> 0.820613 | CI60: =Supuestos!$I$17 -> 0.820613 | CJ60: =Supuestos!$I$17 -> 0.820613 | CK60: =Supuestos!$I$17 -> 0.820613 | CL60: =Supuestos!$I$17 -> 0.820613 | CM60: =Supuestos!$I$17 -> 0.820613 | CN60: =Supuestos!$I$17 -> 0.820613 | ... CR60: =Supuestos!$I$17 -> 0.820613 | CS60: =Supuestos!$J$17 -> 0.815064 | CT60: =Supuestos!$J$17 -> 0.815064 | CU60: =Supuestos!$J$17 -> 0.815064 | CV60: =Supuestos!$J$17 -> 0.815064 | CW60: =Supuestos!$J$17 -> 0.815064 | CX60: =Supuestos!$J$17 -> 0.815064 | CY60: =Supuestos!$J$17 -> 0.815064 | CZ60: =Supuestos!$J$17 -> 0.815064 | ... DF60: =Supuestos!$J$17 -> 0.815064
A61: ¿Mes de pago de inversión? (1 = sí) | B61: Supuestos fila 20 | C61: =IF(C$6=Supuestos!$B$20,1,0) -> 0 | D61: =IF(D$6=Supuestos!$B$20,1,0) -> 0 | E61: =IF(E$6=Supuestos!$B$20,1,0) -> 0 | F61: =IF(F$6=Supuestos!$B$20,1,0) -> 0 | G61: =IF(G$6=Supuestos!$B$20,1,0) -> 0 | H61: =IF(H$6=Supuestos!$B$20,1,0) -> 0 | I61: =IF(I$6=Supuestos!$B$20,1,0) -> 0 | J61: =IF(J$6=Supuestos!$B$20,1,0) -> 0 | ... N61: =IF(N$6=Supuestos!$B$20,1,0) -> 0 | O61: =IF(O$6=Supuestos!$C$20,1,0) -> 1 | P61: =IF(P$6=Supuestos!$C$20,1,0) -> 0 | Q61: =IF(Q$6=Supuestos!$C$20,1,0) -> 0 | R61: =IF(R$6=Supuestos!$C$20,1,0) -> 0 | S61: =IF(S$6=Supuestos!$C$20,1,0) -> 0 | T61: =IF(T$6=Supuestos!$C$20,1,0) -> 0 | U61: =IF(U$6=Supuestos!$C$20,1,0) -> 0 | V61: =IF(V$6=Supuestos!$C$20,1,0) -> 0 | ... Z61: =IF(Z$6=Supuestos!$C$20,1,0) -> 0 | AA61: =IF(AA$6=Supuestos!$D$20,1,0) -> 1 | AB61: =IF(AB$6=Supuestos!$D$20,1,0) -> 0 | AC61: =IF(AC$6=Supuestos!$D$20,1,0) -> 0 | AD61: =IF(AD$6=Supuestos!$D$20,1,0) -> 0 | AE61: =IF(AE$6=Supuestos!$D$20,1,0) -> 0 | AF61: =IF(AF$6=Supuestos!$D$20,1,0) -> 0 | AG61: =IF(AG$6=Supuestos!$D$20,1,0) -> 0 | AH61: =IF(AH$6=Supuestos!$D$20,1,0) -> 0 | ... AL61: =IF(AL$6=Supuestos!$D$20,1,0) -> 0 | AM61: =IF(AM$6=Supuestos!$E$20,1,0) -> 1 | AN61: =IF(AN$6=Supuestos!$E$20,1,0) -> 0 | AO61: =IF(AO$6=Supuestos!$E$20,1,0) -> 0 | AP61: =IF(AP$6=Supuestos!$E$20,1,0) -> 0 | AQ61: =IF(AQ$6=Supuestos!$E$20,1,0) -> 0 | AR61: =IF(AR$6=Supuestos!$E$20,1,0) -> 0 | AS61: =IF(AS$6=Supuestos!$E$20,1,0) -> 0 | AT61: =IF(AT$6=Supuestos!$E$20,1,0) -> 0 | ... AX61: =IF(AX$6=Supuestos!$E$20,1,0) -> 0 | AY61: =IF(AY$6=Supuestos!$F$20,1,0) -> 1 | AZ61: =IF(AZ$6=Supuestos!$F$20,1,0) -> 0 | BA61: =IF(BA$6=Supuestos!$F$20,1,0) -> 0 | BB61: =IF(BB$6=Supuestos!$F$20,1,0) -> 0 | BC61: =IF(BC$6=Supuestos!$F$20,1,0) -> 0 | BD61: =IF(BD$6=Supuestos!$F$20,1,0) -> 0 | BE61: =IF(BE$6=Supuestos!$F$20,1,0) -> 0 | BF61: =IF(BF$6=Supuestos!$F$20,1,0) -> 0 | ... BJ61: =IF(BJ$6=Supuestos!$F$20,1,0) -> 0 | BK61: =IF(BK$6=Supuestos!$G$20,1,0) -> 1 | BL61: =IF(BL$6=Supuestos!$G$20,1,0) -> 0 | BM61: =IF(BM$6=Supuestos!$G$20,1,0) -> 0 | BN61: =IF(BN$6=Supuestos!$G$20,1,0) -> 0 | BO61: =IF(BO$6=Supuestos!$G$20,1,0) -> 0 | BP61: =IF(BP$6=Supuestos!$G$20,1,0) -> 0 | BQ61: =IF(BQ$6=Supuestos!$G$20,1,0) -> 0 | BR61: =IF(BR$6=Supuestos!$G$20,1,0) -> 0 | ... BV61: =IF(BV$6=Supuestos!$G$20,1,0) -> 0 | BW61: =IF(BW$6=Supuestos!$H$20,1,0) -> 1 | BX61: =IF(BX$6=Supuestos!$H$20,1,0) -> 0 | BY61: =IF(BY$6=Supuestos!$H$20,1,0) -> 0 | BZ61: =IF(BZ$6=Supuestos!$H$20,1,0) -> 0 | CA61: =IF(CA$6=Supuestos!$H$20,1,0) -> 0 | CB61: =IF(CB$6=Supuestos!$H$20,1,0) -> 0 | CC61: =IF(CC$6=Supuestos!$H$20,1,0) -> 0 | CD61: =IF(CD$6=Supuestos!$H$20,1,0) -> 0 | ... CH61: =IF(CH$6=Supuestos!$H$20,1,0) -> 0 | CI61: =IF(CI$6=Supuestos!$I$20,1,0) -> 1 | CJ61: =IF(CJ$6=Supuestos!$I$20,1,0) -> 0 | CK61: =IF(CK$6=Supuestos!$I$20,1,0) -> 0 | CL61: =IF(CL$6=Supuestos!$I$20,1,0) -> 0 | CM61: =IF(CM$6=Supuestos!$I$20,1,0) -> 0 | CN61: =IF(CN$6=Supuestos!$I$20,1,0) -> 0 | CO61: =IF(CO$6=Supuestos!$I$20,1,0) -> 0 | CP61: =IF(CP$6=Supuestos!$I$20,1,0) -> 0 | ... CT61: =IF(CT$6=Supuestos!$I$20,1,0) -> 0 | CU61: =IF(CU$6=Supuestos!$J$20,1,0) -> 1 | CV61: =IF(CV$6=Supuestos!$J$20,1,0) -> 0 | CW61: =IF(CW$6=Supuestos!$J$20,1,0) -> 0 | CX61: =IF(CX$6=Supuestos!$J$20,1,0) -> 0 | CY61: =IF(CY$6=Supuestos!$J$20,1,0) -> 0 | CZ61: =IF(CZ$6=Supuestos!$J$20,1,0) -> 0 | DA61: =IF(DA$6=Supuestos!$J$20,1,0) -> 0 | DB61: =IF(DB$6=Supuestos!$J$20,1,0) -> 0 | ... DF61: =IF(DF$6=Supuestos!$J$20,1,0) -> 0

Sheet Motor Semanal
B1: =TEXT(B7,"MMM-YY") -> Ene-26 | C1: =TEXT(C7,"MMM-YY") -> Ene-26 | D1: =TEXT(D7,"MMM-YY") -> Ene-26 | E1: =TEXT(E7,"MMM-YY") -> Ene-26 | F1: =TEXT(F7,"MMM-YY") -> Ene-26 | G1: =TEXT(G7,"MMM-YY") -> Feb-26 | H1: =TEXT(H7,"MMM-YY") -> Feb-26 | I1: =TEXT(I7,"MMM-YY") -> Feb-26 | ... TN1: =TEXT(TN7,"MMM-YY") -> Dic-34
A2: MOTOR SEMANAL – ventas → cobranza (alimenta Flujo Mensual) · Unidad: miles de soles (S/000) | BH2: =BH4+BC4+AX4+AS4+AN4+AI4+AD4+Y4+T4+O4+J4+F4 -> 140027.51 | DO2: =BH2*(Supuestos!$C$2+1) -> 170133.43 | FW2: =DO2*(Supuestos!$D$2+1) -> 199056.11 | ID2: =FW2*(Supuestos!$E$2+1) -> 231900.37 | KK2: =ID2*(Supuestos!$F$2+1) -> 269004.43 | MR2: =KK2*(Supuestos!$G$2+1) -> 310700.11 | OZ2: =MR2*(Supuestos!$H$2+1) -> 354198.13 | RG2: =OZ2*(Supuestos!$I$2+1) -> 403785.87 | TN2: =RG2*(Supuestos!$J$2+1) -> 460315.89
F3: =F4/$BH$2 -> 0.088999053 | J3: =J4/$BH$2 -> 0.074979601 | O3: =O4/$BH$2 -> 0.080804353 | T3: =T4/$BH$2 -> 0.078169104 | Y3: =Y4/$BH$2 -> 0.088506707 | AD3: =AD4/$BH$2 -> 0.068783444 | AI3: =AI4/$BH$2 -> 0.089459988 | AN3: =AN4/$BH$2 -> 0.099301206 | AS3: =AS4/$BH$2 -> 0.09482746 | AX3: =AX4/$BH$2 -> 0.097263288 | BC3: =BC4/$BH$2 -> 0.091476337 | BH3: =BH4/$BH$2 -> 0.047429458 | BM3: =BM4/$DO$2 -> 0.088999053 | BQ3: =BQ4/$DO$2 -> 0.074979601 | BV3: =BV4/$DO$2 -> 0.080804353 | CA3: =CA4/$DO$2 -> 0.078169104 | CF3: =CF4/$DO$2 -> 0.088506707 | CK3: =CK4/$DO$2 -> 0.068783444 | CP3: =CP4/$DO$2 -> 0.089459988 | CU3: =CU4/$DO$2 -> 0.099301206 | CZ3: =CZ4/$DO$2 -> 0.09482746 | DE3: =DE4/$DO$2 -> 0.097263288 | DJ3: =DJ4/$DO$2 -> 0.091476337 | DO3: =DO4/$DO$2 -> 0.047429458 | DT3: =DT4/$FW$2 -> 0.088999053 | DY3: =DY4/$FW$2 -> 0.074979601 | ED3: =ED4/$FW$2 -> 0.080804353 | EI3: =EI4/$FW$2 -> 0.078169104 | EN3: =EN4/$FW$2 -> 0.088506707 | ES3: =ES4/$FW$2 -> 0.068783444 | EX3: =EX4/$FW$2 -> 0.089459988 | FC3: =FC4/$FW$2 -> 0.099301206 | FH3: =FH4/$FW$2 -> 0.09482746 | FM3: =FM4/$FW$2 -> 0.097263288 | FR3: =FR4/$FW$2 -> 0.091476337 | FW3: =FW4/$FW$2 -> 0.047429458 | GB3: =GB4/$ID$2 -> 0.088999053 | GF3: =GF4/$ID$2 -> 0.074979601 | GK3: =GK4/$ID$2 -> 0.080804353 | GP3: =GP4/$ID$2 -> 0.078169104 | GU3: =GU4/$ID$2 -> 0.088506707 | GZ3: =GZ4/$ID$2 -> 0.068783444 | HE3: =HE4/$ID$2 -> 0.089459988 | HJ3: =HJ4/$ID$2 -> 0.099301206 | HO3: =HO4/$ID$2 -> 0.09482746 | HT3: =HT4/$ID$2 -> 0.097263288 | HY3: =HY4/$ID$2 -> 0.091476337 | ID3: =ID4/$ID$2 -> 0.047429458 | II3: =II4/$KK$2 -> 0.088999053 | IM3: =IM4/$KK$2 -> 0.074979601 | IR3: =IR4/$KK$2 -> 0.080804353 | IW3: =IW4/$KK$2 -> 0.078169104 | JB3: =JB4/$KK$2 -> 0.088506707 | JG3: =JG4/$KK$2 -> 0.068783444 | JL3: =JL4/$KK$2 -> 0.089459988 | JQ3: =JQ4/$KK$2 -> 0.099301206 | JV3: =JV4/$KK$2 -> 0.09482746 | KA3: =KA4/$KK$2 -> 0.097263288 | KF3: =KF4/$KK$2 -> 0.091476337 | KK3: =KK4/$KK$2 -> 0.047429458 | KP3: =KP4/$MR$2 -> 0.088999053 | KT3: =KT4/$MR$2 -> 0.074979601 | KY3: =KY4/$MR$2 -> 0.080804353 | LD3: =LD4/$MR$2 -> 0.078169104 | LI3: =LI4/$MR$2 -> 0.088506707 | LN3: =LN4/$MR$2 -> 0.068783444 | LS3: =LS4/$MR$2 -> 0.089459988 | LX3: =LX4/$MR$2 -> 0.099301206 | MC3: =MC4/$MR$2 -> 0.09482746 | MH3: =MH4/$MR$2 -> 0.097263288 | MM3: =MM4/$MR$2 -> 0.091476337 | MR3: =MR4/$MR$2 -> 0.047429458 | MW3: =MW4/$OZ$2 -> 0.088999053 | NB3: =NB4/$OZ$2 -> 0.074979601 | NG3: =NG4/$OZ$2 -> 0.080804353 | NL3: =NL4/$OZ$2 -> 0.078169104 | NQ3: =NQ4/$OZ$2 -> 0.088506707 | NV3: =NV4/$OZ$2 -> 0.068783444 | OA3: =OA4/$OZ$2 -> 0.089459988 | OF3: =OF4/$OZ$2 -> 0.099301206 | OK3: =OK4/$OZ$2 -> 0.09482746 | OP3: =OP4/$OZ$2 -> 0.097263288 | OU3: =OU4/$OZ$2 -> 0.091476337 | OZ3: =OZ4/$OZ$2 -> 0.047429458 | PE3: =PE4/$RG$2 -> 0.088999053 | PI3: =PI4/$RG$2 -> 0.074979601 | PN3: =PN4/$RG$2 -> 0.080804353 | PS3: =PS4/$RG$2 -> 0.078169104 | PX3: =PX4/$RG$2 -> 0.088506707 | QC3: =QC4/$RG$2 -> 0.068783444 | QH3: =QH4/$RG$2 -> 0.089459988 | QM3: =QM4/$RG$2 -> 0.099301206 | QR3: =QR4/$RG$2 -> 0.09482746 | QW3: =QW4/$RG$2 -> 0.097263288 | RB3: =RB4/$RG$2 -> 0.091476337 | RG3: =RG4/$RG$2 -> 0.047429458 | RL3: =RL4/$TN$2 -> 0.088999053 | RP3: =RP4/$TN$2 -> 0.074979601 | RU3: =RU4/$TN$2 -> 0.080804353 | RZ3: =RZ4/$TN$2 -> 0.078169104 | SE3: =SE4/$TN$2 -> 0.088506707 | SJ3: =SJ4/$TN$2 -> 0.068783444 | SO3: =SO4/$TN$2 -> 0.089459988 | ST3: =ST4/$TN$2 -> 0.099301206 | SY3: =SY4/$TN$2 -> 0.09482746 | TD3: =TD4/$TN$2 -> 0.097263288 | TI3: =TI4/$TN$2 -> 0.091476337 | TN3: =TN4/$TN$2 -> 0.047429458
F4: =SUM(B9:F9) -> 12462.316 | J4: =SUM(G9:J9) -> 10499.207 | O4: =SUM(K9:O9) -> 11314.833 | T4: =SUM(P9:T9) -> 10945.825 | Y4: =SUM(U9:Y9) -> 12393.374 | AD4: =SUM(Z9:AD9) -> 9631.5746 | AI4: =SUM(AE9:AI9) -> 12526.86 | AN4: =SUM(AJ9:AN9) -> 13904.901 | AS4: =12678.4534174738+600 -> 13278.453 | AX4: =13019.5363073495+600 -> 13619.536 | BC4: =12209.2039886485+600 -> 12809.204 | BH4: 6641.4291 | BM4: =$DO$2*F3 -> 15141.714 | BQ4: =$DO$2*J3 -> 12756.537 | BV4: =$DO$2*O3 -> 13747.522 | CA4: =$DO$2*T3 -> 13299.178 | CF4: =$DO$2*Y3 -> 15057.95 | CK4: =$DO$2*AD3 -> 11702.363 | CP4: =$DO$2*AI3 -> 15220.134 | CU4: =$DO$2*AN3 -> 16894.455 | CZ4: =$DO$2*AS3 -> 16133.321 | DE4: =$DO$2*AX3 -> 16547.737 | DJ4: =$DO$2*BC3 -> 15563.183 | DO4: =$DO$2*BH3 -> 8069.3363 | DT4: =BM3*$FW$2 -> 17715.805 | DY4: =BQ3*$FW$2 -> 14925.148 | ED4: =BV3*$FW$2 -> 16084.6 | EI4: =CA3*$FW$2 -> 15560.038 | EN4: =CF3*$FW$2 -> 17617.801 | ES4: =CK3*$FW$2 -> 13691.765 | EX4: =CP3*$FW$2 -> 17807.557 | FC4: =CU3*$FW$2 -> 19766.512 | FH4: =CZ3*$FW$2 -> 18875.985 | FM4: =DE3*$FW$2 -> 19360.852 | FR4: =DJ3*$FW$2 -> 18208.924 | FW4: =DO3*$FW$2 -> 9441.1235 | GB4: =DT3*$ID$2 -> 20638.913 | GF4: =DY3*$ID$2 -> 17387.797 | GK4: =ED3*$ID$2 -> 18738.559 | GP4: =EI3*$ID$2 -> 18127.444 | GU4: =EN3*$ID$2 -> 20524.738 | GZ4: =ES3*$ID$2 -> 15950.906 | HE4: =EX3*$ID$2 -> 20745.804 | HJ4: =FC3*$ID$2 -> 23027.986 | HO4: =FH3*$ID$2 -> 21990.523 | HT4: =FM3*$ID$2 -> 22555.392 | HY4: =FR3*$ID$2 -> 21213.396 | ID4: =FW3*$ID$2 -> 10998.909 | II4: =GB3*$KK$2 -> 23941.139 | IM4: =GF3*$KK$2 -> 20169.845 | IR4: =GK3*$KK$2 -> 21736.729 | IW4: =GP3*$KK$2 -> 21027.835 | JB4: =GU3*$KK$2 -> 23808.696 | JG4: =GZ3*$KK$2 -> 18503.051 | JL4: =HE3*$KK$2 -> 24065.133 | JQ4: =HJ3*$KK$2 -> 26712.464 | JV4: =HO3*$KK$2 -> 25509.007 | KA4: =HT3*$KK$2 -> 26164.255 | KF4: =HY3*$KK$2 -> 24607.54 | KK4: =ID3*$KK$2 -> 12758.734 | KP4: =II3*$MR$2 -> 27652.016 | KT4: =IM3*$MR$2 -> 23296.171 | KY4: =IR3*$MR$2 -> 25105.922 | LD4: =IW3*$MR$2 -> 24287.149 | LI4: =JB3*$MR$2 -> 27499.044 | LN4: =JG3*$MR$2 -> 21371.024 | LS4: =JL3*$MR$2 -> 27795.229 | LX4: =JQ3*$MR$2 -> 30852.896 | MC4: =JV3*$MR$2 -> 29462.903 | MH4: =KA3*$MR$2 -> 30219.715 | MM4: =KF3*$MR$2 -> 28421.708 | MR4: =KK3*$MR$2 -> 14736.338 | MW4: =KP3*$OZ$2 -> 31523.298 | NB4: =KT3*$OZ$2 -> 26557.634 | NG4: =KY3*$OZ$2 -> 28620.751 | NL4: =LD3*$OZ$2 -> 27687.35 | NQ4: =LI3*$OZ$2 -> 31348.91 | NV4: =LN3*$OZ$2 -> 24362.967 | OA4: =LS3*$OZ$2 -> 31686.561 | OF4: =LX3*$OZ$2 -> 35172.301 | OK4: =MC3*$OZ$2 -> 33587.709 | OP4: =MH3*$OZ$2 -> 34450.475 | OU4: =MM3*$OZ$2 -> 32400.748 | OZ4: =MR3*$OZ$2 -> 16799.425 | PE4: =MW3*$RG$2 -> 35936.56 | PI4: =NB3*$RG$2 -> 30275.703 | PN4: =NG3*$RG$2 -> 32627.656 | PS4: =NL3*$RG$2 -> 31563.579 | PX4: =NQ3*$RG$2 -> 35737.758 | QC4: =NV3*$RG$2 -> 27773.783 | QH4: =OA3*$RG$2 -> 36122.679 | QM4: =OF3*$RG$2 -> 40096.424 | QR4: =OK3*$RG$2 -> 38289.988 | QW4: =OP3*$RG$2 -> 39273.541 | RB4: =OU3*$RG$2 -> 36936.852 | RG4: =OZ3*$RG$2 -> 19151.345 | RL4: =PE3*$TN$2 -> 40967.679 | RP4: =PI3*$TN$2 -> 34514.302 | RU4: =PN3*$TN$2 -> 37195.528 | RZ4: =PS3*$TN$2 -> 35982.481 | SE4: =PX3*$TN$2 -> 40741.044 | SJ4: =QC3*$TN$2 -> 31662.112 | SO4: =QH3*$TN$2 -> 41179.854 | ST4: =QM3*$TN$2 -> 45709.923 | SY4: =QR3*$TN$2 -> 43650.587 | TD4: =QW3*$TN$2 -> 44771.837 | TI4: =RB3*$TN$2 -> 42108.012 | TN4: =RG3*$TN$2 -> 21832.533
B5: ENERO | G5: FEBRERO | K5: MARZO | P5: ABRIL | U5: MAYO | Z5: JUNIO | AE5: JULIO | AJ5: AGOSTO | AO5: SETIEMBRE | AT5: OCTUBRE | AY5: NOVIEMBRE | BD5: DICIEMBRE | BI5: ENERO | BN5: FEBRERO | BR5: MARZO | BW5: ABRIL | CB5: MAYO | CG5: JUNIO | CL5: JULIO | CQ5: AGOSTO | CV5: SETIEMBRE | DA5: OCTUBRE | DF5: NOVIEMBRE | DK5: DICIEMBRE | DP5: ENERO | DU5: FEBRERO | DZ5: MARZO | EE5: ABRIL | EJ5: MAYO | EO5: JUNIO | ET5: JULIO | EY5: AGOSTO | FD5: SETIEMBRE | FI5: OCTUBRE | FN5: NOVIEMBRE | FS5: DICIEMBRE | FX5: ENERO | GC5: FEBRERO | GG5: MARZO | GL5: ABRIL | GQ5: MAYO | GV5: JUNIO | HA5: JULIO | HF5: AGOSTO | HK5: SETIEMBRE | HP5: OCTUBRE | HU5: NOVIEMBRE | HZ5: DICIEMBRE | IE5: ENERO | IJ5: FEBRERO | IN5: MARZO | IS5: ABRIL | IX5: MAYO | JC5: JUNIO | JH5: JULIO | JM5: AGOSTO | JR5: SETIEMBRE | JW5: OCTUBRE | KB5: NOVIEMBRE | KG5: DICIEMBRE | KL5: ENERO | KQ5: FEBRERO | KU5: MARZO | KZ5: ABRIL | LE5: MAYO | LJ5: JUNIO | LO5: JULIO | LT5: AGOSTO | LY5: SETIEMBRE | MD5: OCTUBRE | MI5: NOVIEMBRE | MN5: DICIEMBRE | MS5: ENERO | MX5: FEBRERO | NC5: MARZO | NH5: ABRIL | NM5: MAYO | NR5: JUNIO | NW5: JULIO | OB5: AGOSTO | OG5: SETIEMBRE | OL5: OCTUBRE | OQ5: NOVIEMBRE | OV5: DICIEMBRE | PA5: ENERO | PF5: FEBRERO | PJ5: MARZO | PO5: ABRIL | PT5: MAYO | PY5: JUNIO | QD5: JULIO | QI5: AGOSTO | QN5: SETIEMBRE | QS5: OCTUBRE | QX5: NOVIEMBRE | RC5: DICIEMBRE | RH5: ENERO | RM5: FEBRERO | RQ5: MARZO | RV5: ABRIL | SA5: MAYO | SF5: JUNIO | SK5: JULIO | SP5: AGOSTO | SU5: SETIEMBRE | SZ5: OCTUBRE | TE5: NOVIEMBRE | TJ5: DICIEMBRE
A6: Semana | B6: Sem. 01 | C6: Sem. 02 | D6: Sem. 03 | E6: Sem. 04 | F6: Sem. 05 | G6: Sem. 01 | H6: Sem. 02 | I6: Sem. 03 | J6: Sem. 04 | K6: Sem. 01 | L6: Sem. 02 | M6: Sem. 03 | N6: Sem. 04 | O6: Sem. 05 | P6: Sem. 01 | Q6: Sem. 02 | R6: Sem. 03 | S6: Sem. 04 | T6: Sem. 05 | U6: Sem. 01 | V6: Sem. 02 | W6: Sem. 03 | X6: Sem. 04 | Y6: Sem. 05 | Z6: Sem. 01 | AA6: Sem. 02 | AB6: Sem. 03 | AC6: Sem. 04 | AD6: Sem. 05 | AE6: Sem. 01 | AF6: Sem. 02 | AG6: Sem. 03 | AH6: Sem. 04 | AI6: Sem. 05 | AJ6: Sem. 01 | AK6: Sem. 02 | AL6: Sem. 03 | AM6: Sem. 04 | AN6: Sem. 05 | AO6: Sem. 01 | AP6: Sem. 02 | AQ6: Sem. 03 | AR6: Sem. 04 | AS6: Sem. 05 | AT6: Sem. 01 | AU6: Sem. 02 | AV6: Sem. 03 | AW6: Sem. 04 | AX6: Sem. 05 | AY6: Sem. 01 | AZ6: Sem. 02 | BA6: Sem. 03 | BB6: Sem. 04 | BC6: Sem. 05 | BD6: Sem. 01 | BE6: Sem. 02 | BF6: Sem. 03 | BG6: Sem. 04 | BH6: Sem. 05 | BI6: Sem. 01 | BJ6: Sem. 02 | BK6: Sem. 03 | BL6: Sem. 04 | BM6: Sem. 05 | BN6: Sem. 01 | BO6: Sem. 02 | BP6: Sem. 03 | BQ6: Sem. 04 | BR6: Sem. 01 | BS6: Sem. 02 | BT6: Sem. 03 | BU6: Sem. 04 | BV6: Sem. 05 | BW6: Sem. 01 | BX6: Sem. 02 | BY6: Sem. 03 | BZ6: Sem. 04 | CA6: Sem. 05 | CB6: Sem. 01 | CC6: Sem. 02 | CD6: Sem. 03 | CE6: Sem. 04 | CF6: Sem. 05 | CG6: Sem. 01 | CH6: Sem. 02 | CI6: Sem. 03 | CJ6: Sem. 04 | CK6: Sem. 05 | CL6: Sem. 01 | CM6: Sem. 02 | CN6: Sem. 03 | CO6: Sem. 04 | CP6: Sem. 05 | CQ6: Sem. 01 | CR6: Sem. 02 | CS6: Sem. 03 | CT6: Sem. 04 | CU6: Sem. 05 | CV6: Sem. 01 | CW6: Sem. 02 | CX6: Sem. 03 | CY6: Sem. 04 | CZ6: Sem. 05 | DA6: Sem. 01 | DB6: Sem. 02 | DC6: Sem. 03 | DD6: Sem. 04 | DE6: Sem. 05 | DF6: Sem. 01 | DG6: Sem. 02 | DH6: Sem. 03 | DI6: Sem. 04 | DJ6: Sem. 05 | DK6: Sem. 01 | DL6: Sem. 02 | DM6: Sem. 03 | DN6: Sem. 04 | DO6: Sem. 05 | DP6: Sem. 01 | DQ6: Sem. 02 | DR6: Sem. 03 | DS6: Sem. 04 | DT6: Sem. 05 | DU6: Sem. 01 | DV6: Sem. 02 | DW6: Sem. 03 | DX6: Sem. 04 | DY6: Sem. 05 | DZ6: Sem. 01 | EA6: Sem. 02 | EB6: Sem. 03 | EC6: Sem. 04 | ED6: Sem. 05 | EE6: Sem. 01 | EF6: Sem. 02 | EG6: Sem. 03 | EH6: Sem. 04 | EI6: Sem. 05 | EJ6: Sem. 01 | EK6: Sem. 02 | EL6: Sem. 03 | EM6: Sem. 04 | EN6: Sem. 05 | EO6: Sem. 01 | EP6: Sem. 02 | EQ6: Sem. 03 | ER6: Sem. 04 | ES6: Sem. 05 | ET6: Sem. 01 | EU6: Sem. 02 | EV6: Sem. 03 | EW6: Sem. 04 | EX6: Sem. 05 | EY6: Sem. 01 | EZ6: Sem. 02 | FA6: Sem. 03 | FB6: Sem. 04 | FC6: Sem. 05 | FD6: Sem. 01 | FE6: Sem. 02 | FF6: Sem. 03 | FG6: Sem. 04 | FH6: Sem. 05 | FI6: Sem. 01 | FJ6: Sem. 02 | FK6: Sem. 03 | FL6: Sem. 04 | FM6: Sem. 05 | FN6: Sem. 01 | FO6: Sem. 02 | FP6: Sem. 03 | FQ6: Sem. 04 | FR6: Sem. 05 | FS6: Sem. 01 | FT6: Sem. 02 | FU6: Sem. 03 | FV6: Sem. 04 | FW6: Sem. 05 | FX6: Sem. 01 | FY6: Sem. 02 | FZ6: Sem. 03 | GA6: Sem. 04 | GB6: Sem. 05 | GC6: Sem. 01 | GD6: Sem. 02 | GE6: Sem. 03 | GF6: Sem. 04 | GG6: Sem. 01 | GH6: Sem. 02 | GI6: Sem. 03 | GJ6: Sem. 04 | GK6: Sem. 05 | GL6: Sem. 01 | GM6: Sem. 02 | GN6: Sem. 03 | GO6: Sem. 04 | GP6: Sem. 05 | GQ6: Sem. 01 | GR6: Sem. 02 | GS6: Sem. 03 | GT6: Sem. 04 | GU6: Sem. 05 | GV6: Sem. 01 | GW6: Sem. 02 | GX6: Sem. 03 | GY6: Sem. 04 | GZ6: Sem. 05 | HA6: Sem. 01 | HB6: Sem. 02 | HC6: Sem. 03 | HD6: Sem. 04 | HE6: Sem. 05 | HF6: Sem. 01 | HG6: Sem. 02 | HH6: Sem. 03 | HI6: Sem. 04 | HJ6: Sem. 05 | HK6: Sem. 01 | HL6: Sem. 02 | HM6: Sem. 03 | HN6: Sem. 04 | HO6: Sem. 05 | HP6: Sem. 01 | HQ6: Sem. 02 | HR6: Sem. 03 | HS6: Sem. 04 | HT6: Sem. 05 | HU6: Sem. 01 | HV6: Sem. 02 | HW6: Sem. 03 | HX6: Sem. 04 | HY6: Sem. 05 | HZ6: Sem. 01 | IA6: Sem. 02 | IB6: Sem. 03 | IC6: Sem. 04 | ID6: Sem. 05 | IE6: Sem. 01 | IF6: Sem. 02 | IG6: Sem. 03 | IH6: Sem. 04 | II6: Sem. 05 | IJ6: Sem. 01 | IK6: Sem. 02 | IL6: Sem. 03 | IM6: Sem. 04 | IN6: Sem. 01 | IO6: Sem. 02 | IP6: Sem. 03 | IQ6: Sem. 04 | IR6: Sem. 05 | IS6: Sem. 01 | IT6: Sem. 02 | IU6: Sem. 03 | IV6: Sem. 04 | IW6: Sem. 05 | IX6: Sem. 01 | IY6: Sem. 02 | IZ6: Sem. 03 | JA6: Sem. 04 | JB6: Sem. 05 | JC6: Sem. 01 | JD6: Sem. 02 | JE6: Sem. 03 | JF6: Sem. 04 | JG6: Sem. 05 | JH6: Sem. 01 | JI6: Sem. 02 | JJ6: Sem. 03 | JK6: Sem. 04 | JL6: Sem. 05 | JM6: Sem. 01 | JN6: Sem. 02 | JO6: Sem. 03 | JP6: Sem. 04 | JQ6: Sem. 05 | JR6: Sem. 01 | JS6: Sem. 02 | JT6: Sem. 03 | JU6: Sem. 04 | JV6: Sem. 05 | JW6: Sem. 01 | JX6: Sem. 02 | JY6: Sem. 03 | JZ6: Sem. 04 | KA6: Sem. 05 | KB6: Sem. 01 | KC6: Sem. 02 | KD6: Sem. 03 | KE6: Sem. 04 | KF6: Sem. 05 | KG6: Sem. 01 | KH6: Sem. 02 | KI6: Sem. 03 | KJ6: Sem. 04 | KK6: Sem. 05 | KL6: Sem. 01 | KM6: Sem. 02 | KN6: Sem. 03 | KO6: Sem. 04 | KP6: Sem. 05 | KQ6: Sem. 01 | KR6: Sem. 02 | KS6: Sem. 03 | KT6: Sem. 04 | KU6: Sem. 01 | KV6: Sem. 02 | KW6: Sem. 03 | KX6: Sem. 04 | KY6: Sem. 05 | KZ6: Sem. 01 | LA6: Sem. 02 | LB6: Sem. 03 | LC6: Sem. 04 | LD6: Sem. 05 | LE6: Sem. 01 | LF6: Sem. 02 | LG6: Sem. 03 | LH6: Sem. 04 | LI6: Sem. 05 | LJ6: Sem. 01 | LK6: Sem. 02 | LL6: Sem. 03 | LM6: Sem. 04 | LN6: Sem. 05 | LO6: Sem. 01 | LP6: Sem. 02 | LQ6: Sem. 03 | LR6: Sem. 04 | LS6: Sem. 05 | LT6: Sem. 01 | LU6: Sem. 02 | LV6: Sem. 03 | LW6: Sem. 04 | LX6: Sem. 05 | LY6: Sem. 01 | LZ6: Sem. 02 | MA6: Sem. 03 | MB6: Sem. 04 | MC6: Sem. 05 | MD6: Sem. 01 | ME6: Sem. 02 | MF6: Sem. 03 | MG6: Sem. 04 | MH6: Sem. 05 | MI6: Sem. 01 | MJ6: Sem. 02 | MK6: Sem. 03 | ML6: Sem. 04 | MM6: Sem. 05 | MN6: Sem. 01 | MO6: Sem. 02 | MP6: Sem. 03 | MQ6: Sem. 04 | MR6: Sem. 05 | MS6: Sem. 01 | MT6: Sem. 02 | MU6: Sem. 03 | MV6: Sem. 04 | MW6: Sem. 05 | MX6: Sem. 01 | MY6: Sem. 02 | MZ6: Sem. 03 | NA6: Sem. 04 | NB6: Sem. 05 | NC6: Sem. 01 | ND6: Sem. 02 | NE6: Sem. 03 | NF6: Sem. 04 | NG6: Sem. 05 | NH6: Sem. 01 | NI6: Sem. 02 | NJ6: Sem. 03 | NK6: Sem. 04 | NL6: Sem. 05 | NM6: Sem. 01 | NN6: Sem. 02 | NO6: Sem. 03 | NP6: Sem. 04 | NQ6: Sem. 05 | NR6: Sem. 01 | NS6: Sem. 02 | NT6: Sem. 03 | NU6: Sem. 04 | NV6: Sem. 05 | NW6: Sem. 01 | NX6: Sem. 02 | NY6: Sem. 03 | NZ6: Sem. 04 | OA6: Sem. 05 | OB6: Sem. 01 | OC6: Sem. 02 | OD6: Sem. 03 | OE6: Sem. 04 | OF6: Sem. 05 | OG6: Sem. 01 | OH6: Sem. 02 | OI6: Sem. 03 | OJ6: Sem. 04 | OK6: Sem. 05 | OL6: Sem. 01 | OM6: Sem. 02 | ON6: Sem. 03 | OO6: Sem. 04 | OP6: Sem. 05 | OQ6: Sem. 01 | OR6: Sem. 02 | OS6: Sem. 03 | OT6: Sem. 04 | OU6: Sem. 05 | OV6: Sem. 01 | OW6: Sem. 02 | OX6: Sem. 03 | OY6: Sem. 04 | OZ6: Sem. 05 | PA6: Sem. 01 | PB6: Sem. 02 | PC6: Sem. 03 | PD6: Sem. 04 | PE6: Sem. 05 | PF6: Sem. 01 | PG6: Sem. 02 | PH6: Sem. 03 | PI6: Sem. 04 | PJ6: Sem. 01 | PK6: Sem. 02 | PL6: Sem. 03 | PM6: Sem. 04 | PN6: Sem. 05 | PO6: Sem. 01 | PP6: Sem. 02 | PQ6: Sem. 03 | PR6: Sem. 04 | PS6: Sem. 05 | PT6: Sem. 01 | PU6: Sem. 02 | PV6: Sem. 03 | PW6: Sem. 04 | PX6: Sem. 05 | PY6: Sem. 01 | PZ6: Sem. 02 | QA6: Sem. 03 | QB6: Sem. 04 | QC6: Sem. 05 | QD6: Sem. 01 | QE6: Sem. 02 | QF6: Sem. 03 | QG6: Sem. 04 | QH6: Sem. 05 | QI6: Sem. 01 | QJ6: Sem. 02 | QK6: Sem. 03 | QL6: Sem. 04 | QM6: Sem. 05 | QN6: Sem. 01 | QO6: Sem. 02 | QP6: Sem. 03 | QQ6: Sem. 04 | QR6: Sem. 05 | QS6: Sem. 01 | QT6: Sem. 02 | QU6: Sem. 03 | QV6: Sem. 04 | QW6: Sem. 05 | QX6: Sem. 01 | QY6: Sem. 02 | QZ6: Sem. 03 | RA6: Sem. 04 | RB6: Sem. 05 | RC6: Sem. 01 | RD6: Sem. 02 | RE6: Sem. 03 | RF6: Sem. 04 | RG6: Sem. 05 | RH6: Sem. 01 | RI6: Sem. 02 | RJ6: Sem. 03 | RK6: Sem. 04 | RL6: Sem. 05 | RM6: Sem. 01 | RN6: Sem. 02 | RO6: Sem. 03 | RP6: Sem. 04 | RQ6: Sem. 01 | RR6: Sem. 02 | RS6: Sem. 03 | RT6: Sem. 04 | RU6: Sem. 05 | RV6: Sem. 01 | RW6: Sem. 02 | RX6: Sem. 03 | RY6: Sem. 04 | RZ6: Sem. 05 | SA6: Sem. 01 | SB6: Sem. 02 | SC6: Sem. 03 | SD6: Sem. 04 | SE6: Sem. 05 | SF6: Sem. 01 | SG6: Sem. 02 | SH6: Sem. 03 | SI6: Sem. 04 | SJ6: Sem. 05 | SK6: Sem. 01 | SL6: Sem. 02 | SM6: Sem. 03 | SN6: Sem. 04 | SO6: Sem. 05 | SP6: Sem. 01 | SQ6: Sem. 02 | SR6: Sem. 03 | SS6: Sem. 04 | ST6: Sem. 05 | SU6: Sem. 01 | SV6: Sem. 02 | SW6: Sem. 03 | SX6: Sem. 04 | SY6: Sem. 05 | SZ6: Sem. 01 | TA6: Sem. 02 | TB6: Sem. 03 | TC6: Sem. 04 | TD6: Sem. 05 | TE6: Sem. 01 | TF6: Sem. 02 | TG6: Sem. 03 | TH6: Sem. 04 | TI6: Sem. 05 | TJ6: Sem. 01 | TK6: Sem. 02 | TL6: Sem. 03 | TM6: Sem. 04 | TN6: Sem. 05
A7: Inicio | B7: 46023 | C7: =B8+1 -> 46030 | D7: =C8+1 -> 46037 | E7: =D8+1 -> 46044 | F7: =E8+1 -> 46051 | G7: =F8+1 -> 46054 | H7: =G8+1 -> 46061 | I7: =H8+1 -> 46068 | J7: =I8+1 -> 46075 | ... TN7: =TM8+1 -> 49307
A8: Fin | B8: =B7+6 -> 46029 | C8: =C7+6 -> 46036 | D8: =D7+6 -> 46043 | E8: =E7+6 -> 46050 | F8: =F7+2 -> 46053 | G8: =G7+6 -> 46060 | H8: =H7+6 -> 46067 | I8: =I7+6 -> 46074 | J8: =J7+6 -> 46081 | K8: =K7+6 -> 46088 | L8: =L7+6 -> 46095 | M8: =M7+6 -> 46102 | N8: =N7+6 -> 46109 | O8: =O7+2 -> 46112 | P8: =P7+6 -> 46119 | Q8: =Q7+6 -> 46126 | R8: =R7+6 -> 46133 | S8: =S7+6 -> 46140 | T8: =T7+1 -> 46142 | U8: =U7+6 -> 46149 | V8: =V7+6 -> 46156 | W8: =W7+6 -> 46163 | X8: =X7+6 -> 46170 | Y8: =Y7+2 -> 46173 | Z8: =Z7+6 -> 46180 | AA8: =AA7+6 -> 46187 | AB8: =AB7+6 -> 46194 | AC8: =AC7+6 -> 46201 | AD8: =AD7+1 -> 46203 | AE8: =AE7+6 -> 46210 | AF8: =AF7+6 -> 46217 | AG8: =AG7+6 -> 46224 | AH8: =AH7+6 -> 46231 | AI8: =AI7+2 -> 46234 | AJ8: =AJ7+6 -> 46241 | AK8: =AK7+6 -> 46248 | AL8: =AL7+6 -> 46255 | AM8: =AM7+6 -> 46262 | AN8: =AN7+2 -> 46265 | AO8: =AO7+6 -> 46272 | AP8: =AP7+6 -> 46279 | AQ8: =AQ7+6 -> 46286 | AR8: =AR7+6 -> 46293 | AS8: =AS7+1 -> 46295 | AT8: =AT7+6 -> 46302 | AU8: =AU7+6 -> 46309 | AV8: =AV7+6 -> 46316 | AW8: =AW7+6 -> 46323 | AX8: =AX7+2 -> 46326 | AY8: =AY7+6 -> 46333 | AZ8: =AZ7+6 -> 46340 | BA8: =BA7+6 -> 46347 | BB8: =BB7+6 -> 46354 | BC8: =BC7+1 -> 46356 | BD8: =BD7+6 -> 46363 | BE8: =BE7+6 -> 46370 | BF8: =BF7+6 -> 46377 | BG8: =BG7+6 -> 46384 | BH8: =BH7+2 -> 46387 | BI8: =BI7+6 -> 46394 | BJ8: =BJ7+6 -> 46401 | BK8: =BK7+6 -> 46408 | BL8: =BL7+6 -> 46415 | BM8: =BM7+2 -> 46418 | BN8: =BN7+6 -> 46425 | BO8: =BO7+6 -> 46432 | BP8: =BP7+6 -> 46439 | BQ8: =BQ7+6 -> 46446 | BR8: =BR7+6 -> 46453 | BS8: =BS7+6 -> 46460 | BT8: =BT7+6 -> 46467 | BU8: =BU7+6 -> 46474 | BV8: =BV7+2 -> 46477 | BW8: =BW7+6 -> 46484 | BX8: =BX7+6 -> 46491 | BY8: =BY7+6 -> 46498 | BZ8: =BZ7+6 -> 46505 | CA8: =CA7+1 -> 46507 | CB8: =CB7+6 -> 46514 | CC8: =CC7+6 -> 46521 | CD8: =CD7+6 -> 46528 | CE8: =CE7+6 -> 46535 | CF8: =CF7+2 -> 46538 | CG8: =CG7+6 -> 46545 | CH8: =CH7+6 -> 46552 | CI8: =CI7+6 -> 46559 | CJ8: =CJ7+6 -> 46566 | CK8: =CK7+1 -> 46568 | CL8: =CL7+6 -> 46575 | CM8: =CM7+6 -> 46582 | CN8: =CN7+6 -> 46589 | CO8: =CO7+6 -> 46596 | CP8: =CP7+2 -> 46599 | CQ8: =CQ7+6 -> 46606 | CR8: =CR7+6 -> 46613 | CS8: =CS7+6 -> 46620 | CT8: =CT7+6 -> 46627 | CU8: =CU7+2 -> 46630 | CV8: =CV7+6 -> 46637 | CW8: =CW7+6 -> 46644 | CX8: =CX7+6 -> 46651 | CY8: =CY7+6 -> 46658 | CZ8: =CZ7+1 -> 46660 | DA8: =DA7+6 -> 46667 | DB8: =DB7+6 -> 46674 | DC8: =DC7+6 -> 46681 | DD8: =DD7+6 -> 46688 | DE8: =DE7+2 -> 46691 | DF8: =DF7+6 -> 46698 | DG8: =DG7+6 -> 46705 | DH8: =DH7+6 -> 46712 | DI8: =DI7+6 -> 46719 | DJ8: =DJ7+1 -> 46721 | DK8: =DK7+6 -> 46728 | DL8: =DL7+6 -> 46735 | DM8: =DM7+6 -> 46742 | DN8: =DN7+6 -> 46749 | DO8: =DO7+2 -> 46752 | DP8: =DP7+6 -> 46759 | DQ8: =DQ7+6 -> 46766 | DR8: =DR7+6 -> 46773 | DS8: =DS7+6 -> 46780 | DT8: =DT7+2 -> 46783 | DU8: =DU7+6 -> 46790 | DV8: =DV7+6 -> 46797 | DW8: =DW7+6 -> 46804 | DX8: =DX7+6 -> 46811 | DY8: =DY7 -> 46812 | DZ8: =DZ7+6 -> 46819 | EA8: =EA7+6 -> 46826 | EB8: =EB7+6 -> 46833 | EC8: =EC7+2 -> 46836 | ED8: =ED7+6 -> 46843 | EE8: =EE7+6 -> 46850 | EF8: =EF7+6 -> 46857 | EG8: =EG7+6 -> 46864 | EH8: =EH7+1 -> 46866 | EI8: =EI7+6 -> 46873 | EJ8: =EJ7+6 -> 46880 | EK8: =EK7+6 -> 46887 | EL8: =EL7+6 -> 46894 | EM8: =EM7+2 -> 46897 | EN8: =EN7+6 -> 46904 | EO8: =EO7+6 -> 46911 | EP8: =EP7+6 -> 46918 | EQ8: =EQ7+6 -> 46925 | ER8: =ER7+1 -> 46927 | ES8: =ES7+6 -> 46934 | ET8: =ET7+6 -> 46941 | EU8: =EU7+6 -> 46948 | EV8: =EV7+6 -> 46955 | EW8: =EW7+2 -> 46958 | EX8: =EX7+6 -> 46965 | EY8: =EY7+6 -> 46972 | EZ8: =EZ7+6 -> 46979 | FA8: =FA7+6 -> 46986 | FB8: =FB7+2 -> 46989 | FC8: =FC7+6 -> 46996 | FD8: =FD7+6 -> 47003 | FE8: =FE7+6 -> 47010 | FF8: =FF7+6 -> 47017 | FG8: =FG7+1 -> 47019 | FH8: =FH7+6 -> 47026 | FI8: =FI7+6 -> 47033 | FJ8: =FJ7+6 -> 47040 | FK8: =FK7+6 -> 47047 | FL8: =FL7+2 -> 47050 | FM8: =FM7+6 -> 47057 | FN8: =FN7+6 -> 47064 | FO8: =FO7+6 -> 47071 | FP8: =FP7+6 -> 47078 | FQ8: =FQ7+1 -> 47080 | FR8: =FR7+6 -> 47087 | FS8: =FS7+6 -> 47094 | FT8: =FT7+6 -> 47101 | FU8: =FU7+6 -> 47108 | FV8: =FV7+6 -> 47115 | FW8: =FW7+2 -> 47118 | FX8: =FX7+6 -> 47125 | FY8: =FY7+6 -> 47132 | FZ8: =FZ7+6 -> 47139 | GA8: =GA7+6 -> 47146 | GB8: =GB7+2 -> 47149 | GC8: =GC7+6 -> 47156 | GD8: =GD7+6 -> 47163 | GE8: =GE7+6 -> 47170 | GF8: =GF7+6 -> 47177 | GG8: =GG7+6 -> 47184 | GH8: =GH7+6 -> 47191 | GI8: =GI7+6 -> 47198 | GJ8: =GJ7+2 -> 47201 | GK8: =GK7+6 -> 47208 | GL8: =GL7+6 -> 47215 | GM8: =GM7+6 -> 47222 | GN8: =GN7+6 -> 47229 | GO8: =GO7+1 -> 47231 | GP8: =GP7+6 -> 47238 | GQ8: =GQ7+6 -> 47245 | GR8: =GR7+6 -> 47252 | GS8: =GS7+6 -> 47259 | GT8: =GT7+2 -> 47262 | GU8: =GU7+6 -> 47269 | GV8: =GV7+6 -> 47276 | GW8: =GW7+6 -> 47283 | GX8: =GX7+6 -> 47290 | GY8: =GY7+1 -> 47292 | GZ8: =GZ7+6 -> 47299 | HA8: =HA7+6 -> 47306 | HB8: =HB7+6 -> 47313 | HC8: =HC7+6 -> 47320 | HD8: =HD7+2 -> 47323 | HE8: =HE7+6 -> 47330 | HF8: =HF7+6 -> 47337 | HG8: =HG7+6 -> 47344 | HH8: =HH7+6 -> 47351 | HI8: =HI7+2 -> 47354 | HJ8: =HJ7+6 -> 47361 | HK8: =HK7+6 -> 47368 | HL8: =HL7+6 -> 47375 | HM8: =HM7+6 -> 47382 | HN8: =HN7+1 -> 47384 | HO8: =HO7+6 -> 47391 | HP8: =HP7+6 -> 47398 | HQ8: =HQ7+6 -> 47405 | HR8: =HR7+6 -> 47412 | HS8: =HS7+2 -> 47415 | HT8: =HT7+6 -> 47422 | HU8: =HU7+6 -> 47429 | HV8: =HV7+6 -> 47436 | HW8: =HW7+6 -> 47443 | HX8: =HX7+1 -> 47445 | HY8: =HY7+6 -> 47452 | HZ8: =HZ7+6 -> 47459 | IA8: =IA7+6 -> 47466 | IB8: =IB7+6 -> 47473 | IC8: =IC7+6 -> 47480 | ID8: =ID7+2 -> 47483 | IE8: =IE7+6 -> 47490 | IF8: =IF7+6 -> 47497 | IG8: =IG7+6 -> 47504 | IH8: =IH7+6 -> 47511 | II8: =II7+2 -> 47514 | IJ8: =IJ7+6 -> 47521 | IK8: =IK7+6 -> 47528 | IL8: =IL7+6 -> 47535 | IM8: =IM7+6 -> 47542 | IN8: =IN7+6 -> 47549 | IO8: =IO7+6 -> 47556 | IP8: =IP7+6 -> 47563 | IQ8: =IQ7+2 -> 47566 | IR8: =IR7+6 -> 47573 | IS8: =IS7+6 -> 47580 | IT8: =IT7+6 -> 47587 | IU8: =IU7+6 -> 47594 | IV8: =IV7+1 -> 47596 | IW8: =IW7+6 -> 47603 | IX8: =IX7+6 -> 47610 | IY8: =IY7+6 -> 47617 | IZ8: =IZ7+6 -> 47624 | JA8: =JA7+2 -> 47627 | JB8: =JB7+6 -> 47634 | JC8: =JC7+6 -> 47641 | JD8: =JD7+6 -> 47648 | JE8: =JE7+6 -> 47655 | JF8: =JF7+1 -> 47657 | JG8: =JG7+6 -> 47664 | JH8: =JH7+6 -> 47671 | JI8: =JI7+6 -> 47678 | JJ8: =JJ7+6 -> 47685 | JK8: =JK7+2 -> 47688 | JL8: =JL7+6 -> 47695 | JM8: =JM7+6 -> 47702 | JN8: =JN7+6 -> 47709 | JO8: =JO7+6 -> 47716 | JP8: =JP7+2 -> 47719 | JQ8: =JQ7+6 -> 47726 | JR8: =JR7+6 -> 47733 | JS8: =JS7+6 -> 47740 | JT8: =JT7+6 -> 47747 | JU8: =JU7+1 -> 47749 | JV8: =JV7+6 -> 47756 | JW8: =JW7+6 -> 47763 | JX8: =JX7+6 -> 47770 | JY8: =JY7+6 -> 47777 | JZ8: =JZ7+2 -> 47780 | KA8: =KA7+6 -> 47787 | KB8: =KB7+6 -> 47794 | KC8: =KC7+6 -> 47801 | KD8: =KD7+6 -> 47808 | KE8: =KE7+1 -> 47810 | KF8: =KF7+6 -> 47817 | KG8: =KG7+6 -> 47824 | KH8: =KH7+6 -> 47831 | KI8: =KI7+6 -> 47838 | KJ8: =KJ7+6 -> 47845 | KK8: =KK7+2 -> 47848 | KL8: =KL7+6 -> 47855 | KM8: =KM7+6 -> 47862 | KN8: =KN7+6 -> 47869 | KO8: =KO7+6 -> 47876 | KP8: =KP7+2 -> 47879 | KQ8: =KQ7+6 -> 47886 | KR8: =KR7+6 -> 47893 | KS8: =KS7+6 -> 47900 | KT8: =KT7+6 -> 47907 | KU8: =KU7+6 -> 47914 | KV8: =KV7+6 -> 47921 | KW8: =KW7+6 -> 47928 | KX8: =KX7+2 -> 47931 | KY8: =KY7+6 -> 47938 | KZ8: =KZ7+6 -> 47945 | LA8: =LA7+6 -> 47952 | LB8: =LB7+6 -> 47959 | LC8: =LC7+1 -> 47961 | LD8: =LD7+6 -> 47968 | LE8: =LE7+6 -> 47975 | LF8: =LF7+6 -> 47982 | LG8: =LG7+6 -> 47989 | LH8: =LH7+2 -> 47992 | LI8: =LI7+6 -> 47999 | LJ8: =LJ7+6 -> 48006 | LK8: =LK7+6 -> 48013 | LL8: =LL7+6 -> 48020 | LM8: =LM7+1 -> 48022 | LN8: =LN7+6 -> 48029 | LO8: =LO7+6 -> 48036 | LP8: =LP7+6 -> 48043 | LQ8: =LQ7+6 -> 48050 | LR8: =LR7+2 -> 48053 | LS8: =LS7+6 -> 48060 | LT8: =LT7+6 -> 48067 | LU8: =LU7+6 -> 48074 | LV8: =LV7+6 -> 48081 | LW8: =LW7+2 -> 48084 | LX8: =LX7+6 -> 48091 | LY8: =LY7+6 -> 48098 | LZ8: =LZ7+6 -> 48105 | MA8: =MA7+6 -> 48112 | MB8: =MB7+1 -> 48114 | MC8: =MC7+6 -> 48121 | MD8: =MD7+6 -> 48128 | ME8: =ME7+6 -> 48135 | MF8: =MF7+6 -> 48142 | MG8: =MG7+2 -> 48145 | MH8: =MH7+6 -> 48152 | MI8: =MI7+6 -> 48159 | MJ8: =MJ7+6 -> 48166 | MK8: =MK7+6 -> 48173 | ML8: =ML7+1 -> 48175 | MM8: =MM7+6 -> 48182 | MN8: =MN7+6 -> 48189 | MO8: =MO7+6 -> 48196 | MP8: =MP7+6 -> 48203 | MQ8: =MQ7+6 -> 48210 | MR8: =MR7+2 -> 48213 | MS8: =MS7+6 -> 48220 | MT8: =MT7+6 -> 48227 | MU8: =MU7+6 -> 48234 | MV8: =MV7+6 -> 48241 | MW8: =MW7+2 -> 48244 | MX8: =MX7+6 -> 48251 | MY8: =MY7+6 -> 48258 | MZ8: =MZ7+6 -> 48265 | NA8: =NA7+6 -> 48272 | NB8: =NB7 -> 48273 | NC8: =NC7+6 -> 48280 | ND8: =ND7+6 -> 48287 | NE8: =NE7+6 -> 48294 | NF8: =NF7+2 -> 48297 | NG8: =NG7+6 -> 48304 | NH8: =NH7+6 -> 48311 | NI8: =NI7+6 -> 48318 | NJ8: =NJ7+6 -> 48325 | NK8: =NK7+1 -> 48327 | NL8: =NL7+6 -> 48334 | NM8: =NM7+6 -> 48341 | NN8: =NN7+6 -> 48348 | NO8: =NO7+6 -> 48355 | NP8: =NP7+2 -> 48358 | NQ8: =NQ7+6 -> 48365 | NR8: =NR7+6 -> 48372 | NS8: =NS7+6 -> 48379 | NT8: =NT7+6 -> 48386 | NU8: =NU7+1 -> 48388 | NV8: =NV7+6 -> 48395 | NW8: =NW7+6 -> 48402 | NX8: =NX7+6 -> 48409 | NY8: =NY7+6 -> 48416 | NZ8: =NZ7+2 -> 48419 | OA8: =OA7+6 -> 48426 | OB8: =OB7+6 -> 48433 | OC8: =OC7+6 -> 48440 | OD8: =OD7+6 -> 48447 | OE8: =OE7+2 -> 48450 | OF8: =OF7+6 -> 48457 | OG8: =OG7+6 -> 48464 | OH8: =OH7+6 -> 48471 | OI8: =OI7+6 -> 48478 | OJ8: =OJ7+1 -> 48480 | OK8: =OK7+6 -> 48487 | OL8: =OL7+6 -> 48494 | OM8: =OM7+6 -> 48501 | ON8: =ON7+6 -> 48508 | OO8: =OO7+2 -> 48511 | OP8: =OP7+6 -> 48518 | OQ8: =OQ7+6 -> 48525 | OR8: =OR7+6 -> 48532 | OS8: =OS7+6 -> 48539 | OT8: =OT7+1 -> 48541 | OU8: =OU7+6 -> 48548 | OV8: =OV7+6 -> 48555 | OW8: =OW7+6 -> 48562 | OX8: =OX7+6 -> 48569 | OY8: =OY7+6 -> 48576 | OZ8: =OZ7+2 -> 48579 | PA8: =PA7+6 -> 48586 | PB8: =PB7+6 -> 48593 | PC8: =PC7+6 -> 48600 | PD8: =PD7+6 -> 48607 | PE8: =PE7+2 -> 48610 | PF8: =PF7+6 -> 48617 | PG8: =PG7+6 -> 48624 | PH8: =PH7+6 -> 48631 | PI8: =PI7+6 -> 48638 | PJ8: =PJ7+6 -> 48645 | PK8: =PK7+6 -> 48652 | PL8: =PL7+6 -> 48659 | PM8: =PM7+2 -> 48662 | PN8: =PN7+6 -> 48669 | PO8: =PO7+6 -> 48676 | PP8: =PP7+6 -> 48683 | PQ8: =PQ7+6 -> 48690 | PR8: =PR7+1 -> 48692 | PS8: =PS7+6 -> 48699 | PT8: =PT7+6 -> 48706 | PU8: =PU7+6 -> 48713 | PV8: =PV7+6 -> 48720 | PW8: =PW7+2 -> 48723 | PX8: =PX7+6 -> 48730 | PY8: =PY7+6 -> 48737 | PZ8: =PZ7+6 -> 48744 | QA8: =QA7+6 -> 48751 | QB8: =QB7+1 -> 48753 | QC8: =QC7+6 -> 48760 | QD8: =QD7+6 -> 48767 | QE8: =QE7+6 -> 48774 | QF8: =QF7+6 -> 48781 | QG8: =QG7+2 -> 48784 | QH8: =QH7+6 -> 48791 | QI8: =QI7+6 -> 48798 | QJ8: =QJ7+6 -> 48805 | QK8: =QK7+6 -> 48812 | QL8: =QL7+2 -> 48815 | QM8: =QM7+6 -> 48822 | QN8: =QN7+6 -> 48829 | QO8: =QO7+6 -> 48836 | QP8: =QP7+6 -> 48843 | QQ8: =QQ7+1 -> 48845 | QR8: =QR7+6 -> 48852 | QS8: =QS7+6 -> 48859 | QT8: =QT7+6 -> 48866 | QU8: =QU7+6 -> 48873 | QV8: =QV7+2 -> 48876 | QW8: =QW7+6 -> 48883 | QX8: =QX7+6 -> 48890 | QY8: =QY7+6 -> 48897 | QZ8: =QZ7+6 -> 48904 | RA8: =RA7+1 -> 48906 | RB8: =RB7+6 -> 48913 | RC8: =RC7+6 -> 48920 | RD8: =RD7+6 -> 48927 | RE8: =RE7+6 -> 48934 | RF8: =RF7+6 -> 48941 | RG8: =RG7+2 -> 48944 | RH8: =RH7+6 -> 48951 | RI8: =RI7+6 -> 48958 | RJ8: =RJ7+6 -> 48965 | RK8: =RK7+6 -> 48972 | RL8: =RL7+2 -> 48975 | RM8: =RM7+6 -> 48982 | RN8: =RN7+6 -> 48989 | RO8: =RO7+6 -> 48996 | RP8: =RP7+6 -> 49003 | RQ8: =RQ7+6 -> 49010 | RR8: =RR7+6 -> 49017 | RS8: =RS7+6 -> 49024 | RT8: =RT7+2 -> 49027 | RU8: =RU7+6 -> 49034 | RV8: =RV7+6 -> 49041 | RW8: =RW7+6 -> 49048 | RX8: =RX7+6 -> 49055 | RY8: =RY7+1 -> 49057 | RZ8: =RZ7+6 -> 49064 | SA8: =SA7+6 -> 49071 | SB8: =SB7+6 -> 49078 | SC8: =SC7+6 -> 49085 | SD8: =SD7+2 -> 49088 | SE8: =SE7+6 -> 49095 | SF8: =SF7+6 -> 49102 | SG8: =SG7+6 -> 49109 | SH8: =SH7+6 -> 49116 | SI8: =SI7+1 -> 49118 | SJ8: =SJ7+6 -> 49125 | SK8: =SK7+6 -> 49132 | SL8: =SL7+6 -> 49139 | SM8: =SM7+6 -> 49146 | SN8: =SN7+2 -> 49149 | SO8: =SO7+6 -> 49156 | SP8: =SP7+6 -> 49163 | SQ8: =SQ7+6 -> 49170 | SR8: =SR7+6 -> 49177 | SS8: =SS7+2 -> 49180 | ST8: =ST7+6 -> 49187 | SU8: =SU7+6 -> 49194 | SV8: =SV7+6 -> 49201 | SW8: =SW7+6 -> 49208 | SX8: =SX7+1 -> 49210 | SY8: =SY7+6 -> 49217 | SZ8: =SZ7+6 -> 49224 | TA8: =TA7+6 -> 49231 | TB8: =TB7+6 -> 49238 | TC8: =TC7+2 -> 49241 | TD8: =TD7+6 -> 49248 | TE8: =TE7+6 -> 49255 | TF8: =TF7+6 -> 49262 | TG8: =TG7+6 -> 49269 | TH8: =TH7+1 -> 49271 | TI8: =TI7+6 -> 49278 | TJ8: =TJ7+6 -> 49285 | TK8: =TK7+6 -> 49292 | TL8: =TL7+6 -> 49299 | TM8: =TM7+6 -> 49306 | TN8: =TN7+2 -> 49309
A9: Ventas por Semana | B9: =B10+B12 -> 538.06383 | C9: =C10+C12 -> 3602.1838 | D9: =D10+D12 -> 2051.0167 | E9: =E10+E12 -> 3754.2197 | F9: =F10+F12 -> 2516.832 | G9: =G10+G12 -> 1255.7666 | H9: =H10+H12 -> 1926.6994 | I9: =I10+I12 -> 2465.2274 | ... TN9: =TN10+TN12 -> 4234.1767
A10: Contado | B10: 265.44446 | C10: 2397.2321 | D10: 1352.1454 | E10: 2521.8643 | F10: 1645.1814 | G10: 696.10222 | H10: 1254.6096 | I10: 1393.6365 | J10: 2624.6439 | K10: 581.224 | L10: 1338.6261 | M10: 1207.1655 | N10: 2243.159 | O10: 1381.2108 | P10: 278.34625 | Q10: 2075.8995 | R10: 1447.4468 | S10: 1715.8149 | T10: 1214.7742 | U10: 960.90441 | V10: 763.65363 | W10: 1846.5383 | X10: 2388.422 | Y10: 1182.9896 | Z10: 573.82856 | AA10: 1439.8379 | AB10: 1069.5546 | AC10: 1426.5837 | AD10: 1508.6509 | AE10: 1170.7045 | AF10: 1399.0095 | AG10: 1398.1522 | AH10: 1228.9778 | AI10: 1654.6406 | AJ10: 1047.1136 | AK10: 2471.7982 | AL10: 2459.5457 | AM10: 3063.7081 | AN10: 741.83706 | AO10: 1132.5537 | AP10: 1167.8743 | AQ10: 2453.3821 | AR10: =$AS$4*Supuestos!I12*Supuestos!$B$5 -> 2263.7607 | AS10: =$AS$4*Supuestos!J12*Supuestos!$B$5+156.823588949399 -> 1856.461 | AT10: =$AX$4*Supuestos!F12*Supuestos!$B$5 -> 845.31755 | AU10: =$AX$4*Supuestos!G12*Supuestos!$B$5 -> 1848.4129 | AV10: =$AX$4*Supuestos!H12*Supuestos!$B$5 -> 2229.9579 | AW10: =$AX$4*Supuestos!I12*Supuestos!$B$5 -> 2321.9098 | AX10: =$AX$4*Supuestos!J12*Supuestos!$B$5 -> 1743.2959 | AY10: =$BC$4*Supuestos!F12*Supuestos!$B$5 -> 795.02303 | AZ10: =$BC$4*Supuestos!G12*Supuestos!$B$5 -> 1738.4364 | BA10: =$BC$4*Supuestos!H12*Supuestos!$B$5 -> 2097.2803 | BB10: =$BC$4*Supuestos!I12*Supuestos!$B$5 -> 2183.7613 | BC10: =$BC$4*Supuestos!J12*Supuestos!$B$5 -> 1639.5736 | BD10: =$BH$4*Supuestos!F12*Supuestos!$B$5 -> 412.21055 | BE10: =$BH$4*Supuestos!G12*Supuestos!$B$5 -> 901.35984 | BF10: =$BH$4*Supuestos!H12*Supuestos!$B$5 -> 1087.4164 | BG10: =$BH$4*Supuestos!I12*Supuestos!$B$5 -> 1132.2558 | BH10: =$BH$4*Supuestos!J12*Supuestos!$B$5 -> 850.10059 | BI10: =$BM$4*Supuestos!F12*Supuestos!$B$5 -> 939.79386 | BJ10: =$BM$4*Supuestos!G12*Supuestos!$B$5 -> 2054.9994 | BK10: =$BM$4*Supuestos!H12*Supuestos!$B$5 -> 2479.1875 | BL10: =$BM$4*Supuestos!I12*Supuestos!$B$5 -> 2581.4164 | BM10: =$BM$4*Supuestos!J12*Supuestos!$B$5 -> 1938.1341 | BN10: =$BQ$4*Supuestos!F13*Supuestos!$B$5 -> 1006.9992 | BO10: =$BQ$4*Supuestos!G13*Supuestos!$B$5 -> 1545.0203 | BP10: =$BQ$4*Supuestos!H13*Supuestos!$B$5 -> 1976.8658 | BQ10: =$BQ$4*Supuestos!I13*Supuestos!$B$5 -> 3890.4288 | BR10: =$BV$4*Supuestos!F12*Supuestos!$B$5 -> 853.26116 | BS10: =$BV$4*Supuestos!G12*Supuestos!$B$5 -> 1865.7828 | BT10: =$BV$4*Supuestos!H12*Supuestos!$B$5 -> 2250.9132 | BU10: =$BV$4*Supuestos!I12*Supuestos!$B$5 -> 2343.7292 | BV10: =$BV$4*Supuestos!J12*Supuestos!$B$5 -> 1759.6779 | BW10: =$CA$4*Supuestos!F12*Supuestos!$B$5 -> 825.43399 | BX10: =$CA$4*Supuestos!G12*Supuestos!$B$5 -> 1804.9345 | BY10: =$CA$4*Supuestos!H12*Supuestos!$B$5 -> 2177.5048 | BZ10: =$CA$4*Supuestos!I12*Supuestos!$B$5 -> 2267.2938 | CA10: =$CA$4*Supuestos!J12*Supuestos!$B$5 -> 1702.2901 | CB10: =$CF$4*Supuestos!F12*Supuestos!$B$5 -> 934.59489 | CC10: =$CF$4*Supuestos!G12*Supuestos!$B$5 -> 2043.6311 | CD10: =$CF$4*Supuestos!H12*Supuestos!$B$5 -> 2465.4726 | CE10: =$CF$4*Supuestos!I12*Supuestos!$B$5 -> 2567.1359 | CF10: =$CF$4*Supuestos!J12*Supuestos!$B$5 -> 1927.4123 | CG10: =$CK$4*Supuestos!F12*Supuestos!$B$5 -> 726.32524 | CH10: =$CK$4*Supuestos!G12*Supuestos!$B$5 -> 1588.2185 | CI10: =$CK$4*Supuestos!H12*Supuestos!$B$5 -> 1916.0547 | CJ10: =$CK$4*Supuestos!I12*Supuestos!$B$5 -> 1995.0629 | CK10: =$CK$4*Supuestos!J12*Supuestos!$B$5 -> 1497.8984 | CL10: =$CP$4*Supuestos!F12*Supuestos!$B$5 -> 944.66115 | CM10: =$CP$4*Supuestos!G12*Supuestos!$B$5 -> 2065.6425 | CN10: =$CP$4*Supuestos!H12*Supuestos!$B$5 -> 2492.0275 | CO10: =$CP$4*Supuestos!I12*Supuestos!$B$5 -> 2594.7858 | CP10: =$CP$4*Supuestos!J12*Supuestos!$B$5 -> 1948.1719 | CQ10: =$CU$4*Supuestos!F12*Supuestos!$B$5 -> 1048.5804 | CR10: =$CU$4*Supuestos!G12*Supuestos!$B$5 -> 2292.8774 | CS10: =$CU$4*Supuestos!H12*Supuestos!$B$5 -> 2766.1677 | CT10: =$CU$4*Supuestos!I12*Supuestos!$B$5 -> 2880.2302 | CU10: =$CU$4*Supuestos!J12*Supuestos!$B$5 -> 2162.4843 | CV10: =CZ4*Supuestos!$F$12*Supuestos!$B$5 -> 1001.3395 | CW10: =CZ4*Supuestos!$G$12*Supuestos!$B$5 -> 2189.5781 | CX10: =CZ4*Supuestos!$H$12*Supuestos!$B$5 -> 2641.5456 | CY10: =CZ4*Supuestos!$I$12*Supuestos!$B$5 -> 2750.4692 | CZ10: =CZ4*Supuestos!$J$12*Supuestos!$B$5 -> 2065.0594 | DA10: =DE4*Supuestos!$F$12*Supuestos!$B$5 -> 1027.0608 | DB10: =DE4*Supuestos!$G$12*Supuestos!$B$5 -> 2245.8216 | DC10: =DE4*Supuestos!$H$12*Supuestos!$B$5 -> 2709.3988 | DD10: =DE4*Supuestos!$I$12*Supuestos!$B$5 -> 2821.1204 | DE10: =DE4*Supuestos!$J$12*Supuestos!$B$5 -> 2118.1045 | DF10: =DJ4*Supuestos!$F$12*Supuestos!$B$5 -> 965.95298 | DG10: =DJ4*Supuestos!$G$12*Supuestos!$B$5 -> 2112.2002 | DH10: =DJ4*Supuestos!$H$12*Supuestos!$B$5 -> 2548.1956 | DI10: =DJ4*Supuestos!$I$12*Supuestos!$B$5 -> 2653.27 | DJ10: =DJ4*Supuestos!$J$12*Supuestos!$B$5 -> 1992.0819 | DK10: =DO4*Supuestos!$F$12*Supuestos!$B$5 -> 500.83582 | DL10: =DO4*Supuestos!$G$12*Supuestos!$B$5 -> 1095.1522 | DM10: =DO4*Supuestos!$H$12*Supuestos!$B$5 -> 1321.2109 | DN10: =DO4*Supuestos!$I$12*Supuestos!$B$5 -> 1375.6908 | DO10: =DO4*Supuestos!$J$12*Supuestos!$B$5 -> 1032.8722 | DP10: =DT4*Supuestos!$F$12*Supuestos!$B$5 -> 1099.5588 | DQ10: =DT4*Supuestos!$G$12*Supuestos!$B$5 -> 2404.3493 | DR10: =DT4*Supuestos!$H$12*Supuestos!$B$5 -> 2900.6494 | DS10: =DT4*Supuestos!$I$12*Supuestos!$B$5 -> 3020.2572 | DT10: =DT4*Supuestos!$J$12*Supuestos!$B$5 -> 2267.6169 | DU10: =DY4*Supuestos!$F$12*Supuestos!$B$5 -> 926.35234 | DV10: =DY4*Supuestos!$G$12*Supuestos!$B$5 -> 2025.6075 | DW10: =DY4*Supuestos!$H$12*Supuestos!$B$5 -> 2443.7286 | DX10: =DY4*Supuestos!$I$12*Supuestos!$B$5 -> 2544.4953 | DY10: =DY4*Supuestos!$J$12*Supuestos!$B$5 -> 1910.4137 | DZ10: =ED4*Supuestos!$F$12*Supuestos!$B$5 -> 998.31555 | EA10: =ED4*Supuestos!$G$12*Supuestos!$B$5 -> 2182.9658 | EB10: =ED4*Supuestos!$H$12*Supuestos!$B$5 -> 2633.5684 | EC10: =ED4*Supuestos!$I$12*Supuestos!$B$5 -> 2742.1632 | ED10: =ED4*Supuestos!$J$12*Supuestos!$B$5 -> 2058.8232 | EE10: =EI4*Supuestos!$F$12*Supuestos!$B$5 -> 965.75777 | EF10: =EI4*Supuestos!$G$12*Supuestos!$B$5 -> 2111.7734 | EG10: =EI4*Supuestos!$H$12*Supuestos!$B$5 -> 2547.6806 | EH10: =EI4*Supuestos!$I$12*Supuestos!$B$5 -> 2652.7338 | EI10: =EI4*Supuestos!$J$12*Supuestos!$B$5 -> 1991.6794 | EJ10: =EN4*Supuestos!$F$12*Supuestos!$B$5 -> 1093.476 | EK10: =EN4*Supuestos!$G$12*Supuestos!$B$5 -> 2391.0484 | EL10: =EN4*Supuestos!$H$12*Supuestos!$B$5 -> 2884.6029 | EM10: =EN4*Supuestos!$I$12*Supuestos!$B$5 -> 3003.549 | EN10: =EN4*Supuestos!$J$12*Supuestos!$B$5 -> 2255.0723 | EO10: =ES4*Supuestos!$F$12*Supuestos!$B$5 -> 849.80053 | EP10: =ES4*Supuestos!$G$12*Supuestos!$B$5 -> 1858.2156 | EQ10: =ES4*Supuestos!$H$12*Supuestos!$B$5 -> 2241.784 | ER10: =ES4*Supuestos!$I$12*Supuestos!$B$5 -> 2334.2236 | ES10: =ES4*Supuestos!$J$12*Supuestos!$B$5 -> 1752.5411 | ET10: =EX4*Supuestos!$F$12*Supuestos!$B$5 -> 1105.2535 | EU10: =EX4*Supuestos!$G$12*Supuestos!$B$5 -> 2416.8017 | EV10: =EX4*Supuestos!$H$12*Supuestos!$B$5 -> 2915.6722 | EW10: =EX4*Supuestos!$I$12*Supuestos!$B$5 -> 3035.8994 | EX10: =EX4*Supuestos!$J$12*Supuestos!$B$5 -> 2279.3611 | EY10: =FC4*Supuestos!$F$12*Supuestos!$B$5 -> 1226.8391 | EZ10: =FC4*Supuestos!$G$12*Supuestos!$B$5 -> 2682.6666 | FA10: =FC4*Supuestos!$H$12*Supuestos!$B$5 -> 3236.4163 | FB10: =FC4*Supuestos!$I$12*Supuestos!$B$5 -> 3369.8693 | FC10: =FC4*Supuestos!$J$12*Supuestos!$B$5 -> 2530.1066 | FD10: =FH4*Supuestos!$F$12*Supuestos!$B$5 -> 1171.5672 | FE10: =FH4*Supuestos!$G$12*Supuestos!$B$5 -> 2561.8064 | FF10: =FH4*Supuestos!$H$12*Supuestos!$B$5 -> 3090.6083 | FG10: =FH4*Supuestos!$I$12*Supuestos!$B$5 -> 3218.049 | FH10: =FH4*Supuestos!$J$12*Supuestos!$B$5 -> 2416.1195 | FI10: =FM4*Supuestos!$F$12*Supuestos!$B$5 -> 1201.6612 | FJ10: =FM4*Supuestos!$G$12*Supuestos!$B$5 -> 2627.6113 | FK10: =FM4*Supuestos!$H$12*Supuestos!$B$5 -> 3169.9966 | FL10: =FM4*Supuestos!$I$12*Supuestos!$B$5 -> 3300.7108 | FM10: =FM4*Supuestos!$J$12*Supuestos!$B$5 -> 2478.1822 | FN10: =FR4*Supuestos!$F$12*Supuestos!$B$5 -> 1130.165 | FO10: =FR4*Supuestos!$G$12*Supuestos!$B$5 -> 2471.2743 | FP10: =FR4*Supuestos!$H$12*Supuestos!$B$5 -> 2981.3888 | FQ10: =FR4*Supuestos!$I$12*Supuestos!$B$5 -> 3104.3258 | FR10: =FR4*Supuestos!$J$12*Supuestos!$B$5 -> 2330.7359 | FS10: =FW4*Supuestos!$F$12*Supuestos!$B$5 -> 585.97791 | FT10: =FW4*Supuestos!$G$12*Supuestos!$B$5 -> 1281.3281 | FU10: =FW4*Supuestos!$H$12*Supuestos!$B$5 -> 1545.8168 | FV10: =FW4*Supuestos!$I$12*Supuestos!$B$5 -> 1609.5583 | FW10: =FW4*Supuestos!$J$12*Supuestos!$B$5 -> 1208.4605 | FX10: =GB4*Supuestos!$F$12*Supuestos!$B$5 -> 1280.986 | FY10: =GB4*Supuestos!$G$12*Supuestos!$B$5 -> 2801.067 | FZ10: =GB4*Supuestos!$H$12*Supuestos!$B$5 -> 3379.2566 | GA10: =GB4*Supuestos!$I$12*Supuestos!$B$5 -> 3518.5996 | GB10: =GB4*Supuestos!$J$12*Supuestos!$B$5 -> 2641.7737 | GC10: =GF4*Supuestos!$F$13*Supuestos!$B$5 -> 1372.5903 | GD10: =GF4*Supuestos!$G$13*Supuestos!$B$5 -> 2105.9399 | GE10: =GF4*Supuestos!$H$13*Supuestos!$B$5 -> 2694.567 | GF10: =GF4*Supuestos!$I$13*Supuestos!$B$5 -> 5302.8489 | GG10: =GK4*Supuestos!$F$12*Supuestos!$B$5 -> 1163.0376 | GH10: =GK4*Supuestos!$G$12*Supuestos!$B$5 -> 2543.1552 | GI10: =GK4*Supuestos!$H$12*Supuestos!$B$5 -> 3068.1072 | GJ10: =GK4*Supuestos!$I$12*Supuestos!$B$5 -> 3194.6201 | GK10: =GK4*Supuestos!$J$12*Supuestos!$B$5 -> 2398.529 | GL10: =GP4*Supuestos!$F$12*Supuestos!$B$5 -> 1125.1078 | GM10: =GP4*Supuestos!$G$12*Supuestos!$B$5 -> 2460.216 | GN10: =GP4*Supuestos!$H$12*Supuestos!$B$5 -> 2968.0479 | GO10: =GP4*Supuestos!$I$12*Supuestos!$B$5 -> 3090.4348 | GP10: =GP4*Supuestos!$J$12*Supuestos!$B$5 -> 2320.3065 | GQ10: =GU4*Supuestos!$F$12*Supuestos!$B$5 -> 1273.8996 | GR10: =GU4*Supuestos!$G$12*Supuestos!$B$5 -> 2785.5714 | GS10: =GU4*Supuestos!$H$12*Supuestos!$B$5 -> 3360.5624 | GT10: =GU4*Supuestos!$I$12*Supuestos!$B$5 -> 3499.1346 | GU10: =GU4*Supuestos!$J$12*Supuestos!$B$5 -> 2627.1593 | GV10: =GZ4*Supuestos!$F$12*Supuestos!$B$5 -> 990.01762 | GW10: =GZ4*Supuestos!$G$12*Supuestos!$B$5 -> 2164.8212 | GX10: =GZ4*Supuestos!$H$12*Supuestos!$B$5 -> 2611.6784 | GY10: =GZ4*Supuestos!$I$12*Supuestos!$B$5 -> 2719.3705 | GZ10: =GZ4*Supuestos!$J$12*Supuestos!$B$5 -> 2041.7104 | HA10: =HE4*Supuestos!$F$12*Supuestos!$B$5 -> 1287.6204 | HB10: =HE4*Supuestos!$G$12*Supuestos!$B$5 -> 2815.574 | HC10: =HE4*Supuestos!$H$12*Supuestos!$B$5 -> 3396.7581 | HD10: =HE4*Supuestos!$I$12*Supuestos!$B$5 -> 3536.8228 | HE10: =HE4*Supuestos!$J$12*Supuestos!$B$5 -> 2655.4557 | HF10: =HJ4*Supuestos!$F$12*Supuestos!$B$5 -> 1429.2675 | HG10: =HJ4*Supuestos!$G$12*Supuestos!$B$5 -> 3125.3066 | HH10: =HJ4*Supuestos!$H$12*Supuestos!$B$5 -> 3770.4249 | HI10: =HJ4*Supuestos!$I$12*Supuestos!$B$5 -> 3925.8977 | HJ10: =HJ4*Supuestos!$J$12*Supuestos!$B$5 -> 2947.5742 | HK10: =HO4*Supuestos!$F$12*Supuestos!$B$5 -> 1364.8758 | HL10: =HO4*Supuestos!$G$12*Supuestos!$B$5 -> 2984.5044 | HM10: =HO4*Supuestos!$H$12*Supuestos!$B$5 -> 3600.5587 | HN10: =HO4*Supuestos!$I$12*Supuestos!$B$5 -> 3749.0271 | HO10: =HO4*Supuestos!$J$12*Supuestos!$B$5 -> 2814.7792 | HP10: =HT4*Supuestos!$F$12*Supuestos!$B$5 -> 1399.9353 | HQ10: =HT4*Supuestos!$G$12*Supuestos!$B$5 -> 3061.1672 | HR10: =HT4*Supuestos!$H$12*Supuestos!$B$5 -> 3693.0461 | HS10: =HT4*Supuestos!$I$12*Supuestos!$B$5 -> 3845.3281 | HT10: =HT4*Supuestos!$J$12*Supuestos!$B$5 -> 2887.0823 | HU10: =HY4*Supuestos!$F$12*Supuestos!$B$5 -> 1316.6422 | HV10: =HY4*Supuestos!$G$12*Supuestos!$B$5 -> 2879.0345 | HW10: =HY4*Supuestos!$H$12*Supuestos!$B$5 -> 3473.318 | HX10: =HY4*Supuestos!$I$12*Supuestos!$B$5 -> 3616.5396 | HY10: =HY4*Supuestos!$J$12*Supuestos!$B$5 -> 2715.3073 | HZ10: =ID4*Supuestos!$F$12*Supuestos!$B$5 -> 682.66427 | IA10: =ID4*Supuestos!$G$12*Supuestos!$B$5 -> 1492.7472 | IB10: =ID4*Supuestos!$H$12*Supuestos!$B$5 -> 1800.8766 | IC10: =ID4*Supuestos!$I$12*Supuestos!$B$5 -> 1875.1354 | ID10: =ID4*Supuestos!$J$12*Supuestos!$B$5 -> 1407.8565 | IE10: =II4*Supuestos!$F$12*Supuestos!$B$5 -> 1485.9438 | IF10: =II4*Supuestos!$G$12*Supuestos!$B$5 -> 3249.2377 | IG10: =II4*Supuestos!$H$12*Supuestos!$B$5 -> 3919.9376 | IH10: =II4*Supuestos!$I$12*Supuestos!$B$5 -> 4081.5755 | II10: =II4*Supuestos!$J$12*Supuestos!$B$5 -> 3064.4574 | IJ10: =IM4*Supuestos!$F$13*Supuestos!$B$5 -> 1592.2047 | IK10: =IM4*Supuestos!$G$13*Supuestos!$B$5 -> 2442.8902 | IL10: =IM4*Supuestos!$H$13*Supuestos!$B$5 -> 3125.6977 | IM10: =IM4*Supuestos!$I$13*Supuestos!$B$5 -> 6151.3048 | IN10: =IR4*Supuestos!$F$12*Supuestos!$B$5 -> 1349.1236 | IO10: =IR4*Supuestos!$G$12*Supuestos!$B$5 -> 2950.06 | IP10: =IR4*Supuestos!$H$12*Supuestos!$B$5 -> 3559.0044 | IQ10: =IR4*Supuestos!$I$12*Supuestos!$B$5 -> 3705.7593 | IR10: =IR4*Supuestos!$J$12*Supuestos!$B$5 -> 2782.2937 | IS10: =IW4*Supuestos!$F$12*Supuestos!$B$5 -> 1305.1251 | IT10: =IW4*Supuestos!$G$12*Supuestos!$B$5 -> 2853.8505 | IU10: =IW4*Supuestos!$H$12*Supuestos!$B$5 -> 3442.9356 | IV10: =IW4*Supuestos!$I$12*Supuestos!$B$5 -> 3584.9044 | IW10: =IW4*Supuestos!$J$12*Supuestos!$B$5 -> 2691.5555 | IX10: =JB4*Supuestos!$F$12*Supuestos!$B$5 -> 1477.7235 | IY10: =JB4*Supuestos!$G$12*Supuestos!$B$5 -> 3231.2628 | IZ10: =JB4*Supuestos!$H$12*Supuestos!$B$5 -> 3898.2524 | JA10: =JB4*Supuestos!$I$12*Supuestos!$B$5 -> 4058.9961 | JB10: =JB4*Supuestos!$J$12*Supuestos!$B$5 -> 3047.5048 | JC10: =JG4*Supuestos!$F$12*Supuestos!$B$5 -> 1148.4204 | JD10: =JG4*Supuestos!$G$12*Supuestos!$B$5 -> 2511.1925 | JE10: =JG4*Supuestos!$H$12*Supuestos!$B$5 -> 3029.547 | JF10: =JG4*Supuestos!$I$12*Supuestos!$B$5 -> 3154.4698 | JG10: =JG4*Supuestos!$J$12*Supuestos!$B$5 -> 2368.3841 | JH10: =JL4*Supuestos!$F$12*Supuestos!$B$5 -> 1493.6396 | JI10: =JL4*Supuestos!$G$12*Supuestos!$B$5 -> 3266.0658 | JJ10: =JL4*Supuestos!$H$12*Supuestos!$B$5 -> 3940.2394 | JK10: =JL4*Supuestos!$I$12*Supuestos!$B$5 -> 4102.7144 | JL10: =JL4*Supuestos!$J$12*Supuestos!$B$5 -> 3080.3286 | JM10: =JQ4*Supuestos!$F$12*Supuestos!$B$5 -> 1657.9503 | JN10: =JQ4*Supuestos!$G$12*Supuestos!$B$5 -> 3625.3556 | JO10: =JQ4*Supuestos!$H$12*Supuestos!$B$5 -> 4373.6929 | JP10: =JQ4*Supuestos!$I$12*Supuestos!$B$5 -> 4554.0414 | JQ10: =JQ4*Supuestos!$J$12*Supuestos!$B$5 -> 3419.186 | JR10: =JV4*Supuestos!$F$12*Supuestos!$B$5 -> 1583.2559 | JS10: =JV4*Supuestos!$G$12*Supuestos!$B$5 -> 3462.0251 | JT10: =JV4*Supuestos!$H$12*Supuestos!$B$5 -> 4176.6481 | JU10: =JV4*Supuestos!$I$12*Supuestos!$B$5 -> 4348.8714 | JV10: =JV4*Supuestos!$J$12*Supuestos!$B$5 -> 3265.1439 | JW10: =KA4*Supuestos!$F$12*Supuestos!$B$5 -> 1623.9249 | JX10: =KA4*Supuestos!$G$12*Supuestos!$B$5 -> 3550.954 | JY10: =KA4*Supuestos!$H$12*Supuestos!$B$5 -> 4283.9334 | JZ10: =KA4*Supuestos!$I$12*Supuestos!$B$5 -> 4460.5806 | KA10: =KA4*Supuestos!$J$12*Supuestos!$B$5 -> 3349.0155 | KB10: =KF4*Supuestos!$F$12*Supuestos!$B$5 -> 1527.305 | KC10: =KF4*Supuestos!$G$12*Supuestos!$B$5 -> 3339.68 | KD10: =KF4*Supuestos!$H$12*Supuestos!$B$5 -> 4029.0489 | KE10: =KF4*Supuestos!$I$12*Supuestos!$B$5 -> 4195.1859 | KF10: =KF4*Supuestos!$J$12*Supuestos!$B$5 -> 3149.7565 | KG10: =KK4*Supuestos!$F$12*Supuestos!$B$5 -> 791.89055 | KH10: =KK4*Supuestos!$G$12*Supuestos!$B$5 -> 1731.5868 | KI10: =KK4*Supuestos!$H$12*Supuestos!$B$5 -> 2089.0168 | KJ10: =KK4*Supuestos!$I$12*Supuestos!$B$5 -> 2175.157 | KK10: =KK4*Supuestos!$J$12*Supuestos!$B$5 -> 1633.1135 | KL10: =KP4*Supuestos!$F$12*Supuestos!$B$5 -> 1716.2651 | KM10: =KP4*Supuestos!$G$12*Supuestos!$B$5 -> 3752.8695 | KN10: =KP4*Supuestos!$H$12*Supuestos!$B$5 -> 4527.5279 | KO10: =KP4*Supuestos!$I$12*Supuestos!$B$5 -> 4714.2197 | KP10: =KP4*Supuestos!$J$12*Supuestos!$B$5 -> 3539.4484 | KQ10: =KT4*Supuestos!$F$13*Supuestos!$B$5 -> 1838.9965 | KR10: =KT4*Supuestos!$G$13*Supuestos!$B$5 -> 2821.5382 | KS10: =KT4*Supuestos!$H$13*Supuestos!$B$5 -> 3610.1809 | KT10: =KT4*Supuestos!$I$13*Supuestos!$B$5 -> 7104.757 | KU10: =KY4*Supuestos!$F$12*Supuestos!$B$5 -> 1558.2378 | KV10: =KY4*Supuestos!$G$12*Supuestos!$B$5 -> 3407.3193 | KW10: =KY4*Supuestos!$H$12*Supuestos!$B$5 -> 4110.6501 | KX10: =KY4*Supuestos!$I$12*Supuestos!$B$5 -> 4280.152 | KY10: =KY4*Supuestos!$J$12*Supuestos!$B$5 -> 3213.5492 | KZ10: =LD4*Supuestos!$F$12*Supuestos!$B$5 -> 1507.4194 | LA10: =LD4*Supuestos!$G$12*Supuestos!$B$5 -> 3296.1974 | LB10: =LD4*Supuestos!$H$12*Supuestos!$B$5 -> 3976.5906 | LC10: =LD4*Supuestos!$I$12*Supuestos!$B$5 -> 4140.5646 | LD10: =LD4*Supuestos!$J$12*Supuestos!$B$5 -> 3108.7466 | LE10: =LI4*Supuestos!$F$12*Supuestos!$B$5 -> 1706.7706 | LF10: =LI4*Supuestos!$G$12*Supuestos!$B$5 -> 3732.1085 | LG10: =LI4*Supuestos!$H$12*Supuestos!$B$5 -> 4502.4815 | LH10: =LI4*Supuestos!$I$12*Supuestos!$B$5 -> 4688.1405 | LI10: =LI4*Supuestos!$J$12*Supuestos!$B$5 -> 3519.868 | LJ10: =LN4*Supuestos!$F$12*Supuestos!$B$5 -> 1326.4256 | LK10: =LN4*Supuestos!$G$12*Supuestos!$B$5 -> 2900.4274 | LL10: =LN4*Supuestos!$H$12*Supuestos!$B$5 -> 3499.1267 | LM10: =LN4*Supuestos!$I$12*Supuestos!$B$5 -> 3643.4126 | LN10: =LN4*Supuestos!$J$12*Supuestos!$B$5 -> 2735.4836 | LO10: =LS4*Supuestos!$F$12*Supuestos!$B$5 -> 1725.1538 | LP10: =LS4*Supuestos!$G$12*Supuestos!$B$5 -> 3772.306 | LQ10: =LS4*Supuestos!$H$12*Supuestos!$B$5 -> 4550.9765 | LR10: =LS4*Supuestos!$I$12*Supuestos!$B$5 -> 4738.6351 | LS10: =LS4*Supuestos!$J$12*Supuestos!$B$5 -> 3557.7795 | LT10: =LX4*Supuestos!$F$12*Supuestos!$B$5 -> 1914.9326 | LU10: =LX4*Supuestos!$G$12*Supuestos!$B$5 -> 4187.2858 | LV10: =LX4*Supuestos!$H$12*Supuestos!$B$5 -> 5051.6153 | LW10: =LX4*Supuestos!$I$12*Supuestos!$B$5 -> 5259.9178 | LX10: =LX4*Supuestos!$J$12*Supuestos!$B$5 -> 3949.1599 | LY10: =MC4*Supuestos!$F$12*Supuestos!$B$5 -> 1828.6606 | LZ10: =MC4*Supuestos!$G$12*Supuestos!$B$5 -> 3998.639 | MA10: =MC4*Supuestos!$H$12*Supuestos!$B$5 -> 4824.0286 | MB10: =MC4*Supuestos!$I$12*Supuestos!$B$5 -> 5022.9465 | MC10: =MC4*Supuestos!$J$12*Supuestos!$B$5 -> 3771.2412 | MD10: =MH4*Supuestos!$F$12*Supuestos!$B$5 -> 1875.6333 | ME10: =MH4*Supuestos!$G$12*Supuestos!$B$5 -> 4101.3518 | MF10: =MH4*Supuestos!$H$12*Supuestos!$B$5 -> 4947.9431 | MG10: =MH4*Supuestos!$I$12*Supuestos!$B$5 -> 5151.9706 | MH10: =MH4*Supuestos!$J$12*Supuestos!$B$5 -> 3868.1129 | MI10: =MM4*Supuestos!$F$12*Supuestos!$B$5 -> 1764.0372 | MJ10: =MM4*Supuestos!$G$12*Supuestos!$B$5 -> 3857.3304 | MK10: =MM4*Supuestos!$H$12*Supuestos!$B$5 -> 4653.5514 | ML10: =MM4*Supuestos!$I$12*Supuestos!$B$5 -> 4845.4398 | MM10: =MM4*Supuestos!$J$12*Supuestos!$B$5 -> 3637.9687 | MN10: =MR4*Supuestos!$F$12*Supuestos!$B$5 -> 914.63358 | MO10: =MR4*Supuestos!$G$12*Supuestos!$B$5 -> 1999.9827 | MP10: =MR4*Supuestos!$H$12*Supuestos!$B$5 -> 2412.8144 | MQ10: =MR4*Supuestos!$I$12*Supuestos!$B$5 -> 2512.3064 | MR10: =MR4*Supuestos!$J$12*Supuestos!$B$5 -> 1886.2461 | MS10: =MW4*Supuestos!$F$12*Supuestos!$B$5 -> 1956.5422 | MT10: =MW4*Supuestos!$G$12*Supuestos!$B$5 -> 4278.2713 | MU10: =MW4*Supuestos!$H$12*Supuestos!$B$5 -> 5161.3819 | MV10: =MW4*Supuestos!$I$12*Supuestos!$B$5 -> 5374.2105 | MW10: =MW4*Supuestos!$J$12*Supuestos!$B$5 -> 4034.9711 | MX10: =NB4*Supuestos!$F$12*Supuestos!$B$5 -> 1648.3406 | MY10: =NB4*Supuestos!$G$12*Supuestos!$B$5 -> 3604.3425 | MZ10: =NB4*Supuestos!$H$12*Supuestos!$B$5 -> 4348.3423 | NA10: =NB4*Supuestos!$I$12*Supuestos!$B$5 -> 4527.6454 | NB10: =NB4*Supuestos!$J$12*Supuestos!$B$5 -> 3399.3679 | NC10: =NG4*Supuestos!$F$12*Supuestos!$B$5 -> 1776.3911 | ND10: =NG4*Supuestos!$G$12*Supuestos!$B$5 -> 3884.344 | NE10: =NG4*Supuestos!$H$12*Supuestos!$B$5 -> 4686.1411 | NF10: =NG4*Supuestos!$I$12*Supuestos!$B$5 -> 4879.3732 | NG10: =NG4*Supuestos!$J$12*Supuestos!$B$5 -> 3663.4461 | NH10: =NL4*Supuestos!$F$12*Supuestos!$B$5 -> 1718.4582 | NI10: =NL4*Supuestos!$G$12*Supuestos!$B$5 -> 3757.665 | NJ10: =NL4*Supuestos!$H$12*Supuestos!$B$5 -> 4533.3133 | NK10: =NL4*Supuestos!$I$12*Supuestos!$B$5 -> 4720.2436 | NL10: =NL4*Supuestos!$J$12*Supuestos!$B$5 -> 3543.9711 | NM10: =NQ4*Supuestos!$F$12*Supuestos!$B$5 -> 1945.7185 | NN10: =NQ4*Supuestos!$G$12*Supuestos!$B$5 -> 4254.6037 | NO10: =NQ4*Supuestos!$H$12*Supuestos!$B$5 -> 5132.8289 | NP10: =NQ4*Supuestos!$I$12*Supuestos!$B$5 -> 5344.4802 | NQ10: =NQ4*Supuestos!$J$12*Supuestos!$B$5 -> 4012.6495 | NR10: =NV4*Supuestos!$F$12*Supuestos!$B$5 -> 1512.1252 | NS10: =NV4*Supuestos!$G$12*Supuestos!$B$5 -> 3306.4872 | NT10: =NV4*Supuestos!$H$12*Supuestos!$B$5 -> 3989.0045 | NU10: =NV4*Supuestos!$I$12*Supuestos!$B$5 -> 4153.4903 | NV10: =NV4*Supuestos!$J$12*Supuestos!$B$5 -> 3118.4513 | NW10: =OA4*Supuestos!$F$12*Supuestos!$B$5 -> 1966.6753 | NX10: =OA4*Supuestos!$G$12*Supuestos!$B$5 -> 4300.4288 | NY10: =OA4*Supuestos!$H$12*Supuestos!$B$5 -> 5188.1132 | NZ10: =OA4*Supuestos!$I$12*Supuestos!$B$5 -> 5402.0441 | OA10: =OA4*Supuestos!$J$12*Supuestos!$B$5 -> 4055.8686 | OB10: =OF4*Supuestos!$F$12*Supuestos!$B$5 -> 2183.0232 | OC10: =OF4*Supuestos!$G$12*Supuestos!$B$5 -> 4773.5058 | OD10: =OF4*Supuestos!$H$12*Supuestos!$B$5 -> 5758.8415 | OE10: =OF4*Supuestos!$I$12*Supuestos!$B$5 -> 5996.3063 | OF10: =OF4*Supuestos!$J$12*Supuestos!$B$5 -> 4502.0422 | OG10: =OK4*Supuestos!$F$12*Supuestos!$B$5 -> 2084.673 | OH10: =OK4*Supuestos!$G$12*Supuestos!$B$5 -> 4558.4485 | OI10: =OK4*Supuestos!$H$12*Supuestos!$B$5 -> 5499.3926 | OJ10: =OK4*Supuestos!$I$12*Supuestos!$B$5 -> 5726.159 | OK10: =OK4*Supuestos!$J$12*Supuestos!$B$5 -> 4299.215 | OL10: =OP4*Supuestos!$F$12*Supuestos!$B$5 -> 2138.2219 | OM10: =OP4*Supuestos!$G$12*Supuestos!$B$5 -> 4675.5411 | ON10: =OP4*Supuestos!$H$12*Supuestos!$B$5 -> 5640.6552 | OO10: =OP4*Supuestos!$I$12*Supuestos!$B$5 -> 5873.2465 | OP10: =OP4*Supuestos!$J$12*Supuestos!$B$5 -> 4409.6487 | OQ10: =OU4*Supuestos!$F$12*Supuestos!$B$5 -> 2011.0024 | OR10: =OU4*Supuestos!$G$12*Supuestos!$B$5 -> 4397.3567 | OS10: =OU4*Supuestos!$H$12*Supuestos!$B$5 -> 5305.0486 | OT10: =OU4*Supuestos!$I$12*Supuestos!$B$5 -> 5523.8013 | OU10: =OU4*Supuestos!$J$12*Supuestos!$B$5 -> 4147.2843 | OV10: =OZ4*Supuestos!$F$12*Supuestos!$B$5 -> 1042.6823 | OW10: =OZ4*Supuestos!$G$12*Supuestos!$B$5 -> 2279.9803 | OX10: =OZ4*Supuestos!$H$12*Supuestos!$B$5 -> 2750.6084 | OY10: =OZ4*Supuestos!$I$12*Supuestos!$B$5 -> 2864.0292 | OZ10: =OZ4*Supuestos!$J$12*Supuestos!$B$5 -> 2150.3206 | PA10: =PE4*Supuestos!$F$12*Supuestos!$B$5 -> 2230.4581 | PB10: =PE4*Supuestos!$G$12*Supuestos!$B$5 -> 4877.2292 | PC10: =PE4*Supuestos!$H$12*Supuestos!$B$5 -> 5883.9753 | PD10: =PE4*Supuestos!$I$12*Supuestos!$B$5 -> 6126.5999 | PE10: =PE4*Supuestos!$J$12*Supuestos!$B$5 -> 4599.8671 | PF10: =PI4*Supuestos!$F$13*Supuestos!$B$5 -> 2389.9598 | PG10: =PI4*Supuestos!$G$13*Supuestos!$B$5 -> 3666.8711 | PH10: =PI4*Supuestos!$H$13*Supuestos!$B$5 -> 4691.791 | PI10: =PI4*Supuestos!$I$13*Supuestos!$B$5 -> 9233.3422 | PJ10: =PN4*Supuestos!$F$12*Supuestos!$B$5 -> 2025.0858 | PK10: =PN4*Supuestos!$G$12*Supuestos!$B$5 -> 4428.1522 | PL10: =PN4*Supuestos!$H$12*Supuestos!$B$5 -> 5342.2008 | PM10: =PN4*Supuestos!$I$12*Supuestos!$B$5 -> 5562.4855 | PN10: =PN4*Supuestos!$J$12*Supuestos!$B$5 -> 4176.3285 | PO10: =PS4*Supuestos!$F$12*Supuestos!$B$5 -> 1959.0423 | PP10: =PS4*Supuestos!$G$12*Supuestos!$B$5 -> 4283.7381 | PQ10: =PS4*Supuestos!$H$12*Supuestos!$B$5 -> 5167.9772 | PR10: =PS4*Supuestos!$I$12*Supuestos!$B$5 -> 5381.0777 | PS10: =PS4*Supuestos!$J$12*Supuestos!$B$5 -> 4040.1271 | PT10: =PX4*Supuestos!$F$12*Supuestos!$B$5 -> 2218.1191 | PU10: =PX4*Supuestos!$G$12*Supuestos!$B$5 -> 4850.2482 | PV10: =PX4*Supuestos!$H$12*Supuestos!$B$5 -> 5851.425 | PW10: =PX4*Supuestos!$I$12*Supuestos!$B$5 -> 6092.7074 | PX10: =PX4*Supuestos!$J$12*Supuestos!$B$5 -> 4574.4205 | PY10: =QC4*Supuestos!$F$12*Supuestos!$B$5 -> 1723.8227 | PZ10: =QC4*Supuestos!$G$12*Supuestos!$B$5 -> 3769.3954 | QA10: =QC4*Supuestos!$H$12*Supuestos!$B$5 -> 4547.4651 | QB10: =QC4*Supuestos!$I$12*Supuestos!$B$5 -> 4734.979 | QC10: =QC4*Supuestos!$J$12*Supuestos!$B$5 -> 3555.0345 | QD10: =QH4*Supuestos!$F$12*Supuestos!$B$5 -> 2242.0099 | QE10: =QH4*Supuestos!$G$12*Supuestos!$B$5 -> 4902.4889 | QF10: =QH4*Supuestos!$H$12*Supuestos!$B$5 -> 5914.449 | QG10: =QH4*Supuestos!$I$12*Supuestos!$B$5 -> 6158.3302 | QH10: =QH4*Supuestos!$J$12*Supuestos!$B$5 -> 4623.6903 | QI10: =QM4*Supuestos!$F$12*Supuestos!$B$5 -> 2488.6465 | QJ10: =QM4*Supuestos!$G$12*Supuestos!$B$5 -> 5441.7966 | QK10: =QM4*Supuestos!$H$12*Supuestos!$B$5 -> 6565.0793 | QL10: =QM4*Supuestos!$I$12*Supuestos!$B$5 -> 6835.7891 | QM10: =QM4*Supuestos!$J$12*Supuestos!$B$5 -> 5132.3282 | QN10: =QR4*Supuestos!$F$12*Supuestos!$B$5 -> 2376.5273 | QO10: =QR4*Supuestos!$G$12*Supuestos!$B$5 -> 5196.6312 | QP10: =QR4*Supuestos!$H$12*Supuestos!$B$5 -> 6269.3075 | QQ10: =QR4*Supuestos!$I$12*Supuestos!$B$5 -> 6527.8213 | QR10: =QR4*Supuestos!$J$12*Supuestos!$B$5 -> 4901.1051 | QS10: =QW4*Supuestos!$F$12*Supuestos!$B$5 -> 2437.573 | QT10: =QW4*Supuestos!$G$12*Supuestos!$B$5 -> 5330.1168 | QU10: =QW4*Supuestos!$H$12*Supuestos!$B$5 -> 6430.3469 | QV10: =QW4*Supuestos!$I$12*Supuestos!$B$5 -> 6695.501 | QW10: =QW4*Supuestos!$J$12*Supuestos!$B$5 -> 5026.9995 | QX10: =RB4*Supuestos!$F$12*Supuestos!$B$5 -> 2292.5428 | QY10: =RB4*Supuestos!$G$12*Supuestos!$B$5 -> 5012.9866 | QZ10: =RB4*Supuestos!$H$12*Supuestos!$B$5 -> 6047.7555 | RA10: =RB4*Supuestos!$I$12*Supuestos!$B$5 -> 6297.1335 | RB10: =RB4*Supuestos!$J$12*Supuestos!$B$5 -> 4727.9041 | RC10: =RG4*Supuestos!$F$12*Supuestos!$B$5 -> 1188.6578 | RD10: =RG4*Supuestos!$G$12*Supuestos!$B$5 -> 2599.1775 | RE10: =RG4*Supuestos!$H$12*Supuestos!$B$5 -> 3135.6936 | RF10: =RG4*Supuestos!$I$12*Supuestos!$B$5 -> 3264.9933 | RG10: =RG4*Supuestos!$J$12*Supuestos!$B$5 -> 2451.3654 | RH10: =RL4*Supuestos!$F$12*Supuestos!$B$5 -> 2542.7222 | RI10: =RL4*Supuestos!$G$12*Supuestos!$B$5 -> 5560.0413 | RJ10: =RL4*Supuestos!$H$12*Supuestos!$B$5 -> 6707.7319 | RK10: =RL4*Supuestos!$I$12*Supuestos!$B$5 -> 6984.3239 | RL10: =RL4*Supuestos!$J$12*Supuestos!$B$5 -> 5243.8485 | RM10: =RP4*Supuestos!$F$13*Supuestos!$B$5 -> 2724.5542 | RN10: =RP4*Supuestos!$G$13*Supuestos!$B$5 -> 4180.233 | RO10: =RP4*Supuestos!$H$13*Supuestos!$B$5 -> 5348.6418 | RP10: =RP4*Supuestos!$I$13*Supuestos!$B$5 -> 10526.01 | RQ10: =RU4*Supuestos!$F$12*Supuestos!$B$5 -> 2308.5979 | RR10: =RU4*Supuestos!$G$12*Supuestos!$B$5 -> 5048.0935 | RS10: =RU4*Supuestos!$H$12*Supuestos!$B$5 -> 6090.109 | RT10: =RU4*Supuestos!$I$12*Supuestos!$B$5 -> 6341.2335 | RU10: =RU4*Supuestos!$J$12*Supuestos!$B$5 -> 4761.0145 | RV10: =RZ4*Supuestos!$F$12*Supuestos!$B$5 -> 2233.3082 | RW10: =RZ4*Supuestos!$G$12*Supuestos!$B$5 -> 4883.4614 | RX10: =RZ4*Supuestos!$H$12*Supuestos!$B$5 -> 5891.494 | RY10: =RZ4*Supuestos!$I$12*Supuestos!$B$5 -> 6134.4286 | RZ10: =RZ4*Supuestos!$J$12*Supuestos!$B$5 -> 4605.7449 | SA10: =SE4*Supuestos!$F$12*Supuestos!$B$5 -> 2528.6558 | SB10: =SE4*Supuestos!$G$12*Supuestos!$B$5 -> 5529.283 | SC10: =SE4*Supuestos!$H$12*Supuestos!$B$5 -> 6670.6245 | SD10: =SE4*Supuestos!$I$12*Supuestos!$B$5 -> 6945.6864 | SE10: =SE4*Supuestos!$J$12*Supuestos!$B$5 -> 5214.8393 | SF10: =SJ4*Supuestos!$F$12*Supuestos!$B$5 -> 1965.1579 | SG10: =SJ4*Supuestos!$G$12*Supuestos!$B$5 -> 4297.1108 | SH10: =SJ4*Supuestos!$H$12*Supuestos!$B$5 -> 5184.1102 | SI10: =SJ4*Supuestos!$I$12*Supuestos!$B$5 -> 5397.876 | SJ10: =SJ4*Supuestos!$J$12*Supuestos!$B$5 -> 4052.7393 | SK10: =SO4*Supuestos!$F$12*Supuestos!$B$5 -> 2555.8912 | SL10: =SO4*Supuestos!$G$12*Supuestos!$B$5 -> 5588.8373 | SM10: =SO4*Supuestos!$H$12*Supuestos!$B$5 -> 6742.4719 | SN10: =SO4*Supuestos!$I$12*Supuestos!$B$5 -> 7020.4964 | SO10: =SO4*Supuestos!$J$12*Supuestos!$B$5 -> 5271.0069 | SP10: =ST4*Supuestos!$F$12*Supuestos!$B$5 -> 2837.057 | SQ10: =ST4*Supuestos!$G$12*Supuestos!$B$5 -> 6203.6481 | SR10: =ST4*Supuestos!$H$12*Supuestos!$B$5 -> 7484.1904 | SS10: =ST4*Supuestos!$I$12*Supuestos!$B$5 -> 7792.7996 | ST10: =ST4*Supuestos!$J$12*Supuestos!$B$5 -> 5850.8541 | SU10: =SY4*Supuestos!$F$12*Supuestos!$B$5 -> 2709.2411 | SV10: =SY4*Supuestos!$G$12*Supuestos!$B$5 -> 5924.1596 | SW10: =SY4*Supuestos!$H$12*Supuestos!$B$5 -> 7147.0106 | SX10: =SY4*Supuestos!$I$12*Supuestos!$B$5 -> 7441.7162 | SY10: =SY4*Supuestos!$J$12*Supuestos!$B$5 -> 5587.2598 | SZ10: =TD4*Supuestos!$F$12*Supuestos!$B$5 -> 2778.8332 | TA10: =TD4*Supuestos!$G$12*Supuestos!$B$5 -> 6076.3332 | TB10: =TD4*Supuestos!$H$12*Supuestos!$B$5 -> 7330.5955 | TC10: =TD4*Supuestos!$I$12*Supuestos!$B$5 -> 7632.8712 | TD10: =TD4*Supuestos!$J$12*Supuestos!$B$5 -> 5730.7794 | TE10: =TI4*Supuestos!$F$12*Supuestos!$B$5 -> 2613.4988 | TF10: =TI4*Supuestos!$G$12*Supuestos!$B$5 -> 5714.8048 | TG10: =TI4*Supuestos!$H$12*Supuestos!$B$5 -> 6894.4412 | TH10: =TI4*Supuestos!$I$12*Supuestos!$B$5 -> 7178.7322 | TI10: =TI4*Supuestos!$J$12*Supuestos!$B$5 -> 5389.8107 | TJ10: =TN4*Supuestos!$F$12*Supuestos!$B$5 -> 1355.0699 | TK10: =TN4*Supuestos!$G$12*Supuestos!$B$5 -> 2963.0624 | TL10: =TN4*Supuestos!$H$12*Supuestos!$B$5 -> 3574.6907 | TM10: =TN4*Supuestos!$I$12*Supuestos!$B$5 -> 3722.0924 | TN10: =TN4*Supuestos!$J$12*Supuestos!$B$5 -> 2794.5566
A11: Ingreso contado | B11: =Supuestos!$B$9*B10 -> 185.81112 | C11: =Supuestos!$B$9*C10+Supuestos!$C$9*B10 -> 1757.6958 | D11: =Supuestos!$B$9*D10+Supuestos!$C$9*C10 -> 1665.6714 | E11: =Supuestos!$B$9*E10+Supuestos!$C$9*D10 -> 2170.9486 | F11: =Supuestos!$B$9*F10+Supuestos!$C$9*E10 -> 1908.1862 | G11: =Supuestos!$B$9*G10+Supuestos!$C$9*F10 -> 980.82596 | H11: =Supuestos!$B$9*H10+Supuestos!$C$9*G10 -> 1087.0574 | I11: =Supuestos!$B$9*I10+Supuestos!$C$9*H10 -> 1351.9284 | J11: =Supuestos!$B$9*J10+Supuestos!$C$9*I10 -> 2255.3417 | ... TN11: =Supuestos!$B$9*TN10+Supuestos!$C$9*TM10 -> 3072.8173
A12: Crédito | B12: 272.61937 | C12: 1204.9517 | D12: 698.87129 | E12: 1232.3555 | F12: 871.6507 | G12: 559.66436 | H12: 672.08985 | I12: 1071.5909 | J12: 2226.8697 | K12: 507.36346 | L12: 658.97305 | M12: 1016.7283 | N12: 1427.9462 | O12: 952.43614 | P12: 175.86104 | Q12: 725.39556 | R12: 1117.6051 | S12: 948.51914 | T12: 1246.1626 | U12: 438.30413 | V12: 754.74567 | W12: 695.78918 | X12: 2269.8257 | Y12: 1092.2016 | Z12: 290.3613 | AA12: 616.17708 | AB12: 941.69852 | AC12: 850.21007 | AD12: 914.67196 | AE12: 533.30956 | AF12: 807.74182 | AG12: 2533.3943 | AH12: 607.92069 | AI12: 1193.0088 | AJ12: 340.18489 | AK12: 1399.6101 | AL12: 912.51463 | AM12: 989.182 | AN12: 479.40669 | AO12: 344.07025 | AP12: 631.63969 | AQ12: 1306.1734 | AR12: =$AS$4*Supuestos!I12*Supuestos!$B$6 -> 1166.1797 | AS12: =$AS$4*Supuestos!J12*Supuestos!$B$6+80.7879094587811 -> 956.35868 | AT12: =$AX$4*Supuestos!F12*Supuestos!$B$6 -> 435.46662 | AU12: =$AX$4*Supuestos!G12*Supuestos!$B$6 -> 952.2127 | AV12: =$AX$4*Supuestos!H12*Supuestos!$B$6 -> 1148.7662 | AW12: =$AX$4*Supuestos!I12*Supuestos!$B$6 -> 1196.1353 | AX12: =$AX$4*Supuestos!J12*Supuestos!$B$6 -> 898.06151 | AY12: =$BC$4*Supuestos!F12*Supuestos!$B$6 -> 409.55732 | AZ12: =$BC$4*Supuestos!G12*Supuestos!$B$6 -> 895.55814 | BA12: =$BC$4*Supuestos!H12*Supuestos!$B$6 -> 1080.4171 | BB12: =$BC$4*Supuestos!I12*Supuestos!$B$6 -> 1124.9679 | BC12: =$BC$4*Supuestos!J12*Supuestos!$B$6 -> 844.62883 | BD12: =$BH$4*Supuestos!F12*Supuestos!$B$6 -> 212.35089 | BE12: =$BH$4*Supuestos!G12*Supuestos!$B$6 -> 464.33689 | BF12: =$BH$4*Supuestos!H12*Supuestos!$B$6 -> 560.18421 | BG12: =$BH$4*Supuestos!I12*Supuestos!$B$6 -> 583.2833 | BH12: =$BH$4*Supuestos!J12*Supuestos!$B$6 -> 437.93061 | BI12: =$BM$4*Supuestos!F12*Supuestos!$B$6 -> 484.13623 | BJ12: =$BM$4*Supuestos!G12*Supuestos!$B$6 -> 1058.6361 | BK12: =$BM$4*Supuestos!H12*Supuestos!$B$6 -> 1277.1572 | BL12: =$BM$4*Supuestos!I12*Supuestos!$B$6 -> 1329.8206 | BM12: =$BM$4*Supuestos!J12*Supuestos!$B$6 -> 998.43271 | BN12: =$BQ$4*Supuestos!F13*Supuestos!$B$6 -> 518.75717 | BO12: =$BQ$4*Supuestos!G13*Supuestos!$B$6 -> 795.91953 | BP12: =$BQ$4*Supuestos!H13*Supuestos!$B$6 -> 1018.3854 | BQ12: =$BQ$4*Supuestos!I13*Supuestos!$B$6 -> 2004.1603 | BR12: =$BV$4*Supuestos!F12*Supuestos!$B$6 -> 439.55878 | BS12: =$BV$4*Supuestos!G12*Supuestos!$B$6 -> 961.16081 | BT12: =$BV$4*Supuestos!H12*Supuestos!$B$6 -> 1159.5613 | BU12: =$BV$4*Supuestos!I12*Supuestos!$B$6 -> 1207.3756 | BV12: =$BV$4*Supuestos!J12*Supuestos!$B$6 -> 906.50075 | BW12: =$CA$4*Supuestos!F12*Supuestos!$B$6 -> 425.22357 | BX12: =$CA$4*Supuestos!G12*Supuestos!$B$6 -> 929.81475 | BY12: =$CA$4*Supuestos!H12*Supuestos!$B$6 -> 1121.7449 | BZ12: =$CA$4*Supuestos!I12*Supuestos!$B$6 -> 1167.9998 | CA12: =$CA$4*Supuestos!J12*Supuestos!$B$6 -> 876.9373 | CB12: =$CF$4*Supuestos!F12*Supuestos!$B$6 -> 481.45797 | CC12: =$CF$4*Supuestos!G12*Supuestos!$B$6 -> 1052.7797 | CD12: =$CF$4*Supuestos!H12*Supuestos!$B$6 -> 1270.0919 | CE12: =$CF$4*Supuestos!I12*Supuestos!$B$6 -> 1322.4639 | CF12: =$CF$4*Supuestos!J12*Supuestos!$B$6 -> 992.90935 | CG12: =$CK$4*Supuestos!F12*Supuestos!$B$6 -> 374.16755 | CH12: =$CK$4*Supuestos!G12*Supuestos!$B$6 -> 818.17314 | CI12: =$CK$4*Supuestos!H12*Supuestos!$B$6 -> 987.0585 | CJ12: =$CK$4*Supuestos!I12*Supuestos!$B$6 -> 1027.7597 | CK12: =$CK$4*Supuestos!J12*Supuestos!$B$6 -> 771.64462 | CL12: =$CP$4*Supuestos!F12*Supuestos!$B$6 -> 486.64362 | CM12: =$CP$4*Supuestos!G12*Supuestos!$B$6 -> 1064.1188 | CN12: =$CP$4*Supuestos!H12*Supuestos!$B$6 -> 1283.7717 | CO12: =$CP$4*Supuestos!I12*Supuestos!$B$6 -> 1336.7078 | CP12: =$CU$4*Supuestos!J12*Supuestos!$B$6 -> 1114.007 | CQ12: =$CU$4*Supuestos!F12*Supuestos!$B$6 -> 540.17779 | CR12: =$CU$4*Supuestos!G12*Supuestos!$B$6 -> 1181.1793 | CS12: =$CU$4*Supuestos!H12*Supuestos!$B$6 -> 1424.9955 | CT12: =$CU$4*Supuestos!I12*Supuestos!$B$6 -> 1483.7549 | CU12: =$CU$4*Supuestos!J12*Supuestos!$B$6 -> 1114.007 | CV12: =CZ4*Supuestos!$F$12*Supuestos!$B$6 -> 515.84155 | CW12: =CZ4*Supuestos!$G$12*Supuestos!$B$6 -> 1127.9645 | CX12: =CZ4*Supuestos!$H$12*Supuestos!$B$6 -> 1360.7962 | CY12: =CZ4*Supuestos!$I$12*Supuestos!$B$6 -> 1416.9084 | CZ12: =CZ4*Supuestos!$J$12*Supuestos!$B$6 -> 1063.8185 | DA12: =DE4*Supuestos!$F$12*Supuestos!$B$6 -> 529.09194 | DB12: =DE4*Supuestos!$G$12*Supuestos!$B$6 -> 1156.9384 | DC12: =DE4*Supuestos!$H$12*Supuestos!$B$6 -> 1395.7509 | DD12: =DE4*Supuestos!$I$12*Supuestos!$B$6 -> 1453.3044 | DE12: =DE4*Supuestos!$J$12*Supuestos!$B$6 -> 1091.1447 | DF12: =DJ4*Supuestos!$F$12*Supuestos!$B$6 -> 497.61214 | DG12: =DJ4*Supuestos!$G$12*Supuestos!$B$6 -> 1088.1031 | DH12: =DJ4*Supuestos!$H$12*Supuestos!$B$6 -> 1312.7068 | DI12: =DJ4*Supuestos!$I$12*Supuestos!$B$6 -> 1366.836 | DJ12: =DJ4*Supuestos!$J$12*Supuestos!$B$6 -> 1026.224 | DK12: =DO4*Supuestos!$F$12*Supuestos!$B$6 -> 258.00633 | DL12: =DO4*Supuestos!$G$12*Supuestos!$B$6 -> 564.16932 | DM12: =DO4*Supuestos!$H$12*Supuestos!$B$6 -> 680.62381 | DN12: =DO4*Supuestos!$I$12*Supuestos!$B$6 -> 708.68921 | DO12: =DO4*Supuestos!$J$12*Supuestos!$B$6 -> 532.08569 | DP12: =DT4*Supuestos!$F$12*Supuestos!$B$6 -> 566.43939 | DQ12: =DT4*Supuestos!$G$12*Supuestos!$B$6 -> 1238.6042 | DR12: =DT4*Supuestos!$H$12*Supuestos!$B$6 -> 1494.2739 | DS12: =DT4*Supuestos!$I$12*Supuestos!$B$6 -> 1555.89 | DT12: =DT4*Supuestos!$J$12*Supuestos!$B$6 -> 1168.1663 | DU12: =DY4*Supuestos!$F$12*Supuestos!$B$6 -> 477.21181 | DV12: =DY4*Supuestos!$G$12*Supuestos!$B$6 -> 1043.4948 | DW12: =DY4*Supuestos!$H$12*Supuestos!$B$6 -> 1258.8905 | DX12: =DY4*Supuestos!$I$12*Supuestos!$B$6 -> 1310.8006 | DY12: =DY4*Supuestos!$J$12*Supuestos!$B$6 -> 984.1525 | DZ12: =ED4*Supuestos!$F$12*Supuestos!$B$6 -> 514.28377 | EA12: =ED4*Supuestos!$G$12*Supuestos!$B$6 -> 1124.5581 | EB12: =ED4*Supuestos!$H$12*Supuestos!$B$6 -> 1356.6868 | EC12: =ED4*Supuestos!$I$12*Supuestos!$B$6 -> 1412.6295 | ED12: =ED4*Supuestos!$J$12*Supuestos!$B$6 -> 1060.6059 | EE12: =EI4*Supuestos!$F$12*Supuestos!$B$6 -> 497.51158 | EF12: =EI4*Supuestos!$G$12*Supuestos!$B$6 -> 1087.8833 | EG12: =EI4*Supuestos!$H$12*Supuestos!$B$6 -> 1312.4415 | EH12: =EI4*Supuestos!$I$12*Supuestos!$B$6 -> 1366.5598 | EI12: =EI4*Supuestos!$J$12*Supuestos!$B$6 -> 1026.0166 | EJ12: =EN4*Supuestos!$F$12*Supuestos!$B$6 -> 563.30583 | EK12: =EN4*Supuestos!$G$12*Supuestos!$B$6 -> 1231.7522 | EL12: =EN4*Supuestos!$H$12*Supuestos!$B$6 -> 1486.0076 | EM12: =EN4*Supuestos!$I$12*Supuestos!$B$6 -> 1547.2828 | EN12: =EN4*Supuestos!$J$12*Supuestos!$B$6 -> 1161.7039 | EO12: =ES4*Supuestos!$F$12*Supuestos!$B$6 -> 437.77603 | EP12: =ES4*Supuestos!$G$12*Supuestos!$B$6 -> 957.26258 | EQ12: =ES4*Supuestos!$H$12*Supuestos!$B$6 -> 1154.8584 | ER12: =ES4*Supuestos!$I$12*Supuestos!$B$6 -> 1202.4788 | ES12: =ES4*Supuestos!$J$12*Supuestos!$B$6 -> 902.82421 | ET12: =EX4*Supuestos!$F$12*Supuestos!$B$6 -> 569.37304 | EU12: =EX4*Supuestos!$G$12*Supuestos!$B$6 -> 1245.0191 | EV12: =EX4*Supuestos!$H$12*Supuestos!$B$6 -> 1502.0129 | EW12: =EX4*Supuestos!$I$12*Supuestos!$B$6 -> 1563.9482 | EX12: =EX4*Supuestos!$J$12*Supuestos!$B$6 -> 1174.2163 | EY12: =FC4*Supuestos!$F$12*Supuestos!$B$6 -> 632.00801 | EZ12: =FC4*Supuestos!$G$12*Supuestos!$B$6 -> 1381.9798 | FA12: =FC4*Supuestos!$H$12*Supuestos!$B$6 -> 1667.2447 | FB12: =FC4*Supuestos!$I$12*Supuestos!$B$6 -> 1735.9933 | FC12: =FC4*Supuestos!$J$12*Supuestos!$B$6 -> 1303.3882 | FD12: =FH4*Supuestos!$F$12*Supuestos!$B$6 -> 603.53461 | FE12: =FH4*Supuestos!$G$12*Supuestos!$B$6 -> 1319.7184 | FF12: =FH4*Supuestos!$H$12*Supuestos!$B$6 -> 1592.1316 | FG12: =FH4*Supuestos!$I$12*Supuestos!$B$6 -> 1657.7828 | FH12: =FH4*Supuestos!$J$12*Supuestos!$B$6 -> 1244.6676 | FI12: =FM4*Supuestos!$F$12*Supuestos!$B$6 -> 619.03757 | FJ12: =FM4*Supuestos!$G$12*Supuestos!$B$6 -> 1353.618 | FK12: =FM4*Supuestos!$H$12*Supuestos!$B$6 -> 1633.0286 | FL12: =FM4*Supuestos!$I$12*Supuestos!$B$6 -> 1700.3662 | FM12: =FM4*Supuestos!$J$12*Supuestos!$B$6 -> 1276.6393 | FN12: =FR4*Supuestos!$F$12*Supuestos!$B$6 -> 582.2062 | FO12: =FR4*Supuestos!$G$12*Supuestos!$B$6 -> 1273.0807 | FP12: =FR4*Supuestos!$H$12*Supuestos!$B$6 -> 1535.867 | FQ12: =FR4*Supuestos!$I$12*Supuestos!$B$6 -> 1599.1982 | FR12: =FR4*Supuestos!$J$12*Supuestos!$B$6 -> 1200.6821 | FS12: =FW4*Supuestos!$F$12*Supuestos!$B$6 -> 301.86741 | FT12: =FW4*Supuestos!$G$12*Supuestos!$B$6 -> 660.0781 | FU12: =FW4*Supuestos!$H$12*Supuestos!$B$6 -> 796.32986 | FV12: =FW4*Supuestos!$I$12*Supuestos!$B$6 -> 829.16637 | FW12: =FW4*Supuestos!$J$12*Supuestos!$B$6 -> 622.54026 | FX12: =GB4*Supuestos!$F$12*Supuestos!$B$6 -> 659.90189 | FY12: =GB4*Supuestos!$G$12*Supuestos!$B$6 -> 1442.9739 | FZ12: =GB4*Supuestos!$H$12*Supuestos!$B$6 -> 1740.8291 | GA12: =GB4*Supuestos!$I$12*Supuestos!$B$6 -> 1812.6119 | GB12: =GB4*Supuestos!$J$12*Supuestos!$B$6 -> 1360.9137 | GC12: =GF4*Supuestos!$F$13*Supuestos!$B$6 -> 707.09197 | GD12: =GF4*Supuestos!$G$13*Supuestos!$B$6 -> 1084.8781 | GE12: =GF4*Supuestos!$H$13*Supuestos!$B$6 -> 1388.1103 | GF12: =GF4*Supuestos!$I$13*Supuestos!$B$6 -> 2731.7707 | GG12: =GK4*Supuestos!$F$12*Supuestos!$B$6 -> 599.14059 | GH12: =GK4*Supuestos!$G$12*Supuestos!$B$6 -> 1310.1102 | GI12: =GK4*Supuestos!$H$12*Supuestos!$B$6 -> 1580.5401 | GJ12: =GK4*Supuestos!$I$12*Supuestos!$B$6 -> 1645.7134 | GK12: =GK4*Supuestos!$J$12*Supuestos!$B$6 -> 1235.6059 | GL12: =GP4*Supuestos!$F$12*Supuestos!$B$6 -> 579.60099 | GM12: =GP4*Supuestos!$G$12*Supuestos!$B$6 -> 1267.384 | GN12: =GP4*Supuestos!$H$12*Supuestos!$B$6 -> 1528.9944 | GO12: =GP4*Supuestos!$I$12*Supuestos!$B$6 -> 1592.0422 | GP12: =GP4*Supuestos!$J$12*Supuestos!$B$6 -> 1195.3094 | GQ12: =GU4*Supuestos!$F$12*Supuestos!$B$6 -> 656.25129 | GR12: =GU4*Supuestos!$G$12*Supuestos!$B$6 -> 1434.9913 | GS12: =GU4*Supuestos!$H$12*Supuestos!$B$6 -> 1731.1988 | GT12: =GU4*Supuestos!$I$12*Supuestos!$B$6 -> 1802.5845 | GU12: =GU4*Supuestos!$J$12*Supuestos!$B$6 -> 1353.3851 | GV12: =GZ4*Supuestos!$F$12*Supuestos!$B$6 -> 510.00908 | GW12: =GZ4*Supuestos!$G$12*Supuestos!$B$6 -> 1115.2109 | GX12: =GZ4*Supuestos!$H$12*Supuestos!$B$6 -> 1345.4101 | GY12: =GZ4*Supuestos!$I$12*Supuestos!$B$6 -> 1400.8878 | GZ12: =GZ4*Supuestos!$J$12*Supuestos!$B$6 -> 1051.7902 | HA12: =HE4*Supuestos!$F$12*Supuestos!$B$6 -> 663.31959 | HB12: =HE4*Supuestos!$G$12*Supuestos!$B$6 -> 1450.4472 | HC12: =HE4*Supuestos!$H$12*Supuestos!$B$6 -> 1749.8451 | HD12: =HE4*Supuestos!$I$12*Supuestos!$B$6 -> 1821.9996 | HE12: =HE4*Supuestos!$J$12*Supuestos!$B$6 -> 1367.962 | HF12: =HJ4*Supuestos!$F$12*Supuestos!$B$6 -> 736.28933 | HG12: =HJ4*Supuestos!$G$12*Supuestos!$B$6 -> 1610.0064 | HH12: =HJ4*Supuestos!$H$12*Supuestos!$B$6 -> 1942.3401 | HI12: =HJ4*Supuestos!$I$12*Supuestos!$B$6 -> 2022.4322 | HJ12: =HJ4*Supuestos!$J$12*Supuestos!$B$6 -> 1518.4473 | HK12: =HO4*Supuestos!$F$12*Supuestos!$B$6 -> 703.11782 | HL12: =HO4*Supuestos!$G$12*Supuestos!$B$6 -> 1537.472 | HM12: =HO4*Supuestos!$H$12*Supuestos!$B$6 -> 1854.8333 | HN12: =HO4*Supuestos!$I$12*Supuestos!$B$6 -> 1931.317 | HO12: =HO4*Supuestos!$J$12*Supuestos!$B$6 -> 1450.0378 | HP12: =HT4*Supuestos!$F$12*Supuestos!$B$6 -> 721.17877 | HQ12: =HT4*Supuestos!$G$12*Supuestos!$B$6 -> 1576.9649 | HR12: =HT4*Supuestos!$H$12*Supuestos!$B$6 -> 1902.4783 | HS12: =HT4*Supuestos!$I$12*Supuestos!$B$6 -> 1980.9266 | HT12: =HT4*Supuestos!$J$12*Supuestos!$B$6 -> 1487.2848 | HU12: =HY4*Supuestos!$F$12*Supuestos!$B$6 -> 678.27023 | HV12: =HY4*Supuestos!$G$12*Supuestos!$B$6 -> 1483.139 | HW12: =HY4*Supuestos!$H$12*Supuestos!$B$6 -> 1789.285 | HX12: =HY4*Supuestos!$I$12*Supuestos!$B$6 -> 1863.0659 | HY12: =HY4*Supuestos!$J$12*Supuestos!$B$6 -> 1398.7947 | HZ12: =ID4*Supuestos!$F$12*Supuestos!$B$6 -> 351.67553 | IA12: =ID4*Supuestos!$G$12*Supuestos!$B$6 -> 768.99099 | IB12: =ID4*Supuestos!$H$12*Supuestos!$B$6 -> 927.72428 | IC12: =ID4*Supuestos!$I$12*Supuestos!$B$6 -> 965.97882 | ID12: =ID4*Supuestos!$J$12*Supuestos!$B$6 -> 725.2594 | IE12: =II4*Supuestos!$F$12*Supuestos!$B$6 -> 765.4862 | IF12: =II4*Supuestos!$G$12*Supuestos!$B$6 -> 1673.8497 | IG12: =II4*Supuestos!$H$12*Supuestos!$B$6 -> 2019.3618 | IH12: =II4*Supuestos!$I$12*Supuestos!$B$6 -> 2102.6298 | II12: =II4*Supuestos!$J$12*Supuestos!$B$6 -> 1578.6599 | IJ12: =IM4*Supuestos!$F$13*Supuestos!$B$6 -> 820.22668 | IK12: =IM4*Supuestos!$G$13*Supuestos!$B$6 -> 1258.4586 | IL12: =IM4*Supuestos!$H$13*Supuestos!$B$6 -> 1610.2079 | IM12: =IM4*Supuestos!$I$13*Supuestos!$B$6 -> 3168.854 | IN12: =IR4*Supuestos!$F$12*Supuestos!$B$6 -> 695.00309 | IO12: =IR4*Supuestos!$G$12*Supuestos!$B$6 -> 1519.7279 | IP12: =IR4*Supuestos!$H$12*Supuestos!$B$6 -> 1833.4265 | IQ12: =IR4*Supuestos!$I$12*Supuestos!$B$6 -> 1909.0275 | IR12: =IR4*Supuestos!$J$12*Supuestos!$B$6 -> 1433.3028 | IS12: =IW4*Supuestos!$F$12*Supuestos!$B$6 -> 672.33715 | IT12: =IW4*Supuestos!$G$12*Supuestos!$B$6 -> 1470.1654 | IU12: =IW4*Supuestos!$H$12*Supuestos!$B$6 -> 1773.6335 | IV12: =IW4*Supuestos!$I$12*Supuestos!$B$6 -> 1846.7689 | IW12: =IW4*Supuestos!$J$12*Supuestos!$B$6 -> 1386.5589 | IX12: =JB4*Supuestos!$F$12*Supuestos!$B$6 -> 761.2515 | IY12: =JB4*Supuestos!$G$12*Supuestos!$B$6 -> 1664.5899 | IZ12: =JB4*Supuestos!$H$12*Supuestos!$B$6 -> 2008.1906 | JA12: =JB4*Supuestos!$I$12*Supuestos!$B$6 -> 2090.998 | JB12: =JB4*Supuestos!$J$12*Supuestos!$B$6 -> 1569.9267 | JC12: =JG4*Supuestos!$F$12*Supuestos!$B$6 -> 591.61053 | JD12: =JG4*Supuestos!$G$12*Supuestos!$B$6 -> 1293.6446 | JE12: =JG4*Supuestos!$H$12*Supuestos!$B$6 -> 1560.6757 | JF12: =JG4*Supuestos!$I$12*Supuestos!$B$6 -> 1625.0299 | JG12: =JG4*Supuestos!$J$12*Supuestos!$B$6 -> 1220.0766 | JH12: =JL4*Supuestos!$F$12*Supuestos!$B$6 -> 769.45072 | JI12: =JL4*Supuestos!$G$12*Supuestos!$B$6 -> 1682.5187 | JJ12: =JL4*Supuestos!$H$12*Supuestos!$B$6 -> 2029.8203 | JK12: =JL4*Supuestos!$I$12*Supuestos!$B$6 -> 2113.5195 | JL12: =JL4*Supuestos!$J$12*Supuestos!$B$6 -> 1586.8359 | JM12: =JQ4*Supuestos!$F$12*Supuestos!$B$6 -> 854.09563 | JN12: =JQ4*Supuestos!$G$12*Supuestos!$B$6 -> 1867.6074 | JO12: =JQ4*Supuestos!$H$12*Supuestos!$B$6 -> 2253.1145 | JP12: =JQ4*Supuestos!$I$12*Supuestos!$B$6 -> 2346.0213 | JQ12: =JQ4*Supuestos!$J$12*Supuestos!$B$6 -> 1761.3989 | JR12: =JV4*Supuestos!$F$12*Supuestos!$B$6 -> 815.61667 | JS12: =JV4*Supuestos!$G$12*Supuestos!$B$6 -> 1783.4675 | JT12: =JV4*Supuestos!$H$12*Supuestos!$B$6 -> 2151.6066 | JU12: =JV4*Supuestos!$I$12*Supuestos!$B$6 -> 2240.3277 | JV12: =JV4*Supuestos!$J$12*Supuestos!$B$6 -> 1682.0438 | JW12: =KA4*Supuestos!$F$12*Supuestos!$B$6 -> 836.56737 | JX12: =KA4*Supuestos!$G$12*Supuestos!$B$6 -> 1829.2793 | JY12: =KA4*Supuestos!$H$12*Supuestos!$B$6 -> 2206.8748 | JZ12: =KA4*Supuestos!$I$12*Supuestos!$B$6 -> 2297.8749 | KA12: =KA4*Supuestos!$J$12*Supuestos!$B$6 -> 1725.2504 | KB12: =KF4*Supuestos!$F$12*Supuestos!$B$6 -> 786.79346 | KC12: =KF4*Supuestos!$G$12*Supuestos!$B$6 -> 1720.4412 | KD12: =KF4*Supuestos!$H$12*Supuestos!$B$6 -> 2075.5706 | KE12: =KF4*Supuestos!$I$12*Supuestos!$B$6 -> 2161.1564 | KF12: =KF4*Supuestos!$J$12*Supuestos!$B$6 -> 1622.6018 | KG12: =KK4*Supuestos!$F$12*Supuestos!$B$6 -> 407.94362 | KH12: =KK4*Supuestos!$G$12*Supuestos!$B$6 -> 892.02955 | KI12: =KK4*Supuestos!$H$12*Supuestos!$B$6 -> 1076.1602 | KJ12: =KK4*Supuestos!$I$12*Supuestos!$B$6 -> 1120.5354 | KK12: =KK4*Supuestos!$J$12*Supuestos!$B$6 -> 841.3009 | KL12: =KP4*Supuestos!$F$12*Supuestos!$B$6 -> 884.13656 | KM12: =KP4*Supuestos!$G$12*Supuestos!$B$6 -> 1933.2964 | KN12: =KP4*Supuestos!$H$12*Supuestos!$B$6 -> 2332.3629 | KO12: =KP4*Supuestos!$I$12*Supuestos!$B$6 -> 2428.5374 | KP12: =KP4*Supuestos!$J$12*Supuestos!$B$6 -> 1823.3522 | KQ12: =KT4*Supuestos!$F$13*Supuestos!$B$6 -> 947.36182 | KR12: =KT4*Supuestos!$G$13*Supuestos!$B$6 -> 1453.5197 | KS12: =KT4*Supuestos!$H$13*Supuestos!$B$6 -> 1859.7901 | KT12: =KT4*Supuestos!$I$13*Supuestos!$B$6 -> 3660.0263 | KU12: =KY4*Supuestos!$F$12*Supuestos!$B$6 -> 802.72856 | KV12: =KY4*Supuestos!$G$12*Supuestos!$B$6 -> 1755.2857 | KW12: =KY4*Supuestos!$H$12*Supuestos!$B$6 -> 2117.6076 | KX12: =KY4*Supuestos!$I$12*Supuestos!$B$6 -> 2204.9268 | KY12: =KY4*Supuestos!$J$12*Supuestos!$B$6 -> 1655.4647 | KZ12: =LD4*Supuestos!$F$12*Supuestos!$B$6 -> 776.54941 | LA12: =LD4*Supuestos!$G$12*Supuestos!$B$6 -> 1698.0411 | LB12: =LD4*Supuestos!$H$12*Supuestos!$B$6 -> 2048.5467 | LC12: =LD4*Supuestos!$I$12*Supuestos!$B$6 -> 2133.0181 | LD12: =LD4*Supuestos!$J$12*Supuestos!$B$6 -> 1601.4755 | LE12: =LI4*Supuestos!$F$12*Supuestos!$B$6 -> 879.24548 | LF12: =LI4*Supuestos!$G$12*Supuestos!$B$6 -> 1922.6014 | LG12: =LI4*Supuestos!$H$12*Supuestos!$B$6 -> 2319.4602 | LH12: =LI4*Supuestos!$I$12*Supuestos!$B$6 -> 2415.1027 | LI12: =LI4*Supuestos!$J$12*Supuestos!$B$6 -> 1813.2653 | LJ12: =LN4*Supuestos!$F$12*Supuestos!$B$6 -> 683.31016 | LK12: =LN4*Supuestos!$G$12*Supuestos!$B$6 -> 1494.1596 | LL12: =LN4*Supuestos!$H$12*Supuestos!$B$6 -> 1802.5804 | LM12: =LN4*Supuestos!$I$12*Supuestos!$B$6 -> 1876.9095 | LN12: =LN4*Supuestos!$J$12*Supuestos!$B$6 -> 1409.1885 | LO12: =LS4*Supuestos!$F$12*Supuestos!$B$6 -> 888.71559 | LP12: =LS4*Supuestos!$G$12*Supuestos!$B$6 -> 1943.3092 | LQ12: =LS4*Supuestos!$H$12*Supuestos!$B$6 -> 2344.4424 | LR12: =LS4*Supuestos!$I$12*Supuestos!$B$6 -> 2441.1151 | LS12: =LS4*Supuestos!$J$12*Supuestos!$B$6 -> 1832.7955 | LT12: =LX4*Supuestos!$F$12*Supuestos!$B$6 -> 986.48045 | LU12: =LX4*Supuestos!$G$12*Supuestos!$B$6 -> 2157.0866 | LV12: =LX4*Supuestos!$H$12*Supuestos!$B$6 -> 2602.3473 | LW12: =LX4*Supuestos!$I$12*Supuestos!$B$6 -> 2709.6546 | LX12: =LX4*Supuestos!$J$12*Supuestos!$B$6 -> 2034.4157 | LY12: =MC4*Supuestos!$F$12*Supuestos!$B$6 -> 942.03726 | LZ12: =MC4*Supuestos!$G$12*Supuestos!$B$6 -> 2059.9049 | MA12: =MC4*Supuestos!$H$12*Supuestos!$B$6 -> 2485.1056 | MB12: =MC4*Supuestos!$I$12*Supuestos!$B$6 -> 2587.5785 | MC12: =MC4*Supuestos!$J$12*Supuestos!$B$6 -> 1942.7606 | MD12: =MH4*Supuestos!$F$12*Supuestos!$B$6 -> 966.23532 | ME12: =MH4*Supuestos!$G$12*Supuestos!$B$6 -> 2112.8176 | MF12: =MH4*Supuestos!$H$12*Supuestos!$B$6 -> 2548.9404 | MG12: =MH4*Supuestos!$I$12*Supuestos!$B$6 -> 2654.0455 | MH12: =MH4*Supuestos!$J$12*Supuestos!$B$6 -> 1992.6642 | MI12: =MM4*Supuestos!$F$12*Supuestos!$B$6 -> 908.74645 | MJ12: =MM4*Supuestos!$G$12*Supuestos!$B$6 -> 1987.1096 | MK12: =MM4*Supuestos!$H$12*Supuestos!$B$6 -> 2397.2841 | ML12: =MM4*Supuestos!$I$12*Supuestos!$B$6 -> 2496.1356 | MM12: =MM4*Supuestos!$J$12*Supuestos!$B$6 -> 1874.1051 | MN12: =MR4*Supuestos!$F$12*Supuestos!$B$6 -> 471.17488 | MO12: =MR4*Supuestos!$G$12*Supuestos!$B$6 -> 1030.2941 | MP12: =MR4*Supuestos!$H$12*Supuestos!$B$6 -> 1242.965 | MQ12: =MR4*Supuestos!$I$12*Supuestos!$B$6 -> 1294.2184 | MR12: =MR4*Supuestos!$J$12*Supuestos!$B$6 -> 971.70254 | MS12: =MW4*Supuestos!$F$12*Supuestos!$B$6 -> 1007.9157 | MT12: =MW4*Supuestos!$G$12*Supuestos!$B$6 -> 2203.9579 | MU12: =MW4*Supuestos!$H$12*Supuestos!$B$6 -> 2658.8937 | MV12: =MW4*Supuestos!$I$12*Supuestos!$B$6 -> 2768.5327 | MW12: =MW4*Supuestos!$J$12*Supuestos!$B$6 -> 2078.6215 | MX12: =NB4*Supuestos!$F$12*Supuestos!$B$6 -> 849.14515 | MY12: =NB4*Supuestos!$G$12*Supuestos!$B$6 -> 1856.7825 | MZ12: =NB4*Supuestos!$H$12*Supuestos!$B$6 -> 2240.0551 | NA12: =NB4*Supuestos!$I$12*Supuestos!$B$6 -> 2332.4234 | NB12: =NB4*Supuestos!$J$12*Supuestos!$B$6 -> 1751.1895 | NC12: =NG4*Supuestos!$F$12*Supuestos!$B$6 -> 915.11056 | ND12: =NG4*Supuestos!$G$12*Supuestos!$B$6 -> 2001.0257 | NE12: =NG4*Supuestos!$H$12*Supuestos!$B$6 -> 2414.0727 | NF12: =NG4*Supuestos!$I$12*Supuestos!$B$6 -> 2513.6165 | NG12: =NG4*Supuestos!$J$12*Supuestos!$B$6 -> 1887.2298 | NH12: =NL4*Supuestos!$F$12*Supuestos!$B$6 -> 885.26632 | NI12: =NL4*Supuestos!$G$12*Supuestos!$B$6 -> 1935.7668 | NJ12: =NL4*Supuestos!$H$12*Supuestos!$B$6 -> 2335.3432 | NK12: =NL4*Supuestos!$I$12*Supuestos!$B$6 -> 2431.6407 | NL12: =NL4*Supuestos!$J$12*Supuestos!$B$6 -> 1825.6821 | NM12: =NQ4*Supuestos!$F$12*Supuestos!$B$6 -> 1002.3398 | NN12: =NQ4*Supuestos!$G$12*Supuestos!$B$6 -> 2191.7655 | NO12: =NQ4*Supuestos!$H$12*Supuestos!$B$6 -> 2644.1846 | NP12: =NQ4*Supuestos!$I$12*Supuestos!$B$6 -> 2753.2171 | NQ12: =NQ4*Supuestos!$J$12*Supuestos!$B$6 -> 2067.1225 | NR12: =NV4*Supuestos!$F$12*Supuestos!$B$6 -> 778.97359 | NS12: =NV4*Supuestos!$G$12*Supuestos!$B$6 -> 1703.3419 | NT12: =NV4*Supuestos!$H$12*Supuestos!$B$6 -> 2054.9417 | NU12: =NV4*Supuestos!$I$12*Supuestos!$B$6 -> 2139.6768 | NV12: =NV4*Supuestos!$J$12*Supuestos!$B$6 -> 1606.4749 | NW12: =OA4*Supuestos!$F$12*Supuestos!$B$6 -> 1013.1358 | NX12: =OA4*Supuestos!$G$12*Supuestos!$B$6 -> 2215.3724 | NY12: =OA4*Supuestos!$H$12*Supuestos!$B$6 -> 2672.6644 | NZ12: =OA4*Supuestos!$I$12*Supuestos!$B$6 -> 2782.8712 | OA12: =OA4*Supuestos!$J$12*Supuestos!$B$6 -> 2089.3869 | OB12: =OF4*Supuestos!$F$12*Supuestos!$B$6 -> 1124.5877 | OC12: =OF4*Supuestos!$G$12*Supuestos!$B$6 -> 2459.0787 | OD12: =OF4*Supuestos!$H$12*Supuestos!$B$6 -> 2966.6759 | OE12: =OF4*Supuestos!$I$12*Supuestos!$B$6 -> 3089.0063 | OF12: =OF4*Supuestos!$J$12*Supuestos!$B$6 -> 2319.2339 | OG12: =OK4*Supuestos!$F$12*Supuestos!$B$6 -> 1073.9225 | OH12: =OK4*Supuestos!$G$12*Supuestos!$B$6 -> 2348.2916 | OI12: =OK4*Supuestos!$H$12*Supuestos!$B$6 -> 2833.0204 | OJ12: =OK4*Supuestos!$I$12*Supuestos!$B$6 -> 2949.8395 | OK12: =OK4*Supuestos!$J$12*Supuestos!$B$6 -> 2214.7471 | OL12: =OP4*Supuestos!$F$12*Supuestos!$B$6 -> 1101.5083 | OM12: =OP4*Supuestos!$G$12*Supuestos!$B$6 -> 2408.6121 | ON12: =OP4*Supuestos!$H$12*Supuestos!$B$6 -> 2905.7921 | OO12: =OP4*Supuestos!$I$12*Supuestos!$B$6 -> 3025.6118 | OP12: =OP4*Supuestos!$J$12*Supuestos!$B$6 -> 2271.6372 | OQ12: =OU4*Supuestos!$F$12*Supuestos!$B$6 -> 1035.971 | OR12: =OU4*Supuestos!$G$12*Supuestos!$B$6 -> 2265.305 | OS12: =OU4*Supuestos!$H$12*Supuestos!$B$6 -> 2732.9038 | OT12: =OU4*Supuestos!$I$12*Supuestos!$B$6 -> 2845.5946 | OU12: =OU4*Supuestos!$J$12*Supuestos!$B$6 -> 2136.4798 | OV12: =OZ4*Supuestos!$F$12*Supuestos!$B$6 -> 537.13936 | OW12: =OZ4*Supuestos!$G$12*Supuestos!$B$6 -> 1174.5353 | OX12: =OZ4*Supuestos!$H$12*Supuestos!$B$6 -> 1416.9801 | OY12: =OZ4*Supuestos!$I$12*Supuestos!$B$6 -> 1475.409 | OZ12: =OZ4*Supuestos!$J$12*Supuestos!$B$6 -> 1107.7409 | PA12: =PE4*Supuestos!$F$12*Supuestos!$B$6 -> 1149.0239 | PB12: =PE4*Supuestos!$G$12*Supuestos!$B$6 -> 2512.512 | PC12: =PE4*Supuestos!$H$12*Supuestos!$B$6 -> 3031.1388 | PD12: =PE4*Supuestos!$I$12*Supuestos!$B$6 -> 3156.1272 | PE12: =PE4*Supuestos!$J$12*Supuestos!$B$6 -> 2369.6285 | PF12: =PI4*Supuestos!$F$13*Supuestos!$B$6 -> 1231.1914 | PG12: =PI4*Supuestos!$G$13*Supuestos!$B$6 -> 1888.9942 | PH12: =PI4*Supuestos!$H$13*Supuestos!$B$6 -> 2416.9833 | PI12: =PI4*Supuestos!$I$13*Supuestos!$B$6 -> 4756.5702 | PJ12: =PN4*Supuestos!$F$12*Supuestos!$B$6 -> 1043.226 | PK12: =PN4*Supuestos!$G$12*Supuestos!$B$6 -> 2281.1693 | PL12: =PN4*Supuestos!$H$12*Supuestos!$B$6 -> 2752.0429 | PM12: =PN4*Supuestos!$I$12*Supuestos!$B$6 -> 2865.5228 | PN12: =PN4*Supuestos!$J$12*Supuestos!$B$6 -> 2151.442 | PO12: =PS4*Supuestos!$F$12*Supuestos!$B$6 -> 1009.2036 | PP12: =PS4*Supuestos!$G$12*Supuestos!$B$6 -> 2206.7742 | PQ12: =PS4*Supuestos!$H$12*Supuestos!$B$6 -> 2662.2913 | PR12: =PS4*Supuestos!$I$12*Supuestos!$B$6 -> 2772.0704 | PS12: =PS4*Supuestos!$J$12*Supuestos!$B$6 -> 2081.2776 | PT12: =PX4*Supuestos!$F$12*Supuestos!$B$6 -> 1142.6674 | PU12: =PX4*Supuestos!$G$12*Supuestos!$B$6 -> 2498.6127 | PV12: =PX4*Supuestos!$H$12*Supuestos!$B$6 -> 3014.3704 | PW12: =PX4*Supuestos!$I$12*Supuestos!$B$6 -> 3138.6674 | PX12: =PX4*Supuestos!$J$12*Supuestos!$B$6 -> 2356.5196 | PY12: =QC4*Supuestos!$F$12*Supuestos!$B$6 -> 888.02989 | PZ12: =QC4*Supuestos!$G$12*Supuestos!$B$6 -> 1941.8098 | QA12: =QC4*Supuestos!$H$12*Supuestos!$B$6 -> 2342.6335 | QB12: =QC4*Supuestos!$I$12*Supuestos!$B$6 -> 2439.2316 | QC12: =QC4*Supuestos!$J$12*Supuestos!$B$6 -> 1831.3814 | QD12: =QH4*Supuestos!$F$12*Supuestos!$B$6 -> 1154.9748 | QE12: =QH4*Supuestos!$G$12*Supuestos!$B$6 -> 2525.5246 | QF12: =QH4*Supuestos!$H$12*Supuestos!$B$6 -> 3046.8374 | QG12: =QH4*Supuestos!$I$12*Supuestos!$B$6 -> 3172.4731 | QH12: =QH4*Supuestos!$J$12*Supuestos!$B$6 -> 2381.901 | QI12: =QM4*Supuestos!$F$12*Supuestos!$B$6 -> 1282.03 | QJ12: =QM4*Supuestos!$G$12*Supuestos!$B$6 -> 2803.3497 | QK12: =QM4*Supuestos!$H$12*Supuestos!$B$6 -> 3382.0106 | QL12: =QM4*Supuestos!$I$12*Supuestos!$B$6 -> 3521.4671 | QM12: =QM4*Supuestos!$J$12*Supuestos!$B$6 -> 2643.9266 | QN12: =QR4*Supuestos!$F$12*Supuestos!$B$6 -> 1224.2716 | QO12: =QR4*Supuestos!$G$12*Supuestos!$B$6 -> 2677.0525 | QP12: =QR4*Supuestos!$H$12*Supuestos!$B$6 -> 3229.6433 | QQ12: =QR4*Supuestos!$I$12*Supuestos!$B$6 -> 3362.817 | QR12: =QR4*Supuestos!$J$12*Supuestos!$B$6 -> 2524.8117 | QS12: =QW4*Supuestos!$F$12*Supuestos!$B$6 -> 1255.7194 | QT12: =QW4*Supuestos!$G$12*Supuestos!$B$6 -> 2745.8178 | QU12: =QW4*Supuestos!$H$12*Supuestos!$B$6 -> 3312.6029 | QV12: =QW4*Supuestos!$I$12*Supuestos!$B$6 -> 3449.1975 | QW12: =QW4*Supuestos!$J$12*Supuestos!$B$6 -> 2589.6664 | QX12: =RB4*Supuestos!$F$12*Supuestos!$B$6 -> 1181.0069 | QY12: =RB4*Supuestos!$G$12*Supuestos!$B$6 -> 2582.4477 | QZ12: =RB4*Supuestos!$H$12*Supuestos!$B$6 -> 3115.5104 | RA12: =RB4*Supuestos!$I$12*Supuestos!$B$6 -> 3243.9779 | RB12: =RB4*Supuestos!$J$12*Supuestos!$B$6 -> 2435.587 | RC12: =RG4*Supuestos!$F$12*Supuestos!$B$6 -> 612.33887 | RD12: =RG4*Supuestos!$G$12*Supuestos!$B$6 -> 1338.9702 | RE12: =RG4*Supuestos!$H$12*Supuestos!$B$6 -> 1615.3573 | RF12: =RG4*Supuestos!$I$12*Supuestos!$B$6 -> 1681.9663 | RG12: =RG4*Supuestos!$J$12*Supuestos!$B$6 -> 1262.8246 | RH12: =RL4*Supuestos!$F$12*Supuestos!$B$6 -> 1309.8872 | RI12: =RL4*Supuestos!$G$12*Supuestos!$B$6 -> 2864.2637 | RJ12: =RL4*Supuestos!$H$12*Supuestos!$B$6 -> 3455.4982 | RK12: =RL4*Supuestos!$I$12*Supuestos!$B$6 -> 3597.9851 | RL12: =RL4*Supuestos!$J$12*Supuestos!$B$6 -> 2701.3765 | RM12: =RP4*Supuestos!$F$13*Supuestos!$B$6 -> 1403.5582 | RN12: =RP4*Supuestos!$G$13*Supuestos!$B$6 -> 2153.4534 | RO12: =RP4*Supuestos!$H$13*Supuestos!$B$6 -> 2755.3609 | RP12: =RP4*Supuestos!$I$13*Supuestos!$B$6 -> 5422.4901 | RQ12: =RU4*Supuestos!$F$12*Supuestos!$B$6 -> 1189.2777 | RR12: =RU4*Supuestos!$G$12*Supuestos!$B$6 -> 2600.533 | RS12: =RU4*Supuestos!$H$12*Supuestos!$B$6 -> 3137.3289 | RT12: =RU4*Supuestos!$I$12*Supuestos!$B$6 -> 3266.696 | RU12: =RU4*Supuestos!$J$12*Supuestos!$B$6 -> 2452.6438 | RV12: =RZ4*Supuestos!$F$12*Supuestos!$B$6 -> 1150.4921 | RW12: =RZ4*Supuestos!$G$12*Supuestos!$B$6 -> 2515.7226 | RX12: =RZ4*Supuestos!$H$12*Supuestos!$B$6 -> 3035.012 | RY12: =RZ4*Supuestos!$I$12*Supuestos!$B$6 -> 3160.1602 | RZ12: =RZ4*Supuestos!$J$12*Supuestos!$B$6 -> 2372.6565 | SA12: =SE4*Supuestos!$F$12*Supuestos!$B$6 -> 1302.6409 | SB12: =SE4*Supuestos!$G$12*Supuestos!$B$6 -> 2848.4185 | SC12: =SE4*Supuestos!$H$12*Supuestos!$B$6 -> 3436.3823 | SD12: =SE4*Supuestos!$I$12*Supuestos!$B$6 -> 3578.0809 | SE12: =SE4*Supuestos!$J$12*Supuestos!$B$6 -> 2686.4324 | SF12: =SJ4*Supuestos!$F$12*Supuestos!$B$6 -> 1012.3541 | SG12: =SJ4*Supuestos!$G$12*Supuestos!$B$6 -> 2213.6631 | SH12: =SJ4*Supuestos!$H$12*Supuestos!$B$6 -> 2670.6022 | SI12: =SJ4*Supuestos!$I$12*Supuestos!$B$6 -> 2780.724 | SJ12: =SJ4*Supuestos!$J$12*Supuestos!$B$6 -> 2087.7748 | SK12: =SO4*Supuestos!$F$12*Supuestos!$B$6 -> 1316.6712 | SL12: =SO4*Supuestos!$G$12*Supuestos!$B$6 -> 2879.098 | SM12: =SO4*Supuestos!$H$12*Supuestos!$B$6 -> 3473.3946 | SN12: =SO4*Supuestos!$I$12*Supuestos!$B$6 -> 3616.6194 | SO12: =SO4*Supuestos!$J$12*Supuestos!$B$6 -> 2715.3672 | SP12: =ST4*Supuestos!$F$12*Supuestos!$B$6 -> 1461.5142 | SQ12: =ST4*Supuestos!$G$12*Supuestos!$B$6 -> 3195.8187 | SR12: =ST4*Supuestos!$H$12*Supuestos!$B$6 -> 3855.492 | SS12: =ST4*Supuestos!$I$12*Supuestos!$B$6 -> 4014.4725 | ST12: =ST4*Supuestos!$J$12*Supuestos!$B$6 -> 3014.0764 | SU12: =SY4*Supuestos!$F$12*Supuestos!$B$6 -> 1395.6696 | SV12: =SY4*Supuestos!$G$12*Supuestos!$B$6 -> 3051.8398 | SW12: =SY4*Supuestos!$H$12*Supuestos!$B$6 -> 3681.7933 | SX12: =SY4*Supuestos!$I$12*Supuestos!$B$6 -> 3833.6114 | SY12: =SY4*Supuestos!$J$12*Supuestos!$B$6 -> 2878.2853 | SZ12: =TD4*Supuestos!$F$12*Supuestos!$B$6 -> 1431.5201 | TA12: =TD4*Supuestos!$G$12*Supuestos!$B$6 -> 3130.2322 | TB12: =TD4*Supuestos!$H$12*Supuestos!$B$6 -> 3776.3674 | TC12: =TD4*Supuestos!$I$12*Supuestos!$B$6 -> 3932.0852 | TD12: =TD4*Supuestos!$J$12*Supuestos!$B$6 -> 2952.2197 | TE12: =TI4*Supuestos!$F$12*Supuestos!$B$6 -> 1346.3478 | TF12: =TI4*Supuestos!$G$12*Supuestos!$B$6 -> 2943.9903 | TG12: =TI4*Supuestos!$H$12*Supuestos!$B$6 -> 3551.6818 | TH12: =TI4*Supuestos!$I$12*Supuestos!$B$6 -> 3698.1348 | TI12: =TI4*Supuestos!$J$12*Supuestos!$B$6 -> 2776.5692 | TJ12: =TN4*Supuestos!$F$12*Supuestos!$B$6 -> 698.06631 | TK12: =TN4*Supuestos!$G$12*Supuestos!$B$6 -> 1526.4261 | TL12: =TN4*Supuestos!$H$12*Supuestos!$B$6 -> 1841.5073 | TM12: =TN4*Supuestos!$I$12*Supuestos!$B$6 -> 1917.4415 | TN12: =TN4*Supuestos!$J$12*Supuestos!$B$6 -> 1439.6201
A13: En descuento | C13: =B12*Supuestos!$B$12 -> 125.40491 | D13: =C12*Supuestos!$B$12 -> 554.27778 | E13: =D12*Supuestos!$B$12 -> 321.48079 | F13: =E12*Supuestos!$B$12 -> 566.88351 | G13: =F12*Supuestos!$B$12 -> 400.95932 | H13: =G12*Supuestos!$B$12 -> 257.44561 | I13: =H12*Supuestos!$B$12 -> 309.16133 | J13: =I12*Supuestos!$B$12 -> 492.9318 | ... TN13: =TM12*Supuestos!$B$12 -> 882.02311
